Workbook

Sheet README
A1: Veloop Data Dictionary — Work Package G
A3: ASSUMPTION: No Veloop source material was supplied, so Veloop is modelled as a shared bike / e-bike / e-scooter mobility platform (app, vehicles, stations, trips, payments, support). Entities, fields and sources are PROPOSED. Replace or delete any that do not match the real business.
A5: How to use
A6: 1. 'Data Dictionary' sheet: one row per field, with all 11 required attributes plus Field ID and Status.
A7: 2. 'Entity Summary': grain and field counts per entity (formula-driven, updates when you edit the dictionary).
A8: 3. 'Checks': automatic quality checks (75+ field target, duplicates, missing attributes, sensitivity mix).
A9: 4. 'Rationale & Gaps': why the field set is sufficient, and what to add next.
A11: Status rule: every field is 'Proposed'. Change to 'Confirmed' only after the data owner has verified the field exists in the named source with the stated type and rules.
A12: Sensitivity: Public = safe to publish; Internal = staff only; Restricted = personal, precise location, or identity-linked data (access-controlled, aggregate when reporting).
A13: Edit cells in 'Data Dictionary' directly; dropdowns exist for Required, Sensitivity and Status.

Sheet Data Dictionary
A1: Field ID | B1: Entity | C1: Field Name | D1: Data Type | E1: Definition | F1: Example | G1: Required | H1: Allowed Values | I1: Validation | J1: Source | K1: Sensitivity | L1: Analytical Use | M1: Status
A2: F001 | B2: dim_user | C2: user_id | D2: STRING | E2: Unique surrogate identifier of a registered rider account. | F2: U-00048213 | G2: Yes | I2: Unique, not null, format U-####### | J2: Mobile app backend | K2: Internal | L2: Primary join key for all rider-level analysis (retention, LTV, cohorts). | M2: Proposed
A3: F002 | B3: dim_user | C3: signup_date | D3: DATE | E3: Calendar date the account was created. | F3: 2026-03-14 | G3: Yes | I3: Valid date, <= today, >= launch date | J3: Mobile app backend | K3: Internal | L3: Cohort assignment and acquisition trend analysis. | M3: Proposed
A4: F003 | B4: dim_user | C4: signup_channel | D4: STRING | E4: Marketing/acquisition channel credited for the signup. | F4: referral | G4: Yes | H4: organic, paid_social, paid_search, referral, partner, unknown | I4: Must be in allowed list | J4: App backend + attribution SDK | K4: Internal | L4: Compares CAC and retention by channel. | M4: Proposed
A5: F004 | B5: dim_user | C5: country_code | D5: STRING | E5: ISO 3166-1 alpha-2 country of the account's home market. | F5: DE | G5: Yes | H5: ISO 3166-1 alpha-2 | I5: 2 uppercase letters, in ISO list | J5: Mobile app backend | K5: Internal | L5: Market-level segmentation and reporting. | M5: Proposed
A6: F005 | B6: dim_user | C6: home_city | D6: STRING | E6: City where the user takes most trips or registered. | F6: Berlin | G6: No | I6: Not blank if provided; matches city reference list | J6: Derived (ETL) from trips | K6: Internal | L6: City-level demand and penetration analysis. | M6: Proposed
A7: F006 | B7: dim_user | C7: birth_year | D7: INTEGER | E7: Year of birth supplied at signup (year only, to limit PII). | F7: 1994 | G7: No | I7: 1920 <= value <= current year - minimum age | J7: Mobile app backend | K7: Restricted | L7: Age-band segmentation and age-eligibility compliance. | M7: Proposed
A8: F007 | B8: dim_user | C8: user_status | D8: STRING | E8: Current lifecycle state of the account. | F8: active | G8: Yes | H8: active, dormant, suspended, deleted | I8: Must be in allowed list | J8: Derived (ETL) | K8: Internal | L8: Active-user counts, churn and reactivation tracking. | M8: Proposed
A9: F008 | B9: dim_user | C9: account_tier | D9: STRING | E9: Subscription tier the user is currently on. | F9: monthly_pass | G9: Yes | H9: pay_as_you_go, monthly_pass, annual_pass, corporate | I9: Must be in allowed list | J9: Billing system | K9: Internal | L9: Revenue mix and tier-upgrade analysis. | M9: Proposed
A10: F009 | B10: dim_user | C10: marketing_consent_flag | D10: BOOLEAN | E10: Whether the user consented to marketing communications. | F10: TRUE | G10: Yes | H10: TRUE, FALSE | I10: Not null | J10: Mobile app backend | K10: Restricted | L10: Ensures campaign analysis respects consent (GDPR). | M10: Proposed
A11: F010 | B11: dim_user | C11: email_hash | D11: STRING | E11: SHA-256 hash of normalised email, used for matching without exposing the address. | F11: 9f86d0...a08 | G11: No | I11: 64 hex chars, lowercase | J11: Derived (ETL) | K11: Restricted | L11: Deduplicating accounts and joining to CRM without raw PII. | M11: Proposed
A12: F011 | B12: dim_user | C12: first_trip_date | D12: DATE | E12: Date of the user's first completed trip. | F12: 2026-03-15 | G12: No | I12: Null until first trip; >= signup_date | J12: Derived (ETL) | K12: Internal | L12: Activation rate and time-to-first-trip. | M12: Proposed
A13: F012 | B13: dim_vehicle | C13: vehicle_id | D13: STRING | E13: Unique identifier of a physical bike/e-bike/scooter. | F13: V-100245 | G13: Yes | I13: Unique, not null | J13: Fleet ops system | K13: Internal | L13: Join key for utilisation, maintenance and telemetry. | M13: Proposed
A14: F013 | B14: dim_vehicle | C14: vehicle_type | D14: STRING | E14: Category of vehicle. | F14: ebike | G14: Yes | H14: bike, ebike, escooter, cargo_bike | I14: Must be in allowed list | J14: Fleet ops system | K14: Internal | L14: Utilisation and revenue comparison by vehicle type. | M14: Proposed
A15: F014 | B15: dim_vehicle | C15: model_name | D15: STRING | E15: Manufacturer model designation. | F15: VL-E2 Gen3 | G15: Yes | I15: Must match vehicle model reference list | J15: Fleet ops system | K15: Internal | L15: Reliability and cost analysis by model. | M15: Proposed
A16: F015 | B16: dim_vehicle | C16: battery_capacity_wh | D16: INTEGER | E16: Rated battery capacity in watt-hours (null for non-electric). | F16: 504 | G16: No | I16: > 0 when vehicle_type is electric, else null | J16: Fleet ops system | K16: Internal | L16: Range modelling and battery-swap planning. | M16: Proposed
A17: F016 | B17: dim_vehicle | C17: commission_date | D17: DATE | E17: Date the vehicle entered service. | F17: 2025-09-01 | G17: Yes | I17: Valid date, <= today | J17: Fleet ops system | K17: Internal | L17: Vehicle age and lifecycle analysis. | M17: Proposed
A18: F017 | B18: dim_vehicle | C18: vehicle_status | D18: STRING | E18: Current operational state. | F18: available | G18: Yes | H18: available, in_use, maintenance, missing, retired | I18: Must be in allowed list | J18: Fleet ops system | K18: Internal | L18: Fleet availability and downtime reporting. | M18: Proposed
A19: F018 | B19: dim_vehicle | C19: firmware_version | D19: STRING | E19: Version of firmware on the vehicle's lock/IoT unit. | F19: 3.4.1 | G19: No | I19: Semantic version pattern X.Y.Z | J19: IoT telematics | K19: Internal | L19: Links faults and trip anomalies to firmware releases. | M19: Proposed
A20: F019 | B20: dim_vehicle | C20: fleet_owner_type | D20: STRING | E20: Whether the vehicle is owned, leased or partner-supplied. | F20: owned | G20: Yes | H20: owned, leased, partner | I20: Must be in allowed list | J20: Finance / fleet ops | K20: Internal | L20: Unit economics by ownership model. | M20: Proposed
A21: F020 | B21: dim_vehicle | C21: retirement_date | D21: DATE | E21: Date the vehicle left the fleet permanently. | F21: 2027-01-20 | G21: No | I21: Null unless vehicle_status = retired; >= commission_date | J21: Fleet ops system | K21: Internal | L21: Asset life and replacement planning. | M21: Proposed
A22: F021 | B22: dim_station | C22: station_id | D22: STRING | E22: Unique identifier of a docking station or designated parking zone. | F22: S-0231 | G22: Yes | I22: Unique, not null | J22: Station registry | K22: Internal | L22: Join key for supply/demand and flow analysis. | M22: Proposed
A23: F022 | B23: dim_station | C23: station_name | D23: STRING | E23: Public name of the station. | F23: Alexanderplatz North | G23: Yes | I23: Not blank, <= 100 chars | J23: Station registry | K23: Public | L23: Readable labels for dashboards and maps. | M23: Proposed
A24: F023 | B24: dim_station | C24: city | D24: STRING | E24: City in which the station is located. | F24: Berlin | G24: Yes | I24: Matches city reference list | J24: Station registry | K24: Public | L24: Geographic roll-ups. | M24: Proposed
A25: F024 | B25: dim_station | C25: latitude | D25: DECIMAL(9,6) | E25: WGS84 latitude of the station. | F25: 52.521918 | G25: Yes | I25: -90 to 90 | J25: Station registry | K25: Public | L25: Spatial analysis and heatmaps. | M25: Proposed
A26: F025 | B26: dim_station | C26: longitude | D26: DECIMAL(9,6) | E26: WGS84 longitude of the station. | F26: 13.413215 | G26: Yes | I26: -180 to 180 | J26: Station registry | K26: Public | L26: Spatial analysis and heatmaps. | M26: Proposed
A27: F026 | B27: dim_station | C27: dock_capacity | D27: INTEGER | E27: Number of vehicles the station can hold. | F27: 24 | G27: Yes | I27: Integer >= 0 (0 allowed for virtual zones) | J27: Station registry | K27: Internal | L27: Occupancy and rebalancing calculations. | M27: Proposed
A28: F027 | B28: dim_station | C28: station_type | D28: STRING | E28: Physical or virtual type of the location. | F28: docked | G28: Yes | H28: docked, virtual_zone, hub | I28: Must be in allowed list | J28: Station registry | K28: Internal | L28: Compares performance by station design. | M28: Proposed
A29: F028 | B29: dim_station | C29: pricing_zone_id | D29: STRING | E29: Pricing zone the station belongs to. | F29: Z-CENTRAL | G29: No | I29: Must exist in zone reference list | J29: Reference data (manual) | K29: Internal | L29: Analyses price sensitivity by zone. | M29: Proposed
A30: F029 | B30: dim_station | C30: station_opened_date | D30: DATE | E30: Date the station became operational. | F30: 2025-06-12 | G30: Yes | I30: Valid date, <= today | J30: Station registry | K30: Internal | L30: Maturity curves for new stations. | M30: Proposed
A31: F030 | B31: dim_station | C31: station_status | D31: STRING | E31: Current operating state of the station. | F31: active | G31: Yes | H31: active, temporarily_closed, decommissioned | I31: Must be in allowed list | J31: Station registry | K31: Internal | L31: Excludes closed stations from availability metrics. | M31: Proposed
A32: F031 | B32: dim_date | C32: date_key | D32: INTEGER | E32: Surrogate key in YYYYMMDD form. | F32: 20261017 | G32: Yes | I32: 8 digits, valid date | J32: Calendar table (generated) | K32: Public | L32: Standard time join for all facts. | M32: Proposed
A33: F032 | B33: dim_date | C33: calendar_date | D33: DATE | E33: The calendar date. | F33: 2026-10-17 | G33: Yes | I33: Unique, continuous series | J33: Calendar table (generated) | K33: Public | L33: Daily trend analysis. | M33: Proposed
A34: F033 | B34: dim_date | C34: day_of_week | D34: STRING | E34: Day name. | F34: Saturday | G34: Yes | H34: Monday ... Sunday | I34: Must be in allowed list | J34: Calendar table (generated) | K34: Public | L34: Weekday vs weekend demand patterns. | M34: Proposed
A35: F034 | B35: dim_date | C35: is_weekend | D35: BOOLEAN | E35: TRUE for Saturday or Sunday. | F35: TRUE | G35: Yes | H35: TRUE, FALSE | I35: Consistent with day_of_week | J35: Calendar table (generated) | K35: Public | L35: Leisure vs commuter segmentation. | M35: Proposed
A36: F035 | B36: dim_date | C36: is_public_holiday | D36: BOOLEAN | E36: TRUE if the date is a public holiday in the market. | F36: FALSE | G36: Yes | H36: TRUE, FALSE | I36: Matches holiday reference per country | J36: Reference data (manual) | K36: Public | L36: Explains demand spikes and dips. | M36: Proposed
A37: F036 | B37: dim_date | C37: iso_week | D37: INTEGER | E37: ISO 8601 week number of the year. | F37: 42 | G37: Yes | I37: 1 to 53 | J37: Calendar table (generated) | K37: Public | L37: Weekly reporting cadence. | M37: Proposed
A38: F037 | B38: fact_trip | C38: trip_id | D38: STRING | E38: Unique identifier of one rental/trip. | F38: T-9004412 | G38: Yes | I38: Unique, not null | J38: Mobile app backend | K38: Internal | L38: Grain of the trip fact; counts and rates. | M38: Proposed
A39: F038 | B39: fact_trip | C39: user_id | D39: STRING | E39: Rider who took the trip (FK to dim_user). | F39: U-00048213 | G39: Yes | I39: Must exist in dim_user | J39: Mobile app backend | K39: Internal | L39: Rider behaviour, frequency and retention. | M39: Proposed
A40: F039 | B40: fact_trip | C40: vehicle_id | D40: STRING | E40: Vehicle used (FK to dim_vehicle). | F40: V-100245 | G40: Yes | I40: Must exist in dim_vehicle | J40: Mobile app backend | K40: Internal | L40: Vehicle utilisation and revenue per vehicle. | M40: Proposed
A41: F040 | B41: fact_trip | C41: start_station_id | D41: STRING | E41: Station where the trip began (FK to dim_station); null for free-floating start. | F41: S-0231 | G41: No | I41: Must exist in dim_station if present | J41: IoT telematics | K41: Internal | L41: Origin-destination flows. | M41: Proposed
A42: F041 | B42: fact_trip | C42: end_station_id | D42: STRING | E42: Station where the trip ended (FK to dim_station); null if ended outside a station. | F42: S-0307 | G42: No | I42: Must exist in dim_station if present | J42: IoT telematics | K42: Internal | L42: Origin-destination flows and rebalancing need. | M42: Proposed
A43: F042 | B43: fact_trip | C43: trip_start_ts | D43: TIMESTAMP | E43: UTC time the vehicle was unlocked. | F43: 2026-10-17T07:42:10Z | G43: Yes | I43: Valid UTC timestamp, <= trip_end_ts | J43: IoT telematics | K43: Internal | L43: Hourly demand profile and peak analysis. | M43: Proposed
A44: F043 | B44: fact_trip | C44: trip_end_ts | D44: TIMESTAMP | E44: UTC time the trip was locked/ended. | F44: 2026-10-17T08:03:55Z | G44: No | I44: Null only while trip_status = in_progress | J44: IoT telematics | K44: Internal | L44: Duration and billing calculations. | M44: Proposed
A45: F044 | B45: fact_trip | C45: duration_sec | D45: INTEGER | E45: Trip length in seconds (trip_end_ts - trip_start_ts). | F45: 1305 | G45: No | I45: Equals end minus start; 0 < value <= 86400 else flag | J45: Derived (ETL) | K45: Internal | L45: Core usage metric; outlier detection. | M45: Proposed
A46: F045 | B46: fact_trip | C46: distance_m | D46: INTEGER | E46: GPS-derived trip distance in metres. | F46: 4820 | G46: No | I46: 0 <= value <= 100000 | J46: IoT telematics | K46: Internal | L46: Distance-based demand and carbon savings. | M46: Proposed
A47: F046 | B47: fact_trip | C47: start_latitude | D47: DECIMAL(9,6) | E47: Latitude at unlock. | F47: 52.521918 | G47: No | I47: -90 to 90 | J47: IoT telematics | K47: Restricted | L47: Free-floating demand mapping (precise location is sensitive). | M47: Proposed
A48: F047 | B48: fact_trip | C48: start_longitude | D48: DECIMAL(9,6) | E48: Longitude at unlock. | F48: 13.413215 | G48: No | I48: -180 to 180 | J48: IoT telematics | K48: Restricted | L48: Free-floating demand mapping. | M48: Proposed
... A52: F051 | B52: fact_trip | C52: battery_end_pct | D52: INTEGER | E52: Battery level at lock (electric only). | F52: 79 | G52: No | I52: 0 to 100, <= battery_start_pct unless swapped | J52: IoT telematics | K52: Internal | L52: Battery consumption per km; charging triggers. | M52: Proposed
A53: F052 | B53: fact_trip | C53: trip_status | D53: STRING | E53: Outcome of the trip. | F53: completed | G53: Yes | H53: in_progress, completed, cancelled, system_terminated | I53: Must be in allowed list | J53: Mobile app backend | K53: Internal | L53: Separates valid trips from failed unlocks. | M53: Proposed
A54: F053 | B54: fact_trip | C54: unlock_method | D54: STRING | E54: How the rider unlocked the vehicle. | F54: qr_scan | G54: Yes | H54: qr_scan, nfc, bluetooth, manual_code | I54: Must be in allowed list | J54: Mobile app backend | K54: Internal | L54: UX friction and failure analysis. | M54: Proposed
A55: F054 | B55: fact_trip | C55: pricing_plan_id | D55: STRING | E55: Pricing plan applied (FK to dim_pricing_plan). | F55: PP-STD-2026 | G55: Yes | I55: Must exist in dim_pricing_plan | J55: Billing system | K55: Internal | L55: Revenue analysis by plan. | M55: Proposed
A56: F055 | B56: fact_trip | C56: is_ended_in_station | D56: BOOLEAN | E56: Whether the trip ended inside a valid station or zone. | F56: TRUE | G56: Yes | H56: TRUE, FALSE | I56: Consistent with end_station_id | J56: Derived (ETL) | K56: Internal | L56: Parking compliance and station-return rate. | M56: Proposed
A57: F056 | B57: fact_trip | C57: trip_rating | D57: INTEGER | E57: Rider's post-trip rating. | F57: 5 | G57: No | H57: 1-5 | I57: Integer 1 to 5 or null | J57: Mobile app backend | K57: Internal | L57: Satisfaction tracking by vehicle and station. | M57: Proposed
A58: F057 | B58: dim_pricing_plan | C58: pricing_plan_id | D58: STRING | E58: Unique ID of a price configuration. | F58: PP-STD-2026 | G58: Yes | I58: Unique, not null | J58: Billing system | K58: Internal | L58: Join key to trips and payments. | M58: Proposed
A59: F058 | B59: dim_pricing_plan | C59: plan_name | D59: STRING | E59: Display name of the plan. | F59: Standard 2026 | G59: Yes | I59: Not blank | J59: Billing system | K59: Public | L59: Readable reporting labels. | M59: Proposed
A60: F059 | B60: dim_pricing_plan | C60: unlock_fee | D60: DECIMAL(8,2) | E60: Fixed fee charged on unlock. | F60: 1.00 | G60: Yes | I60: > = 0 | J60: Billing system | K60: Public | L60: Revenue decomposition and price tests. | M60: Proposed
A61: F060 | B61: dim_pricing_plan | C61: per_minute_rate | D61: DECIMAL(8,4) | E61: Charge per minute of riding. | F61: 0.2500 | G61: Yes | I61: > = 0 | J61: Billing system | K61: Public | L61: Price elasticity analysis. | M61: Proposed
A62: F061 | B62: dim_pricing_plan | C62: free_minutes | D62: INTEGER | E62: Free minutes included per trip (e.g. pass benefit). | F62: 30 | G62: Yes | I62: > = 0 | J62: Billing system | K62: Public | L62: Pass profitability analysis. | M62: Proposed
A63: F062 | B63: dim_pricing_plan | C63: plan_valid_from | D63: DATE | E63: First date the plan is effective. | F63: 2026-01-01 | G63: Yes | I63: Valid date; < plan_valid_to | J63: Billing system | K63: Internal | L63: Correct plan history for time-series revenue. | M63: Proposed
A64: F063 | B64: fact_payment | C64: payment_id | D64: STRING | E64: Unique identifier of a payment transaction. | F64: PAY-5521098 | G64: Yes | I64: Unique, not null | J64: Payment service provider | K64: Internal | L64: Grain of the payment fact. | M64: Proposed
A65: F064 | B65: fact_payment | C65: trip_id | D65: STRING | E65: Trip the payment relates to; null for pass purchases. | F65: T-9004412 | G65: No | I65: Must exist in fact_trip if present | J65: Billing system | K65: Internal | L65: Trip-level revenue attribution. | M65: Proposed
A66: F065 | B66: fact_payment | C66: user_id | D66: STRING | E66: Payer (FK to dim_user). | F66: U-00048213 | G66: Yes | I66: Must exist in dim_user | J66: Payment service provider | K66: Internal | L66: Customer lifetime value. | M66: Proposed
A67: F066 | B67: fact_payment | C67: payment_ts | D67: TIMESTAMP | E67: UTC time the transaction was processed. | F67: 2026-10-17T08:04:30Z | G67: Yes | I67: Valid UTC timestamp | J67: Payment service provider | K67: Internal | L67: Daily revenue and reconciliation. | M67: Proposed
A68: F067 | B68: fact_payment | C68: gross_amount | D68: DECIMAL(10,2) | E68: Amount charged including tax, before refunds. | F68: 3.75 | G68: Yes | I68: > = 0 | J68: Payment service provider | K68: Internal | L68: Core revenue metric. | M68: Proposed
A69: F068 | B69: fact_payment | C69: tax_amount | D69: DECIMAL(10,2) | E69: VAT/sales tax included in gross_amount. | F69: 0.60 | G69: Yes | I69: 0 <= value <= gross_amount | J69: Billing system | K69: Internal | L69: Net revenue and tax reporting. | M69: Proposed
A70: F069 | B70: fact_payment | C70: currency_code | D70: STRING | E70: ISO 4217 currency of the transaction. | F70: EUR | G70: Yes | H70: ISO 4217 | I70: 3 uppercase letters, in ISO list | J70: Payment service provider | K70: Internal | L70: Multi-market revenue conversion. | M70: Proposed
A71: F070 | B71: fact_payment | C71: payment_method_type | D71: STRING | E71: Instrument used to pay. | F71: card | G71: Yes | H71: card, apple_pay, google_pay, wallet, invoice | I71: Must be in allowed list | J71: Payment service provider | K71: Internal | L71: Payment cost and failure analysis. | M71: Proposed
A72: F071 | B72: fact_payment | C72: payment_status | D72: STRING | E72: Result of the transaction. | F72: succeeded | G72: Yes | H72: succeeded, failed, pending, refunded | I72: Must be in allowed list | J72: Payment service provider | K72: Internal | L72: Failed-payment recovery and revenue leakage. | M72: Proposed
A73: F072 | B73: fact_payment | C73: refund_amount | D73: DECIMAL(10,2) | E73: Amount refunded to the rider. | F73: 0.00 | G73: Yes | I73: 0 <= value <= gross_amount | J73: Payment service provider | K73: Internal | L73: Net revenue and refund-rate monitoring. | M73: Proposed
A74: F073 | B74: fact_payment | C74: promo_code_id | D74: STRING | E74: Promo code applied, if any (FK to dim_promo). | F74: PC-WELCOME10 | G74: No | I74: Must exist in dim_promo if present | J74: Billing system | K74: Internal | L74: Promotion ROI. | M74: Proposed
A75: F074 | B75: dim_promo | C75: promo_code_id | D75: STRING | E75: Unique ID of a promotion code. | F75: PC-WELCOME10 | G75: Yes | I75: Unique, not null | J75: Marketing platform | K75: Internal | L75: Join key to payments. | M75: Proposed
A76: F075 | B76: dim_promo | C76: campaign_id | D76: STRING | E76: Marketing campaign the code belongs to. | F76: CMP-AUT26 | G76: Yes | I76: Not null | J76: Marketing platform | K76: Internal | L76: Campaign performance roll-ups. | M76: Proposed
A77: F076 | B77: dim_promo | C77: discount_type | D77: STRING | E77: Type of discount. | F77: percentage | G77: Yes | H77: percentage, fixed_amount, free_minutes | I77: Must be in allowed list | J77: Marketing platform | K77: Internal | L77: Compares promotion mechanics. | M77: Proposed
A78: F077 | B78: dim_promo | C78: discount_value | D78: DECIMAL(8,2) | E78: Size of the discount in the unit of discount_type. | F78: 10.00 | G78: Yes | I78: > 0; <= 100 if percentage | J78: Marketing platform | K78: Internal | L78: Cost of promotion. | M78: Proposed
A79: F078 | B79: dim_promo | C79: promo_valid_to | D79: DATE | E79: Last date the code can be redeemed. | F79: 2026-12-31 | G79: Yes | I79: Valid date; >= start date | J79: Marketing platform | K79: Internal | L79: Excludes expired promos; measures campaign windows. | M79: Proposed
A80: F079 | B80: fact_maintenance | C80: maintenance_id | D80: STRING | E80: Unique ID of a maintenance work order. | F80: M-33018 | G80: Yes | I80: Unique, not null | J80: Fleet ops system | K80: Internal | L80: Grain of the maintenance fact. | M80: Proposed
A81: F080 | B81: fact_maintenance | C81: vehicle_id | D81: STRING | E81: Vehicle serviced (FK to dim_vehicle). | F81: V-100245 | G81: Yes | I81: Must exist in dim_vehicle | J81: Fleet ops system | K81: Internal | L81: Reliability per vehicle. | M81: Proposed
A82: F081 | B82: fact_maintenance | C82: opened_ts | D82: TIMESTAMP | E82: UTC time the issue was logged. | F82: 2026-10-16T18:20:00Z | G82: Yes | I82: Valid UTC timestamp | J82: Fleet ops system | K82: Internal | L82: Start of downtime. | M82: Proposed
A83: F082 | B83: fact_maintenance | C83: closed_ts | D83: TIMESTAMP | E83: UTC time the vehicle returned to service. | F83: 2026-10-17T09:10:00Z | G83: No | I83: Null if open; >= opened_ts | J83: Fleet ops system | K83: Internal | L83: Downtime and repair turnaround. | M83: Proposed
A84: F083 | B84: fact_maintenance | C84: issue_category | D84: STRING | E84: Primary fault type. | F84: brakes | G84: Yes | H84: brakes, battery, tyre, lock, motor, frame, vandalism, other | I84: Must be in allowed list | J84: Fleet ops system | K84: Internal | L84: Root-cause and parts planning. | M84: Proposed
A85: F084 | B85: fact_maintenance | C85: severity | D85: STRING | E85: Severity of the issue. | F85: high | G85: Yes | H85: low, medium, high, safety_critical | I85: Must be in allowed list | J85: Fleet ops system | K85: Internal | L85: Prioritisation and safety monitoring. | M85: Proposed
A86: F085 | B86: fact_maintenance | C86: reported_source | D86: STRING | E86: How the issue was detected. | F86: rider_report | G86: Yes | H86: rider_report, telemetry_alert, inspection, technician | I86: Must be in allowed list | J86: Fleet ops system | K86: Internal | L86: Evaluates early-detection effectiveness. | M86: Proposed
A87: F086 | B87: fact_maintenance | C87: repair_cost_amount | D87: DECIMAL(10,2) | E87: Total parts and labour cost. | F87: 18.40 | G87: No | I87: > = 0 | J87: Finance / fleet ops | K87: Internal | L87: Cost per vehicle and cost per trip. | M87: Proposed
A88: F087 | B88: fact_maintenance | C88: technician_id | D88: STRING | E88: Technician who closed the order. | F88: TECH-021 | G88: No | I88: Must exist in staff reference | J88: Fleet ops system | K88: Restricted | L88: Productivity analysis (aggregate use only). | M88: Proposed
A89: F088 | B89: fact_support_ticket | C89: ticket_id | D89: STRING | E89: Unique ID of a support ticket. | F89: TK-77120 | G89: Yes | I89: Unique, not null | J89: Helpdesk system | K89: Internal | L89: Grain of support fact. | M89: Proposed
A90: F089 | B90: fact_support_ticket | C90: user_id | D90: STRING | E90: Rider who raised the ticket. | F90: U-00048213 | G90: Yes | I90: Must exist in dim_user | J90: Helpdesk system | K90: Internal | L90: Links support load to rider segments. | M90: Proposed
A91: F090 | B91: fact_support_ticket | C91: trip_id | D91: STRING | E91: Related trip, if any. | F91: T-9004412 | G91: No | I91: Must exist in fact_trip if present | J91: Helpdesk system | K91: Internal | L91: Ties issues to specific trips. | M91: Proposed
A92: F091 | B92: fact_support_ticket | C92: created_ts | D92: TIMESTAMP | E92: UTC time ticket was created. | F92: 2026-10-17T08:30:00Z | G92: Yes | I92: Valid UTC timestamp | J92: Helpdesk system | K92: Internal | L92: Volume and response-time analysis. | M92: Proposed
A93: F092 | B93: fact_support_ticket | C93: ticket_category | D93: STRING | E93: Reason for contact. | F93: billing_dispute | G93: Yes | H93: billing_dispute, unlock_failure, damaged_vehicle, safety, account, other | I93: Must be in allowed list | J93: Helpdesk system | K93: Internal | L93: Identifies top product and ops pain points. | M93: Proposed
A94: F093 | B94: fact_support_ticket | C94: priority | D94: STRING | E94: Ticket priority. | F94: normal | G94: Yes | H94: low, normal, high, urgent | I94: Must be in allowed list | J94: Helpdesk system | K94: Internal | L94: SLA analysis. | M94: Proposed
A95: F094 | B95: fact_support_ticket | C95: resolved_ts | D95: TIMESTAMP | E95: UTC time the ticket was resolved. | F95: 2026-10-17T10:00:00Z | G95: No | I95: Null if open; >= created_ts | J95: Helpdesk system | K95: Internal | L95: Resolution time metric. | M95: Proposed
A96: F095 | B96: fact_support_ticket | C96: csat_score | D96: INTEGER | E96: Customer satisfaction score after resolution. | F96: 4 | G96: No | H96: 1-5 | I96: Integer 1 to 5 or null | J96: Helpdesk system | K96: Internal | L96: Service quality and churn-risk signals. | M96: Proposed
A97: F096 | B97: fact_app_event | C97: event_id | D97: STRING | E97: Unique ID of an app event. | F97: EV-8821004411 | G97: Yes | I97: Unique, not null | J97: Product analytics SDK | K97: Internal | L97: Grain of the event fact. | M97: Proposed
A98: F097 | B98: fact_app_event | C98: user_id | D98: STRING | E98: User who triggered the event; null if anonymous. | F98: U-00048213 | G98: No | I98: Must exist in dim_user if present | J98: Product analytics SDK | K98: Internal | L98: Funnel analysis by user. | M98: Proposed
A99: F098 | B99: fact_app_event | C99: session_id | D99: STRING | E99: App session identifier. | F99: SES-aa91f | G99: Yes | I99: Not null | J99: Product analytics SDK | K99: Internal | L99: Session-level behaviour. | M99: Proposed
A100: F099 | B100: fact_app_event | C100: event_ts | D100: TIMESTAMP | E100: UTC time the event occurred. | F100: 2026-10-17T07:40:02Z | G100: Yes | I100: Valid UTC timestamp | J100: Product analytics SDK | K100: Internal | L100: Sequencing of funnel steps. | M100: Proposed
A101: F100 | B101: fact_app_event | C101: event_name | D101: STRING | E101: Name of tracked action. | F101: unlock_tapped | G101: Yes | H101: app_open, map_viewed, vehicle_selected, unlock_tapped, unlock_failed, trip_ended, payment_added | I101: Must be in event taxonomy | J101: Product analytics SDK | K101: Internal | L101: Conversion funnel from open to trip. | M101: Proposed
A102: F101 | B102: fact_app_event | C102: platform | D102: STRING | E102: Client platform. | F102: ios | G102: Yes | H102: ios, android, web | I102: Must be in allowed list | J102: Product analytics SDK | K102: Internal | L102: Platform-specific UX issues. | M102: Proposed
A103: F102 | B103: fact_app_event | C103: app_version | D103: STRING | E103: Version of the app. | F103: 5.12.0 | G103: Yes | I103: Semantic version pattern | J103: Product analytics SDK | K103: Internal | L103: Links regressions to releases. | M103: Proposed
...

Sheet Entity Summary
A1: Entity | B1: Type | C1: Grain | D1: Total Fields | E1: Required Fields | F1: Restricted Fields | G1: Proposed Fields
A2: dim_user | B2: Dimension | C2: One row per rider account | D2: =COUNTIF('Data Dictionary'!$B$2:$B$210,A2) -> 11 | E2: =COUNTIFS('Data Dictionary'!$B$2:$B$210,A2,'Data Dictionary'!$G$2:$G$210,"Yes") -> 7 | F2: =COUNTIFS('Data Dictionary'!$B$2:$B$210,A2,'Data Dictionary'!$K$2:$K$210,"Restricted") -> 3 | G2: =COUNTIFS('Data Dictionary'!$B$2:$B$210,A2,'Data Dictionary'!$M$2:$M$210,"Proposed") -> 11
A3: dim_vehicle | B3: Dimension | C3: One row per physical vehicle | D3: =COUNTIF('Data Dictionary'!$B$2:$B$210,A3) -> 9 | E3: =COUNTIFS('Data Dictionary'!$B$2:$B$210,A3,'Data Dictionary'!$G$2:$G$210,"Yes") -> 6 | F3: =COUNTIFS('Data Dictionary'!$B$2:$B$210,A3,'Data Dictionary'!$K$2:$K$210,"Restricted") -> 0 | G3: =COUNTIFS('Data Dictionary'!$B$2:$B$210,A3,'Data Dictionary'!$M$2:$M$210,"Proposed") -> 9
A4: dim_station | B4: Dimension | C4: One row per station / parking zone | D4: =COUNTIF('Data Dictionary'!$B$2:$B$210,A4) -> 10 | E4: =COUNTIFS('Data Dictionary'!$B$2:$B$210,A4,'Data Dictionary'!$G$2:$G$210,"Yes") -> 9 | F4: =COUNTIFS('Data Dictionary'!$B$2:$B$210,A4,'Data Dictionary'!$K$2:$K$210,"Restricted") -> 0 | G4: =COUNTIFS('Data Dictionary'!$B$2:$B$210,A4,'Data Dictionary'!$M$2:$M$210,"Proposed") -> 10
A5: dim_date | B5: Dimension | C5: One row per calendar date | D5: =COUNTIF('Data Dictionary'!$B$2:$B$210,A5) -> 6 | E5: =COUNTIFS('Data Dictionary'!$B$2:$B$210,A5,'Data Dictionary'!$G$2:$G$210,"Yes") -> 6 | F5: =COUNTIFS('Data Dictionary'!$B$2:$B$210,A5,'Data Dictionary'!$K$2:$K$210,"Restricted") -> 0 | G5: =COUNTIFS('Data Dictionary'!$B$2:$B$210,A5,'Data Dictionary'!$M$2:$M$210,"Proposed") -> 6
A6: dim_pricing_plan | B6: Dimension | C6: One row per pricing plan version | D6: =COUNTIF('Data Dictionary'!$B$2:$B$210,A6) -> 6 | E6: =COUNTIFS('Data Dictionary'!$B$2:$B$210,A6,'Data Dictionary'!$G$2:$G$210,"Yes") -> 6 | F6: =COUNTIFS('Data Dictionary'!$B$2:$B$210,A6,'Data Dictionary'!$K$2:$K$210,"Restricted") -> 0 | G6: =COUNTIFS('Data Dictionary'!$B$2:$B$210,A6,'Data Dictionary'!$M$2:$M$210,"Proposed") -> 6
A7: dim_promo | B7: Dimension | C7: One row per promo code | D7: =COUNTIF('Data Dictionary'!$B$2:$B$210,A7) -> 5 | E7: =COUNTIFS('Data Dictionary'!$B$2:$B$210,A7,'Data Dictionary'!$G$2:$G$210,"Yes") -> 5 | F7: =COUNTIFS('Data Dictionary'!$B$2:$B$210,A7,'Data Dictionary'!$K$2:$K$210,"Restricted") -> 0 | G7: =COUNTIFS('Data Dictionary'!$B$2:$B$210,A7,'Data Dictionary'!$M$2:$M$210,"Proposed") -> 5
A8: fact_trip | B8: Fact | C8: One row per trip | D8: =COUNTIF('Data Dictionary'!$B$2:$B$210,A8) -> 20 | E8: =COUNTIFS('Data Dictionary'!$B$2:$B$210,A8,'Data Dictionary'!$G$2:$G$210,"Yes") -> 8 | F8: =COUNTIFS('Data Dictionary'!$B$2:$B$210,A8,'Data Dictionary'!$K$2:$K$210,"Restricted") -> 4 | G8: =COUNTIFS('Data Dictionary'!$B$2:$B$210,A8,'Data Dictionary'!$M$2:$M$210,"Proposed") -> 20
A9: fact_payment | B9: Fact | C9: One row per payment transaction | D9: =COUNTIF('Data Dictionary'!$B$2:$B$210,A9) -> 11 | E9: =COUNTIFS('Data Dictionary'!$B$2:$B$210,A9,'Data Dictionary'!$G$2:$G$210,"Yes") -> 9 | F9: =COUNTIFS('Data Dictionary'!$B$2:$B$210,A9,'Data Dictionary'!$K$2:$K$210,"Restricted") -> 0 | G9: =COUNTIFS('Data Dictionary'!$B$2:$B$210,A9,'Data Dictionary'!$M$2:$M$210,"Proposed") -> 11
A10: fact_maintenance | B10: Fact | C10: One row per maintenance work order | D10: =COUNTIF('Data Dictionary'!$B$2:$B$210,A10) -> 9 | E10: =COUNTIFS('Data Dictionary'!$B$2:$B$210,A10,'Data Dictionary'!$G$2:$G$210,"Yes") -> 6 | F10: =COUNTIFS('Data Dictionary'!$B$2:$B$210,A10,'Data Dictionary'!$K$2:$K$210,"Restricted") -> 1 | G10: =COUNTIFS('Data Dictionary'!$B$2:$B$210,A10,'Data Dictionary'!$M$2:$M$210,"Proposed") -> 9
A11: fact_support_ticket | B11: Fact | C11: One row per support ticket | D11: =COUNTIF('Data Dictionary'!$B$2:$B$210,A11) -> 8 | E11: =COUNTIFS('Data Dictionary'!$B$2:$B$210,A11,'Data Dictionary'!$G$2:$G$210,"Yes") -> 5 | F11: =COUNTIFS('Data Dictionary'!$B$2:$B$210,A11,'Data Dictionary'!$K$2:$K$210,"Restricted") -> 0 | G11: =COUNTIFS('Data Dictionary'!$B$2:$B$210,A11,'Data Dictionary'!$M$2:$M$210,"Proposed") -> 8
A12: fact_app_event | B12: Fact | C12: One row per app event | D12: =COUNTIF('Data Dictionary'!$B$2:$B$210,A12) -> 8 | E12: =COUNTIFS('Data Dictionary'!$B$2:$B$210,A12,'Data Dictionary'!$G$2:$G$210,"Yes") -> 6 | F12: =COUNTIFS('Data Dictionary'!$B$2:$B$210,A12,'Data Dictionary'!$K$2:$K$210,"Restricted") -> 1 | G12: =COUNTIFS('Data Dictionary'!$B$2:$B$210,A12,'Data Dictionary'!$M$2:$M$210,"Proposed") -> 8
A13: fact_vehicle_snapshot | B13: Fact | C13: One row per vehicle per snapshot interval | D13: =COUNTIF('Data Dictionary'!$B$2:$B$210,A13) -> 6 | E13: =COUNTIFS('Data Dictionary'!$B$2:$B$210,A13,'Data Dictionary'!$G$2:$G$210,"Yes") -> 4 | F13: =COUNTIFS('Data Dictionary'!$B$2:$B$210,A13,'Data Dictionary'!$K$2:$K$210,"Restricted") -> 0 | G13: =COUNTIFS('Data Dictionary'!$B$2:$B$210,A13,'Data Dictionary'!$M$2:$M$210,"Proposed") -> 6
A14: TOTAL | D14: =SUM(D2:D13) -> 109 | E14: =SUM(E2:E13) -> 77 | F14: =SUM(F2:F13) -> 9 | G14: =SUM(G2:G13) -> 109

Sheet Checks
A1: Check | B1: Result | C1: Expected | D1: Pass?
A2: Total fields documented | B2: =COUNTA('Data Dictionary'!$C$2:$C$210) -> 109 | C2: 75 or more | D2: =IF(B2>=75,"PASS","FAIL") -> PASS
A3: Entities covered | B3: =COUNTA('Entity Summary'!A2:A13) -> 12 | C3: 1 or more | D3: =IF(B3>=1,"PASS","FAIL") -> PASS
A4: Duplicate Entity+Field rows | B4: =SUMPRODUCT(('Data Dictionary'!$B$2:$B$210<>"")*(COUNTIFS('Data Dictionary'!$B$2:$B$210,'Data Dictionary'!$B$2:$B$210,'Data Dictionary'!$C$2:$C$210,'Data Dictionary'!$C$2:$C$210)>1)) -> 0 | C4: 0 | D4: =IF(B4=0,"PASS","FAIL") -> PASS
A5: Rows with a blank required attribute | B5: =SUMPRODUCT(('Data Dictionary'!$C$2:$C$210<>"")*(('Data Dictionary'!$D$2:$D$210="")+('Data Dictionary'!$E$2:$E$210="")+('Data Dictionary'!$F$2:$F$210="")+('Data Dictionary'!$G$2:$G$210="")+('Data Dictionary'!$I$2:$I$210="")+('Data Dictionary'!$J$2:$J$210="")+('Data Dictionary'!$K$2:$K$210="")+('Data Dictionary'!$L$2:$L$210="")+('Data Dictionary'!$M$2:$M$210="")>0)) -> 0 | C5: 0 | D5: =IF(B5=0,"PASS","FAIL") -> PASS
A6: Fields still Proposed (count) | B6: =COUNTIF('Data Dictionary'!$M$2:$M$210,"Proposed") -> 109 | C6: Falls to 0 as owners sign off | D6: =IF(B6=0,"DONE","OPEN") -> OPEN
A7: Confirmed fields (%) | B7: =COUNTIF('Data Dictionary'!$M$2:$M$210,"Confirmed")/B2 -> 0 | C7: Rises toward 100% | D7: =IF(B7=1,"DONE","OPEN") -> OPEN
A8: Restricted fields (%) | B8: =COUNTIF('Data Dictionary'!$K$2:$K$210,"Restricted")/B2 -> 0.082568807 | C8: Keep small; review each | D8: =IF(B8<=0.2,"OK","REVIEW") -> OK
A9: Entity Summary total = dictionary total | B9: ='Entity Summary'!D14-B2 -> 0 | C9: 0 | D9: =IF(B9=0,"PASS","FAIL") -> PASS

Sheet Rationale & Gaps
A1: Why this field set
A2: Each field supports at least one named question: demand and utilisation (trips, snapshots), revenue and pricing (payments, plans, promos), retention and acquisition (users, channel, app events), fleet reliability and cost (vehicles, maintenance), and service quality (support tickets).
A3: Fields deliberately excluded: free-text notes, raw GPS breadcrumbs per second, full names, addresses, phone numbers and card data. They add privacy risk without a defined analytical question.
A4: The 75-field target is met only through fields tied to an analytical use; no filler columns were added.
A6: What to add next (not yet in the model)
A7: fact_incident: accidents, theft, vandalism, injuries (safety KPIs, insurance).
A8: fact_rebalancing_task: vehicle moves and battery swaps by operations crew (cost per rebalance, stock-out reduction).
A9: dim_city / dim_zone: population, regulation, fleet caps (market penetration).
A10: fact_marketing_spend: spend by channel and day (CAC, ROAS).
A11: fact_subscription: pass start, renewal, cancel dates and reasons (churn and LTV).
A12: fact_trip_route_point: sampled GPS path (route and safety analysis; Restricted).
A14: Open questions for the data owner
A15: Which source systems actually exist (names, owners)? Which fields are already captured? What is the legal retention period for precise location? Are there markets with different currency or tax rules?
