Workbook

Sheet README
A1: Work Package D - Wallet & Withdrawal Analytics (VELOOP)
A3: Purpose | B3: A transaction model and KPI set that lets VELOOP understand wallet movements and the withdrawal lifecycle.
A4: Wallet flow | B4: Reward Credit (+) | Redemption (-) | Reversal (undoes a prior entry) | Adjustment (+/-) - other types are marked PROPOSED.
A5: Withdrawal flow | B5: Requested -> Under Review / Processing -> Completed. Alternative end states: Rejected, Reversed (Cancelled = Proposed).
A7: SHEETS
A8: KPI_Dashboard | B8: Live KPIs vs targets: status counts, rates, processing times, pending queue, volume, method and reason mix, wallet KPIs, data-quality checks, charts.
A9: Withdrawals | B9: D2 - one row per withdrawal with timestamps, status, reason and calculated times / checks.
A10: Wallet_Transactions | B10: D1 - one row per ledger entry incl. reversal / correction links and automatic validation.
A11: Wallet_Balances | B11: Balance per user from Posted entries, plus pending withdrawal exposure.
A12: Daily_Operations | B12: Daily requests, completions, backlog, credits, redemptions and charts.
A13: Transaction_Types | B13: Catalogue of transaction types with Supported / Proposed status and direction.
A14: Withdrawal_Lifecycle | B14: State model, allowed transitions, reason categories and methods (all with Supported / Proposed marking).
A15: Settings | B15: As-of time, base unit, SLA, thresholds, targets and the wallet-debit timing assumption.
A16: D1 / D2 Data Dictionary | B16: Field definitions and rules for the wallet and withdrawal models.
A17: D3_KPI_Definitions | B17: Every KPI with Name, Definition, Formula, Data Required, Source, Frequency, Stakeholder Purpose, Limitation, live value.
A19: HOW TO USE
A20: 1 | B20: Replace the sample rows in Withdrawals and Wallet_Transactions (blue) with real data. All sample data is invented for illustration.
A21: 2 | B21: Copy the grey formula cells down for new rows. Summary formulas read to row 1000 (withdrawals) and 3000 (transactions).
A22: 3 | B22: Confirm the yellow assumptions in Settings and Transaction_Types, then change Proposed items to Supported once verified with Product / Engineering.
A23: 4 | B23: Update the As-of Timestamp on each refresh; extend Daily_Operations if the period exceeds 45 days; add users to Wallet_Balances.
A24: 5 | B24: Keep section 8 of the dashboard at 0 flags - these catch missing links, bad signs, wrong timestamps and wallet / withdrawal mismatches.
A26: KEY ASSUMPTIONS
A27: A | B27: I could not verify which transaction types, methods or reason categories exist in VELOOP. The four core types are marked Supported as an assumption; everything else is Proposed.
A28: B | B28: One base unit (Points) is used for all amounts; the currency conversion is illustrative.
A29: C | B29: The wallet is debited (Redemption) when a withdrawal is Completed; Rejected, pending and cancelled withdrawals have no wallet movement.
A30: D | B30: Targets, SLA hours and thresholds are placeholders, not benchmarks.
A32: COLOR LEGEND
A33: Blue text | B33: Input data / assumptions you can edit.
A34: Black text | B34: Formulas - do not overwrite.
A35: Green text | B35: Link pulled from another sheet.
A36: Yellow fill | B36: Assumption to confirm.
A37: Orange fill | B37: Proposed item - not confirmed as existing in VELOOP.

Sheet KPI_Dashboard
A1: Wallet & Withdrawal KPI Dashboard
A2: As-of: | B2: =Settings!B5 -> 46310.75
A4: 1. WITHDRAWAL LIFECYCLE - STATUS COUNTS | B4: Count | C4: % of Requests | D4: Amount (Base Unit) | E4: Notes
A5: Requested | B5: =COUNTIF(Withdrawals!$I$5:$I$1000,$A5) -> 0 | C5: =IFERROR(B5/$B$12,0) -> 0 | D5: =SUMIFS(Withdrawals!$C$5:$C$1000,Withdrawals!$I$5:$I$1000,$A5,Withdrawals!$D$5:$D$1000,Settings!$B$6) -> 0 | E5: Open: submitted, review not started.
A6: Under Review | B6: =COUNTIF(Withdrawals!$I$5:$I$1000,$A6) -> 9 | C6: =IFERROR(B6/$B$12,0) -> 0.1875 | D6: =SUMIFS(Withdrawals!$C$5:$C$1000,Withdrawals!$I$5:$I$1000,$A6,Withdrawals!$D$5:$D$1000,Settings!$B$6) -> 8600 | E6: Open: checks in progress.
A7: Processing | B7: =COUNTIF(Withdrawals!$I$5:$I$1000,$A7) -> 2 | C7: =IFERROR(B7/$B$12,0) -> 0.041666667 | D7: =SUMIFS(Withdrawals!$C$5:$C$1000,Withdrawals!$I$5:$I$1000,$A7,Withdrawals!$D$5:$D$1000,Settings!$B$6) -> 1500 | E7: Open: payout in progress.
A8: Completed | B8: =COUNTIF(Withdrawals!$I$5:$I$1000,$A8) -> 29 | C8: =IFERROR(B8/$B$12,0) -> 0.60416667 | D8: =SUMIFS(Withdrawals!$C$5:$C$1000,Withdrawals!$I$5:$I$1000,$A8,Withdrawals!$D$5:$D$1000,Settings!$B$6) -> 29650 | E8: Final: paid out and not reversed.
A9: Rejected | B9: =COUNTIF(Withdrawals!$I$5:$I$1000,$A9) -> 5 | C9: =IFERROR(B9/$B$12,0) -> 0.10416667 | D9: =SUMIFS(Withdrawals!$C$5:$C$1000,Withdrawals!$I$5:$I$1000,$A9,Withdrawals!$D$5:$D$1000,Settings!$B$6) -> 6450 | E9: Final: denied.
A10: Reversed | B10: =COUNTIF(Withdrawals!$I$5:$I$1000,$A10) -> 1 | C10: =IFERROR(B10/$B$12,0) -> 0.020833333 | D10: =SUMIFS(Withdrawals!$C$5:$C$1000,Withdrawals!$I$5:$I$1000,$A10,Withdrawals!$D$5:$D$1000,Settings!$B$6) -> 550 | E10: Final: paid then undone.
A11: Cancelled | B11: =COUNTIF(Withdrawals!$I$5:$I$1000,$A11) -> 2 | C11: =IFERROR(B11/$B$12,0) -> 0.041666667 | D11: =SUMIFS(Withdrawals!$C$5:$C$1000,Withdrawals!$I$5:$I$1000,$A11,Withdrawals!$D$5:$D$1000,Settings!$B$6) -> 3350 | E11: Final: PROPOSED state - user cancelled.
A12: Total Requests | B12: =COUNTA(Withdrawals!$A$5:$A$1000) -> 48 | C12: =IFERROR(SUM(C5:C11),0) -> 1 | D12: =SUM(D5:D11) -> 50100 | E12: Every request is in exactly one status.
A13: Check: sum of statuses minus total (should be 0) | B13: =SUM(B5:B11)-B12 -> 0
A15: 2. WITHDRAWAL KPIs vs TARGET | B15: Value | C15: Target | D15: Status | E15: Definition
A16: Withdrawal Requests | B16: =B12 -> 48 | E16: All requests created.
A17: Completed Withdrawals | B17: =B8 -> 29 | E17: Status = Completed (reversed ones are excluded).
A18: Pending Withdrawals (queue) | B18: =B5+B6+B7 -> 11 | E18: Requested + Under Review + Processing.
A19: Rejected Withdrawals | B19: =B9 -> 5 | E19: Status = Rejected.
A20: Reversed Withdrawals | B20: =B10 -> 1 | E20: Status = Reversed.
A21: Completion Rate | B21: =IFERROR(B17/B16,0) -> 0.60416667 | C21: =Settings!B13 -> 0.8 | D21: =IF(B21>=C21,"On track","Below target") -> Below target | E21: Completed / all requests.
A22: Completion Rate of Resolved Requests | B22: =IFERROR(B17/(B17+B19+B20),0) -> 0.82857143 | E22: Completed / (Completed + Rejected + Reversed). Ignores pending and cancelled.
A23: Rejection Rate | B23: =IFERROR(B19/B16,0) -> 0.10416667 | C23: =Settings!B14 -> 0.15 | D23: =IF(B23<=C23,"On track","Above target") -> On track | E23: Rejected / all requests.
A24: Reversal Rate | B24: =IFERROR(B20/(B17+B20),0) -> 0.033333333 | C24: =Settings!B15 -> 0.03 | D24: =IF(B24<=C24,"On track","Above target") -> Above target | E24: Reversed / (Completed + Reversed): share of payouts later undone.
A25: SLA Compliance | B25: =IFERROR(COUNTIF(Withdrawals!$P$5:$P$1000,"Yes")/B17,0) -> 0.65517241 | C25: =Settings!B16 -> 0.9 | D25: =IF(B25>=C25,"On track","Below target") -> Below target | E25: Completed within SLA hours / Completed.
A26: Avg End-to-End Processing Time (hrs) | B26: =IFERROR(AVERAGE(Withdrawals!$O$5:$O$1000),0) -> 44.364422 | C26: =Settings!B17 -> 36 | D26: =IF(B26<=C26,"On track","Above target") -> Above target | E26: Requested to Final, Completed only.
A27: Median End-to-End Time (hrs) | B27: =IFERROR(MEDIAN(Withdrawals!$O$5:$O$1000),0) -> 43.718908 | E27: Less sensitive to outliers than the average.
A28: P90 End-to-End Time (hrs) | B28: =IFERROR(PERCENTILE(Withdrawals!$O$5:$O$1000,0.9),0) -> 71.223395 | E28: 9 in 10 completed withdrawals finish within this time.
A29: Avg Queue Wait (hrs) | B29: =IFERROR(AVERAGE(Withdrawals!$M$5:$M$1000),0) -> 12.818641 | E29: Requested to Processing start, all requests that started.
A30: Avg Processing Time (hrs) | B30: =IFERROR(AVERAGE(Withdrawals!$N$5:$N$1000),0) -> 30.078528 | E30: Processing start to Final, Completed only.
A31: Avg Time to Rejection (hrs) | B31: =IFERROR(AVERAGE(Withdrawals!$Q$5:$Q$1000),0) -> 32.344435 | E31: Requested to Final, Rejected only.
A33: 3. PENDING QUEUE | B33: Value | C33: Target | D33: Status | E33: Definition
A34: Pending Count | B34: =B18 -> 11 | E34: Open requests right now.
A35: Pending Amount (Base Unit) | B35: =D5+D6+D7 -> 10100 | E35: Sum of requested amounts still open.
A36: Oldest Pending Age (hrs) | B36: =IFERROR(MAX(Withdrawals!$R$5:$R$1000),0) -> 217.98333 | E36: Age of the longest-waiting open request at the as-of time.
A37: Average Pending Age (hrs) | B37: =IFERROR(AVERAGE(Withdrawals!$R$5:$R$1000),0) -> 77.360125 | E37: Mean age of open requests.
A38: Aged Pending (> threshold) | B38: =COUNTIF(Withdrawals!$R$5:$R$1000,">"&Settings!B9) -> 4 | C38: =Settings!B18 -> 0 | D38: =IF(B38<=C38,"On track","Above target") -> Above target | E38: Open requests older than the aged-pending threshold.
A40: 4. WITHDRAWAL VOLUME | B40: Base Unit | C40: Currency Equivalent | D40: % of Requested | E40: Definition
A41: Requested Volume | B41: =SUMIFS(Withdrawals!$C$5:$C$1000,Withdrawals!$D$5:$D$1000,Settings!$B$6) -> 50100 | C41: =B41*Settings!$B$7 -> 501 | E41: All requested amounts.
A42: Completed Volume | B42: =D8 -> 29650 | C42: =B42*Settings!$B$7 -> 296.5 | D42: =IFERROR(B42/$B$41,0) -> 0.59181637 | E42: Paid out and not reversed.
A43: Pending Volume | B43: =D5+D6+D7 -> 10100 | C43: =B43*Settings!$B$7 -> 101 | D43: =IFERROR(B43/$B$41,0) -> 0.20159681 | E43: Open requests.
A44: Rejected Volume | B44: =D9 -> 6450 | C44: =B44*Settings!$B$7 -> 64.5 | D44: =IFERROR(B44/$B$41,0) -> 0.12874251 | E44: Denied requests.
A45: Reversed Volume | B45: =D10 -> 550 | C45: =B45*Settings!$B$7 -> 5.5 | D45: =IFERROR(B45/$B$41,0) -> 0.010978044 | E45: Paid then undone.
A46: Average Requested Amount | B46: =IFERROR(B41/B16,0) -> 1043.75 | C46: =B46*Settings!$B$7 -> 10.4375 | E46: Requested volume / requests.
A47: Unique Withdrawing Users | B47: =SUM(Withdrawals!$S$5:$S$1000) -> 19 | E47: Distinct users with at least one request.
A49: 5. METHOD DISTRIBUTION | B49: Requests | C49: % of Requests | D49: Completed | E49: Completion Rate | F49: Requested Volume | G49: Completed Volume | H49: Avg End-to-End Hrs
A50: Bank Transfer | B50: =COUNTIF(Withdrawals!$E$5:$E$1000,$A50) -> 23 | C50: =IFERROR(B50/$B$54,0) -> 0.47916667 | D50: =COUNTIFS(Withdrawals!$E$5:$E$1000,$A50,Withdrawals!$I$5:$I$1000,"Completed") -> 14 | E50: =IFERROR(D50/B50,0) -> 0.60869565 | F50: =SUMIFS(Withdrawals!$C$5:$C$1000,Withdrawals!$E$5:$E$1000,$A50,Withdrawals!$D$5:$D$1000,Settings!$B$6) -> 21900 | G50: =SUMIFS(Withdrawals!$C$5:$C$1000,Withdrawals!$E$5:$E$1000,$A50,Withdrawals!$I$5:$I$1000,"Completed",Withdrawals!$D$5:$D$1000,Settings!$B$6) -> 12150 | H50: =IFERROR(AVERAGEIFS(Withdrawals!$O$5:$O$1000,Withdrawals!$E$5:$E$1000,$A50),0) -> 40.814139
A51: E-Wallet | B51: =COUNTIF(Withdrawals!$E$5:$E$1000,$A51) -> 14 | C51: =IFERROR(B51/$B$54,0) -> 0.29166667 | D51: =COUNTIFS(Withdrawals!$E$5:$E$1000,$A51,Withdrawals!$I$5:$I$1000,"Completed") -> 9 | E51: =IFERROR(D51/B51,0) -> 0.64285714 | F51: =SUMIFS(Withdrawals!$C$5:$C$1000,Withdrawals!$E$5:$E$1000,$A51,Withdrawals!$D$5:$D$1000,Settings!$B$6) -> 17950 | G51: =SUMIFS(Withdrawals!$C$5:$C$1000,Withdrawals!$E$5:$E$1000,$A51,Withdrawals!$I$5:$I$1000,"Completed",Withdrawals!$D$5:$D$1000,Settings!$B$6) -> 10850 | H51: =IFERROR(AVERAGEIFS(Withdrawals!$O$5:$O$1000,Withdrawals!$E$5:$E$1000,$A51),0) -> 44.779058
A52: Gift Card | B52: =COUNTIF(Withdrawals!$E$5:$E$1000,$A52) -> 8 | C52: =IFERROR(B52/$B$54,0) -> 0.16666667 | D52: =COUNTIFS(Withdrawals!$E$5:$E$1000,$A52,Withdrawals!$I$5:$I$1000,"Completed") -> 4 | E52: =IFERROR(D52/B52,0) -> 0.5 | F52: =SUMIFS(Withdrawals!$C$5:$C$1000,Withdrawals!$E$5:$E$1000,$A52,Withdrawals!$D$5:$D$1000,Settings!$B$6) -> 7700 | G52: =SUMIFS(Withdrawals!$C$5:$C$1000,Withdrawals!$E$5:$E$1000,$A52,Withdrawals!$I$5:$I$1000,"Completed",Withdrawals!$D$5:$D$1000,Settings!$B$6) -> 5200 | H52: =IFERROR(AVERAGEIFS(Withdrawals!$O$5:$O$1000,Withdrawals!$E$5:$E$1000,$A52),0) -> 51.630806
A53: Other | B53: =COUNTIF(Withdrawals!$E$5:$E$1000,$A53) -> 3 | C53: =IFERROR(B53/$B$54,0) -> 0.0625 | D53: =COUNTIFS(Withdrawals!$E$5:$E$1000,$A53,Withdrawals!$I$5:$I$1000,"Completed") -> 2 | E53: =IFERROR(D53/B53,0) -> 0.66666667 | F53: =SUMIFS(Withdrawals!$C$5:$C$1000,Withdrawals!$E$5:$E$1000,$A53,Withdrawals!$D$5:$D$1000,Settings!$B$6) -> 2550 | G53: =SUMIFS(Withdrawals!$C$5:$C$1000,Withdrawals!$E$5:$E$1000,$A53,Withdrawals!$I$5:$I$1000,"Completed",Withdrawals!$D$5:$D$1000,Settings!$B$6) -> 1450 | H53: =IFERROR(AVERAGEIFS(Withdrawals!$O$5:$O$1000,Withdrawals!$E$5:$E$1000,$A53),0) -> 52.817777
A54: Total | B54: =SUM(B50:B53) -> 48 | C54: =SUM(C50:C53) -> 1 | D54: =SUM(D50:D53) -> 29 | E54: =IFERROR(D54/B54,0) -> 0.60416667 | F54: =SUM(F50:F53) -> 50100 | G54: =SUM(G50:G53) -> 29650 | H54: =IFERROR(AVERAGE(Withdrawals!$O$5:$O$1000),0) -> 44.364422
A56: 6. REJECTION & REVERSAL REASONS | B56: Rejected | C56: Reversed | D56: Total | E56: % of Rejected + Reversed
A57: Insufficient Balance | B57: =COUNTIFS(Withdrawals!$J$5:$J$1000,$A57,Withdrawals!$I$5:$I$1000,"Rejected") -> 0 | C57: =COUNTIFS(Withdrawals!$J$5:$J$1000,$A57,Withdrawals!$I$5:$I$1000,"Reversed") -> 0 | D57: =B57+C57 -> 0 | E57: =IFERROR(D57/$D$65,0) -> 0
A58: Verification Failed | B58: =COUNTIFS(Withdrawals!$J$5:$J$1000,$A58,Withdrawals!$I$5:$I$1000,"Rejected") -> 2 | C58: =COUNTIFS(Withdrawals!$J$5:$J$1000,$A58,Withdrawals!$I$5:$I$1000,"Reversed") -> 0 | D58: =B58+C58 -> 2 | E58: =IFERROR(D58/$D$65,0) -> 0.33333333
A59: Suspected Fraud | B59: =COUNTIFS(Withdrawals!$J$5:$J$1000,$A59,Withdrawals!$I$5:$I$1000,"Rejected") -> 2 | C59: =COUNTIFS(Withdrawals!$J$5:$J$1000,$A59,Withdrawals!$I$5:$I$1000,"Reversed") -> 0 | D59: =B59+C59 -> 2 | E59: =IFERROR(D59/$D$65,0) -> 0.33333333
A60: Limit / Minimum Rule | B60: =COUNTIFS(Withdrawals!$J$5:$J$1000,$A60,Withdrawals!$I$5:$I$1000,"Rejected") -> 0 | C60: =COUNTIFS(Withdrawals!$J$5:$J$1000,$A60,Withdrawals!$I$5:$I$1000,"Reversed") -> 0 | D60: =B60+C60 -> 0 | E60: =IFERROR(D60/$D$65,0) -> 0
A61: Duplicate Request | B61: =COUNTIFS(Withdrawals!$J$5:$J$1000,$A61,Withdrawals!$I$5:$I$1000,"Rejected") -> 1 | C61: =COUNTIFS(Withdrawals!$J$5:$J$1000,$A61,Withdrawals!$I$5:$I$1000,"Reversed") -> 1 | D61: =B61+C61 -> 2 | E61: =IFERROR(D61/$D$65,0) -> 0.33333333
A62: Payment Failure | B62: =COUNTIFS(Withdrawals!$J$5:$J$1000,$A62,Withdrawals!$I$5:$I$1000,"Rejected") -> 0 | C62: =COUNTIFS(Withdrawals!$J$5:$J$1000,$A62,Withdrawals!$I$5:$I$1000,"Reversed") -> 0 | D62: =B62+C62 -> 0 | E62: =IFERROR(D62/$D$65,0) -> 0
A63: User Request | B63: =COUNTIFS(Withdrawals!$J$5:$J$1000,$A63,Withdrawals!$I$5:$I$1000,"Rejected") -> 0 | C63: =COUNTIFS(Withdrawals!$J$5:$J$1000,$A63,Withdrawals!$I$5:$I$1000,"Reversed") -> 0 | D63: =B63+C63 -> 0 | E63: =IFERROR(D63/$D$65,0) -> 0
A64: Other | B64: =COUNTIFS(Withdrawals!$J$5:$J$1000,$A64,Withdrawals!$I$5:$I$1000,"Rejected") -> 0 | C64: =COUNTIFS(Withdrawals!$J$5:$J$1000,$A64,Withdrawals!$I$5:$I$1000,"Reversed") -> 0 | D64: =B64+C64 -> 0 | E64: =IFERROR(D64/$D$65,0) -> 0
A65: Total | B65: =SUM(B57:B64) -> 5 | C65: =SUM(C57:C64) -> 1 | D65: =SUM(D57:D64) -> 6 | E65: =SUM(E57:E64) -> 1
A67: 7. WALLET KPIs | B67: Value | C67: Target | D67: Status | E67: Definition
A68: Wallet Transactions (total rows) | B68: =COUNTA(Wallet_Transactions!$A$5:$A$3000) -> 289 | E68: All ledger entries, any status.
A69: Reward Credit Volume (Posted) | B69: =SUMIFS(Wallet_Transactions!$N$5:$N$3000,Wallet_Transactions!$D$5:$D$3000,"Reward Credit") -> 63500 | E69: Value issued to wallets.
A70: Redemption Volume (Posted) | B70: =-SUMIFS(Wallet_Transactions!$N$5:$N$3000,Wallet_Transactions!$D$5:$D$3000,"Redemption") -> 30200 | E70: Value taken out of wallets (shown positive).
A71: Reversal Transactions (count) | B71: =COUNTIFS(Wallet_Transactions!$D$5:$D$3000,"Reversal",Wallet_Transactions!$G$5:$G$3000,"Posted") -> 4 | E71: Posted reversal entries.
A72: Net Reversal Volume | B72: =SUMIFS(Wallet_Transactions!$N$5:$N$3000,Wallet_Transactions!$D$5:$D$3000,"Reversal") -> 100 | E72: Positive = value returned to users; negative = value clawed back.
A73: Net Adjustment Volume | B73: =SUMIFS(Wallet_Transactions!$N$5:$N$3000,Wallet_Transactions!$D$5:$D$3000,"Adjustment") -> 0 | E73: Manual corrections, net.
A74: Outstanding Wallet Balance (all users) | B74: =SUM(Wallet_Transactions!$N$5:$N$3000) -> 33400 | E74: Net Posted value held in wallets (a liability for VELOOP).
A75: Failed / Voided Transaction Rate | B75: =IFERROR((COUNTIF(Wallet_Transactions!$G$5:$G$3000,"Failed")+COUNTIF(Wallet_Transactions!$G$5:$G$3000,"Voided"))/B68,0) -> 0.0069204152 | C75: =Settings!B19 -> 0.02 | D75: =IF(B75<=C75,"On track","Above target") -> On track | E75: (Failed + Voided) / all transactions.
A76: Wallet Reversal Rate | B76: =IFERROR(B71/(COUNTIFS(Wallet_Transactions!$D$5:$D$3000,"Reward Credit",Wallet_Transactions!$G$5:$G$3000,"Posted")+COUNTIFS(Wallet_Transactions!$D$5:$D$3000,"Redemption",Wallet_Transactions!$G$5:$G$3000,"Posted")),0) -> 0.014388489 | E76: Reversals / (Posted Reward Credits + Redemptions).
A77: Users with Negative Balance | B77: =COUNTIF(Wallet_Balances!$G$5:$G$24,"<0") -> 0 | E77: Should be 0; otherwise ledger error or missing credits.
A78: Transactions using Proposed types | B78: =COUNTIF(Wallet_Transactions!$L$5:$L$3000,"Proposed") -> 0 | E78: Rows whose type is not yet confirmed as supported.
A80: 8. DATA QUALITY & RECONCILIATION | B80: Flags | C80: Target | D80: Status | E80: Meaning
A81: Wallet_Transactions data-check flags | B81: =COUNTIF(Wallet_Transactions!$Q$5:$Q$3000,"CHECK*") -> 0 | C81: 0 | D81: =IF(B81<=C81,"On track","Above target") -> On track | E81: Type, unit, sign or reversal-link problems.
A82: Withdrawals data-check flags | B82: =COUNTIF(Withdrawals!$K$5:$K$1000,"CHECK*") -> 0 | C82: 0 | D82: =IF(B82<=C82,"On track","Above target") -> On track | E82: Status / timestamp / reason inconsistencies.
A83: Withdrawal vs wallet reconciliation exceptions | B83: =COUNTIF(Withdrawals!$T$5:$T$1000,"CHECK*") -> 0 | C83: 0 | D83: =IF(B83<=C83,"On track","Above target") -> On track | E83: Completed without debit, reversed without reversal entry, or unexpected debit.
A85: 9. WALLET TRANSACTION TYPES | B85: Transactions | C85: Posted Signed Volume | D85: Support Status
A86: =Transaction_Types!A5 -> Reward Credit | B86: =COUNTIF(Wallet_Transactions!$D$5:$D$3000,$A86) -> 252 | C86: =SUMIFS(Wallet_Transactions!$N$5:$N$3000,Wallet_Transactions!$D$5:$D$3000,$A86) -> 63500 | D86: =Transaction_Types!B5 -> Supported
A87: =Transaction_Types!A6 -> Redemption | B87: =COUNTIF(Wallet_Transactions!$D$5:$D$3000,$A87) -> 30 | C87: =SUMIFS(Wallet_Transactions!$N$5:$N$3000,Wallet_Transactions!$D$5:$D$3000,$A87) -> -30200 | D87: =Transaction_Types!B6 -> Supported
A88: =Transaction_Types!A7 -> Reversal | B88: =COUNTIF(Wallet_Transactions!$D$5:$D$3000,$A88) -> 4 | C88: =SUMIFS(Wallet_Transactions!$N$5:$N$3000,Wallet_Transactions!$D$5:$D$3000,$A88) -> 100 | D88: =Transaction_Types!B7 -> Supported
A89: =Transaction_Types!A8 -> Adjustment | B89: =COUNTIF(Wallet_Transactions!$D$5:$D$3000,$A89) -> 3 | C89: =SUMIFS(Wallet_Transactions!$N$5:$N$3000,Wallet_Transactions!$D$5:$D$3000,$A89) -> 0 | D89: =Transaction_Types!B8 -> Supported
A90: =Transaction_Types!A9 -> Withdrawal Hold | B90: =COUNTIF(Wallet_Transactions!$D$5:$D$3000,$A90) -> 0 | C90: =SUMIFS(Wallet_Transactions!$N$5:$N$3000,Wallet_Transactions!$D$5:$D$3000,$A90) -> 0 | D90: =Transaction_Types!B9 -> Proposed
A91: =Transaction_Types!A10 -> Hold Release | B91: =COUNTIF(Wallet_Transactions!$D$5:$D$3000,$A91) -> 0 | C91: =SUMIFS(Wallet_Transactions!$N$5:$N$3000,Wallet_Transactions!$D$5:$D$3000,$A91) -> 0 | D91: =Transaction_Types!B10 -> Proposed
A92: =Transaction_Types!A11 -> Fee / Charge | B92: =COUNTIF(Wallet_Transactions!$D$5:$D$3000,$A92) -> 0 | C92: =SUMIFS(Wallet_Transactions!$N$5:$N$3000,Wallet_Transactions!$D$5:$D$3000,$A92) -> 0 | D92: =Transaction_Types!B11 -> Proposed
A93: =Transaction_Types!A12 -> Expiry | B93: =COUNTIF(Wallet_Transactions!$D$5:$D$3000,$A93) -> 0 | C93: =SUMIFS(Wallet_Transactions!$N$5:$N$3000,Wallet_Transactions!$D$5:$D$3000,$A93) -> 0 | D93: =Transaction_Types!B12 -> Proposed

Sheet Withdrawals
A1: Withdrawals (D2) - one row per withdrawal request
A2: Blue = input (replace sample rows with real data). Grey = formulas (copy down for new rows). Rule: Processing Timestamp = when review/payout work started; Final Timestamp = when a terminal state (Completed / Rejected / Reversed / Cancelled) was reached.
A4: Withdrawal ID | B4: User ID | C4: Requested Amount | D4: Unit | E4: Method | F4: Requested Timestamp | G4: Processing Timestamp | H4: Final Timestamp | I4: Status | J4: Reason Category | K4: Data Check | L4: Is Pending (1/0) | M4: Queue Wait Hrs (Requested to Processing) | N4: Processing Hrs (Processing to Final, Completed) | O4: End-to-End Hrs (Requested to Final, Completed) | P4: SLA Met? (Completed) | Q4: Hrs to Rejection (Rejected) | R4: Pending Age Hrs (as-of) | S4: First Request of User (1/0) | T4: Wallet Reconciliation
A5: WD-0001 | B5: U002 | C5: 800 | D5: Points | E5: E-Wallet | F5: 46270.307 | G5: 46271.061 | H5: 46272.148 | I5: Completed | K5: =IF(ISNA(MATCH(I5,Withdrawal_Lifecycle!$A$5:$A$11,0)),"CHECK status",IF(AND(I5="Requested",OR(G5<>"",H5<>"")),"CHECK timestamps",IF(AND(OR(I5="Under Review",I5="Processing"),OR(G5="",H5<>"")),"CHECK timestamps",IF(AND(OR(I5="Completed",I5="Reversed",I5="Rejected"),OR(G5="",H5="")),"CHECK timestamps",IF(AND(I5="Cancelled",H5=""),"CHECK timestamps",IF(OR(AND(G5<>"",G5<F5),AND(H5<>"",H5<IF(G5<>"",G5,F5))),"CHECK order",IF(AND(OR(I5="Rejected",I5="Reversed"),J5=""),"CHECK reason","OK"))))))) -> OK | L5: =IF(OR(I5="Requested",I5="Under Review",I5="Processing"),1,0) -> 0 | M5: =IF(G5="","",(G5-F5)*24) -> 18.085751 | N5: =IF(AND(I5="Completed",G5<>"",H5<>""),(H5-G5)*24,"") -> 26.092326 | O5: =IF(AND(I5="Completed",H5<>""),(H5-F5)*24,"") -> 44.178077 | P5: =IF(O5="","",IF(O5<=Settings!$B$8,"Yes","No")) -> Yes | Q5: =IF(AND(I5="Rejected",H5<>""),(H5-F5)*24,"") | R5: =IF(L5=1,(Settings!$B$5-F5)*24,"") | S5: =IF(COUNTIF($B$5:B5,B5)=1,1,0) -> 1 | T5: =IF(I5="Completed",IF(COUNTIFS(Wallet_Transactions!$I$5:$I$3000,A5,Wallet_Transactions!$D$5:$D$3000,"Redemption",Wallet_Transactions!$G$5:$G$3000,"Posted")>=1,"OK","CHECK no debit"),IF(I5="Reversed",IF(AND(COUNTIFS(Wallet_Transactions!$I$5:$I$3000,A5,Wallet_Transactions!$D$5:$D$3000,"Redemption",Wallet_Transactions!$G$5:$G$3000,"Posted")>=1,COUNTIFS(Wallet_Transactions!$I$5:$I$3000,A5,Wallet_Transactions!$D$5:$D$3000,"Reversal",Wallet_Transactions!$G$5:$G$3000,"Posted")>=1),"OK","CHECK no reversal"),IF(COUNTIFS(Wallet_Transactions!$I$5:$I$3000,A5,Wallet_Transactions!$D$5:$D$3000,"Redemption",Wallet_Transactions!$G$5:$G$3000,"Posted")>0,"CHECK unexpected debit","OK"))) -> OK
A6: WD-0002 | B6: U006 | C6: 1100 | D6: Points | E6: Bank Transfer | F6: 46271.551 | G6: 46272.447 | H6: 46273.29 | I6: Completed | K6: =IF(ISNA(MATCH(I6,Withdrawal_Lifecycle!$A$5:$A$11,0)),"CHECK status",IF(AND(I6="Requested",OR(G6<>"",H6<>"")),"CHECK timestamps",IF(AND(OR(I6="Under Review",I6="Processing"),OR(G6="",H6<>"")),"CHECK timestamps",IF(AND(OR(I6="Completed",I6="Reversed",I6="Rejected"),OR(G6="",H6="")),"CHECK timestamps",IF(AND(I6="Cancelled",H6=""),"CHECK timestamps",IF(OR(AND(G6<>"",G6<F6),AND(H6<>"",H6<IF(G6<>"",G6,F6))),"CHECK order",IF(AND(OR(I6="Rejected",I6="Reversed"),J6=""),"CHECK reason","OK"))))))) -> OK | L6: =IF(OR(I6="Requested",I6="Under Review",I6="Processing"),1,0) -> 0 | M6: =IF(G6="","",(G6-F6)*24) -> 21.505025 | N6: =IF(AND(I6="Completed",G6<>"",H6<>""),(H6-G6)*24,"") -> 20.223598 | O6: =IF(AND(I6="Completed",H6<>""),(H6-F6)*24,"") -> 41.728623 | P6: =IF(O6="","",IF(O6<=Settings!$B$8,"Yes","No")) -> Yes | Q6: =IF(AND(I6="Rejected",H6<>""),(H6-F6)*24,"") | R6: =IF(L6=1,(Settings!$B$5-F6)*24,"") | S6: =IF(COUNTIF($B$5:B6,B6)=1,1,0) -> 1 | T6: =IF(I6="Completed",IF(COUNTIFS(Wallet_Transactions!$I$5:$I$3000,A6,Wallet_Transactions!$D$5:$D$3000,"Redemption",Wallet_Transactions!$G$5:$G$3000,"Posted")>=1,"OK","CHECK no debit"),IF(I6="Reversed",IF(AND(COUNTIFS(Wallet_Transactions!$I$5:$I$3000,A6,Wallet_Transactions!$D$5:$D$3000,"Redemption",Wallet_Transactions!$G$5:$G$3000,"Posted")>=1,COUNTIFS(Wallet_Transactions!$I$5:$I$3000,A6,Wallet_Transactions!$D$5:$D$3000,"Reversal",Wallet_Transactions!$G$5:$G$3000,"Posted")>=1),"OK","CHECK no reversal"),IF(COUNTIFS(Wallet_Transactions!$I$5:$I$3000,A6,Wallet_Transactions!$D$5:$D$3000,"Redemption",Wallet_Transactions!$G$5:$G$3000,"Posted")>0,"CHECK unexpected debit","OK"))) -> OK
A7: WD-0003 | B7: U003 | C7: 1950 | D7: Points | E7: E-Wallet | F7: 46273.069 | G7: 46273.324 | H7: 46274.984 | I7: Completed | K7: =IF(ISNA(MATCH(I7,Withdrawal_Lifecycle!$A$5:$A$11,0)),"CHECK status",IF(AND(I7="Requested",OR(G7<>"",H7<>"")),"CHECK timestamps",IF(AND(OR(I7="Under Review",I7="Processing"),OR(G7="",H7<>"")),"CHECK timestamps",IF(AND(OR(I7="Completed",I7="Reversed",I7="Rejected"),OR(G7="",H7="")),"CHECK timestamps",IF(AND(I7="Cancelled",H7=""),"CHECK timestamps",IF(OR(AND(G7<>"",G7<F7),AND(H7<>"",H7<IF(G7<>"",G7,F7))),"CHECK order",IF(AND(OR(I7="Rejected",I7="Reversed"),J7=""),"CHECK reason","OK"))))))) -> OK | L7: =IF(OR(I7="Requested",I7="Under Review",I7="Processing"),1,0) -> 0 | M7: =IF(G7="","",(G7-F7)*24) -> 6.1251639 | N7: =IF(AND(I7="Completed",G7<>"",H7<>""),(H7-G7)*24,"") -> 39.843158 | O7: =IF(AND(I7="Completed",H7<>""),(H7-F7)*24,"") -> 45.968322 | P7: =IF(O7="","",IF(O7<=Settings!$B$8,"Yes","No")) -> Yes | Q7: =IF(AND(I7="Rejected",H7<>""),(H7-F7)*24,"") | R7: =IF(L7=1,(Settings!$B$5-F7)*24,"") | S7: =IF(COUNTIF($B$5:B7,B7)=1,1,0) -> 1 | T7: =IF(I7="Completed",IF(COUNTIFS(Wallet_Transactions!$I$5:$I$3000,A7,Wallet_Transactions!$D$5:$D$3000,"Redemption",Wallet_Transactions!$G$5:$G$3000,"Posted")>=1,"OK","CHECK no debit"),IF(I7="Reversed",IF(AND(COUNTIFS(Wallet_Transactions!$I$5:$I$3000,A7,Wallet_Transactions!$D$5:$D$3000,"Redemption",Wallet_Transactions!$G$5:$G$3000,"Posted")>=1,COUNTIFS(Wallet_Transactions!$I$5:$I$3000,A7,Wallet_Transactions!$D$5:$D$3000,"Reversal",Wallet_Transactions!$G$5:$G$3000,"Posted")>=1),"OK","CHECK no reversal"),IF(COUNTIFS(Wallet_Transactions!$I$5:$I$3000,A7,Wallet_Transactions!$D$5:$D$3000,"Redemption",Wallet_Transactions!$G$5:$G$3000,"Posted")>0,"CHECK unexpected debit","OK"))) -> OK
A8: WD-0004 | B8: U015 | C8: 550 | D8: Points | E8: Other | F8: 46274.96 | G8: 46275.873 | H8: 46277.984 | I8: Completed | K8: =IF(ISNA(MATCH(I8,Withdrawal_Lifecycle!$A$5:$A$11,0)),"CHECK status",IF(AND(I8="Requested",OR(G8<>"",H8<>"")),"CHECK timestamps",IF(AND(OR(I8="Under Review",I8="Processing"),OR(G8="",H8<>"")),"CHECK timestamps",IF(AND(OR(I8="Completed",I8="Reversed",I8="Rejected"),OR(G8="",H8="")),"CHECK timestamps",IF(AND(I8="Cancelled",H8=""),"CHECK timestamps",IF(OR(AND(G8<>"",G8<F8),AND(H8<>"",H8<IF(G8<>"",G8,F8))),"CHECK order",IF(AND(OR(I8="Rejected",I8="Reversed"),J8=""),"CHECK reason","OK"))))))) -> OK | L8: =IF(OR(I8="Requested",I8="Under Review",I8="Processing"),1,0) -> 0 | M8: =IF(G8="","",(G8-F8)*24) -> 21.898631 | N8: =IF(AND(I8="Completed",G8<>"",H8<>""),(H8-G8)*24,"") -> 50.669366 | O8: =IF(AND(I8="Completed",H8<>""),(H8-F8)*24,"") -> 72.567997 | P8: =IF(O8="","",IF(O8<=Settings!$B$8,"Yes","No")) -> No | Q8: =IF(AND(I8="Rejected",H8<>""),(H8-F8)*24,"") | R8: =IF(L8=1,(Settings!$B$5-F8)*24,"") | S8: =IF(COUNTIF($B$5:B8,B8)=1,1,0) -> 1 | T8: =IF(I8="Completed",IF(COUNTIFS(Wallet_Transactions!$I$5:$I$3000,A8,Wallet_Transactions!$D$5:$D$3000,"Redemption",Wallet_Transactions!$G$5:$G$3000,"Posted")>=1,"OK","CHECK no debit"),IF(I8="Reversed",IF(AND(COUNTIFS(Wallet_Transactions!$I$5:$I$3000,A8,Wallet_Transactions!$D$5:$D$3000,"Redemption",Wallet_Transactions!$G$5:$G$3000,"Posted")>=1,COUNTIFS(Wallet_Transactions!$I$5:$I$3000,A8,Wallet_Transactions!$D$5:$D$3000,"Reversal",Wallet_Transactions!$G$5:$G$3000,"Posted")>=1),"OK","CHECK no reversal"),IF(COUNTIFS(Wallet_Transactions!$I$5:$I$3000,A8,Wallet_Transactions!$D$5:$D$3000,"Redemption",Wallet_Transactions!$G$5:$G$3000,"Posted")>0,"CHECK unexpected debit","OK"))) -> OK
A9: WD-0005 | B9: U015 | C9: 750 | D9: Points | E9: Bank Transfer | F9: 46278.524 | G9: 46278.641 | H9: 46278.92 | I9: Completed | K9: =IF(ISNA(MATCH(I9,Withdrawal_Lifecycle!$A$5:$A$11,0)),"CHECK status",IF(AND(I9="Requested",OR(G9<>"",H9<>"")),"CHECK timestamps",IF(AND(OR(I9="Under Review",I9="Processing"),OR(G9="",H9<>"")),"CHECK timestamps",IF(AND(OR(I9="Completed",I9="Reversed",I9="Rejected"),OR(G9="",H9="")),"CHECK timestamps",IF(AND(I9="Cancelled",H9=""),"CHECK timestamps",IF(OR(AND(G9<>"",G9<F9),AND(H9<>"",H9<IF(G9<>"",G9,F9))),"CHECK order",IF(AND(OR(I9="Rejected",I9="Reversed"),J9=""),"CHECK reason","OK"))))))) -> OK | L9: =IF(OR(I9="Requested",I9="Under Review",I9="Processing"),1,0) -> 0 | M9: =IF(G9="","",(G9-F9)*24) -> 2.8081394 | N9: =IF(AND(I9="Completed",G9<>"",H9<>""),(H9-G9)*24,"") -> 6.6842523 | O9: =IF(AND(I9="Completed",H9<>""),(H9-F9)*24,"") -> 9.4923917 | P9: =IF(O9="","",IF(O9<=Settings!$B$8,"Yes","No")) -> Yes | Q9: =IF(AND(I9="Rejected",H9<>""),(H9-F9)*24,"") | R9: =IF(L9=1,(Settings!$B$5-F9)*24,"") | S9: =IF(COUNTIF($B$5:B9,B9)=1,1,0) -> 0 | T9: =IF(I9="Completed",IF(COUNTIFS(Wallet_Transactions!$I$5:$I$3000,A9,Wallet_Transactions!$D$5:$D$3000,"Redemption",Wallet_Transactions!$G$5:$G$3000,"Posted")>=1,"OK","CHECK no debit"),IF(I9="Reversed",IF(AND(COUNTIFS(Wallet_Transactions!$I$5:$I$3000,A9,Wallet_Transactions!$D$5:$D$3000,"Redemption",Wallet_Transactions!$G$5:$G$3000,"Posted")>=1,COUNTIFS(Wallet_Transactions!$I$5:$I$3000,A9,Wallet_Transactions!$D$5:$D$3000,"Reversal",Wallet_Transactions!$G$5:$G$3000,"Posted")>=1),"OK","CHECK no reversal"),IF(COUNTIFS(Wallet_Transactions!$I$5:$I$3000,A9,Wallet_Transactions!$D$5:$D$3000,"Redemption",Wallet_Transactions!$G$5:$G$3000,"Posted")>0,"CHECK unexpected debit","OK"))) -> OK
A10: WD-0006 | B10: U004 | C10: 1350 | D10: Points | E10: Bank Transfer | F10: 46278.826 | H10: 46279.005 | I10: Cancelled | J10: User Request | K10: =IF(ISNA(MATCH(I10,Withdrawal_Lifecycle!$A$5:$A$11,0)),"CHECK status",IF(AND(I10="Requested",OR(G10<>"",H10<>"")),"CHECK timestamps",IF(AND(OR(I10="Under Review",I10="Processing"),OR(G10="",H10<>"")),"CHECK timestamps",IF(AND(OR(I10="Completed",I10="Reversed",I10="Rejected"),OR(G10="",H10="")),"CHECK timestamps",IF(AND(I10="Cancelled",H10=""),"CHECK timestamps",IF(OR(AND(G10<>"",G10<F10),AND(H10<>"",H10<IF(G10<>"",G10,F10))),"CHECK order",IF(AND(OR(I10="Rejected",I10="Reversed"),J10=""),"CHECK reason","OK"))))))) -> OK | L10: =IF(OR(I10="Requested",I10="Under Review",I10="Processing"),1,0) -> 0 | M10: =IF(G10="","",(G10-F10)*24) | N10: =IF(AND(I10="Completed",G10<>"",H10<>""),(H10-G10)*24,"") | O10: =IF(AND(I10="Completed",H10<>""),(H10-F10)*24,"") | P10: =IF(O10="","",IF(O10<=Settings!$B$8,"Yes","No")) | Q10: =IF(AND(I10="Rejected",H10<>""),(H10-F10)*24,"") | R10: =IF(L10=1,(Settings!$B$5-F10)*24,"") | S10: =IF(COUNTIF($B$5:B10,B10)=1,1,0) -> 1 | T10: =IF(I10="Completed",IF(COUNTIFS(Wallet_Transactions!$I$5:$I$3000,A10,Wallet_Transactions!$D$5:$D$3000,"Redemption",Wallet_Transactions!$G$5:$G$3000,"Posted")>=1,"OK","CHECK no debit"),IF(I10="Reversed",IF(AND(COUNTIFS(Wallet_Transactions!$I$5:$I$3000,A10,Wallet_Transactions!$D$5:$D$3000,"Redemption",Wallet_Transactions!$G$5:$G$3000,"Posted")>=1,COUNTIFS(Wallet_Transactions!$I$5:$I$3000,A10,Wallet_Transactions!$D$5:$D$3000,"Reversal",Wallet_Transactions!$G$5:$G$3000,"Posted")>=1),"OK","CHECK no reversal"),IF(COUNTIFS(Wallet_Transactions!$I$5:$I$3000,A10,Wallet_Transactions!$D$5:$D$3000,"Redemption",Wallet_Transactions!$G$5:$G$3000,"Posted")>0,"CHECK unexpected debit","OK"))) -> OK
A11: WD-0007 | B11: U010 | C11: 1800 | D11: Points | E11: E-Wallet | F11: 46279.015 | G11: 46279.143 | H11: 46280.331 | I11: Rejected | J11: Verification Failed | K11: =IF(ISNA(MATCH(I11,Withdrawal_Lifecycle!$A$5:$A$11,0)),"CHECK status",IF(AND(I11="Requested",OR(G11<>"",H11<>"")),"CHECK timestamps",IF(AND(OR(I11="Under Review",I11="Processing"),OR(G11="",H11<>"")),"CHECK timestamps",IF(AND(OR(I11="Completed",I11="Reversed",I11="Rejected"),OR(G11="",H11="")),"CHECK timestamps",IF(AND(I11="Cancelled",H11=""),"CHECK timestamps",IF(OR(AND(G11<>"",G11<F11),AND(H11<>"",H11<IF(G11<>"",G11,F11))),"CHECK order",IF(AND(OR(I11="Rejected",I11="Reversed"),J11=""),"CHECK reason","OK"))))))) -> OK | L11: =IF(OR(I11="Requested",I11="Under Review",I11="Processing"),1,0) -> 0 | M11: =IF(G11="","",(G11-F11)*24) -> 3.0889277 | N11: =IF(AND(I11="Completed",G11<>"",H11<>""),(H11-G11)*24,"") | O11: =IF(AND(I11="Completed",H11<>""),(H11-F11)*24,"") | P11: =IF(O11="","",IF(O11<=Settings!$B$8,"Yes","No")) | Q11: =IF(AND(I11="Rejected",H11<>""),(H11-F11)*24,"") -> 31.593931 | R11: =IF(L11=1,(Settings!$B$5-F11)*24,"") | S11: =IF(COUNTIF($B$5:B11,B11)=1,1,0) -> 1 | T11: =IF(I11="Completed",IF(COUNTIFS(Wallet_Transactions!$I$5:$I$3000,A11,Wallet_Transactions!$D$5:$D$3000,"Redemption",Wallet_Transactions!$G$5:$G$3000,"Posted")>=1,"OK","CHECK no debit"),IF(I11="Reversed",IF(AND(COUNTIFS(Wallet_Transactions!$I$5:$I$3000,A11,Wallet_Transactions!$D$5:$D$3000,"Redemption",Wallet_Transactions!$G$5:$G$3000,"Posted")>=1,COUNTIFS(Wallet_Transactions!$I$5:$I$3000,A11,Wallet_Transactions!$D$5:$D$3000,"Reversal",Wallet_Transactions!$G$5:$G$3000,"Posted")>=1),"OK","CHECK no reversal"),IF(COUNTIFS(Wallet_Transactions!$I$5:$I$3000,A11,Wallet_Transactions!$D$5:$D$3000,"Redemption",Wallet_Transactions!$G$5:$G$3000,"Posted")>0,"CHECK unexpected debit","OK"))) -> OK
A12: WD-0008 | B12: U015 | C12: 800 | D12: Points | E12: E-Wallet | F12: 46279.121 | G12: 46280.048 | H12: 46281.278 | I12: Completed | K12: =IF(ISNA(MATCH(I12,Withdrawal_Lifecycle!$A$5:$A$11,0)),"CHECK status",IF(AND(I12="Requested",OR(G12<>"",H12<>"")),"CHECK timestamps",IF(AND(OR(I12="Under Review",I12="Processing"),OR(G12="",H12<>"")),"CHECK timestamps",IF(AND(OR(I12="Completed",I12="Reversed",I12="Rejected"),OR(G12="",H12="")),"CHECK timestamps",IF(AND(I12="Cancelled",H12=""),"CHECK timestamps",IF(OR(AND(G12<>"",G12<F12),AND(H12<>"",H12<IF(G12<>"",G12,F12))),"CHECK order",IF(AND(OR(I12="Rejected",I12="Reversed"),J12=""),"CHECK reason","OK"))))))) -> OK | L12: =IF(OR(I12="Requested",I12="Under Review",I12="Processing"),1,0) -> 0 | M12: =IF(G12="","",(G12-F12)*24) -> 22.250934 | N12: =IF(AND(I12="Completed",G12<>"",H12<>""),(H12-G12)*24,"") -> 29.522992 | O12: =IF(AND(I12="Completed",H12<>""),(H12-F12)*24,"") -> 51.773926 | P12: =IF(O12="","",IF(O12<=Settings!$B$8,"Yes","No")) -> No | Q12: =IF(AND(I12="Rejected",H12<>""),(H12-F12)*24,"") | R12: =IF(L12=1,(Settings!$B$5-F12)*24,"") | S12: =IF(COUNTIF($B$5:B12,B12)=1,1,0) -> 0 | T12: =IF(I12="Completed",IF(COUNTIFS(Wallet_Transactions!$I$5:$I$3000,A12,Wallet_Transactions!$D$5:$D$3000,"Redemption",Wallet_Transactions!$G$5:$G$3000,"Posted")>=1,"OK","CHECK no debit"),IF(I12="Reversed",IF(AND(COUNTIFS(Wallet_Transactions!$I$5:$I$3000,A12,Wallet_Transactions!$D$5:$D$3000,"Redemption",Wallet_Transactions!$G$5:$G$3000,"Posted")>=1,COUNTIFS(Wallet_Transactions!$I$5:$I$3000,A12,Wallet_Transactions!$D$5:$D$3000,"Reversal",Wallet_Transactions!$G$5:$G$3000,"Posted")>=1),"OK","CHECK no reversal"),IF(COUNTIFS(Wallet_Transactions!$I$5:$I$3000,A12,Wallet_Transactions!$D$5:$D$3000,"Redemption",Wallet_Transactions!$G$5:$G$3000,"Posted")>0,"CHECK unexpected debit","OK"))) -> OK
A13: WD-0009 | B13: U008 | C13: 1750 | D13: Points | E13: E-Wallet | F13: 46279.34 | G13: 46279.858 | H13: 46280.849 | I13: Completed | K13: =IF(ISNA(MATCH(I13,Withdrawal_Lifecycle!$A$5:$A$11,0)),"CHECK status",IF(AND(I13="Requested",OR(G13<>"",H13<>"")),"CHECK timestamps",IF(AND(OR(I13="Under Review",I13="Processing"),OR(G13="",H13<>"")),"CHECK timestamps",IF(AND(OR(I13="Completed",I13="Reversed",I13="Rejected"),OR(G13="",H13="")),"CHECK timestamps",IF(AND(I13="Cancelled",H13=""),"CHECK timestamps",IF(OR(AND(G13<>"",G13<F13),AND(H13<>"",H13<IF(G13<>"",G13,F13))),"CHECK order",IF(AND(OR(I13="Rejected",I13="Reversed"),J13=""),"CHECK reason","OK"))))))) -> OK | L13: =IF(OR(I13="Requested",I13="Under Review",I13="Processing"),1,0) -> 0 | M13: =IF(G13="","",(G13-F13)*24) -> 12.440792 | N13: =IF(AND(I13="Completed",G13<>"",H13<>""),(H13-G13)*24,"") -> 23.782924 | O13: =IF(AND(I13="Completed",H13<>""),(H13-F13)*24,"") -> 36.223716 | P13: =IF(O13="","",IF(O13<=Settings!$B$8,"Yes","No")) -> Yes | Q13: =IF(AND(I13="Rejected",H13<>""),(H13-F13)*24,"") | R13: =IF(L13=1,(Settings!$B$5-F13)*24,"") | S13: =IF(COUNTIF($B$5:B13,B13)=1,1,0) -> 1 | T13: =IF(I13="Completed",IF(COUNTIFS(Wallet_Transactions!$I$5:$I$3000,A13,Wallet_Transactions!$D$5:$D$3000,"Redemption",Wallet_Transactions!$G$5:$G$3000,"Posted")>=1,"OK","CHECK no debit"),IF(I13="Reversed",IF(AND(COUNTIFS(Wallet_Transactions!$I$5:$I$3000,A13,Wallet_Transactions!$D$5:$D$3000,"Redemption",Wallet_Transactions!$G$5:$G$3000,"Posted")>=1,COUNTIFS(Wallet_Transactions!$I$5:$I$3000,A13,Wallet_Transactions!$D$5:$D$3000,"Reversal",Wallet_Transactions!$G$5:$G$3000,"Posted")>=1),"OK","CHECK no reversal"),IF(COUNTIFS(Wallet_Transactions!$I$5:$I$3000,A13,Wallet_Transactions!$D$5:$D$3000,"Redemption",Wallet_Transactions!$G$5:$G$3000,"Posted")>0,"CHECK unexpected debit","OK"))) -> OK
A14: WD-0010 | B14: U002 | C14: 900 | D14: Points | E14: Bank Transfer | F14: 46280.078 | G14: 46280.176 | H14: 46281.723 | I14: Completed | K14: =IF(ISNA(MATCH(I14,Withdrawal_Lifecycle!$A$5:$A$11,0)),"CHECK status",IF(AND(I14="Requested",OR(G14<>"",H14<>"")),"CHECK timestamps",IF(AND(OR(I14="Under Review",I14="Processing"),OR(G14="",H14<>"")),"CHECK timestamps",IF(AND(OR(I14="Completed",I14="Reversed",I14="Rejected"),OR(G14="",H14="")),"CHECK timestamps",IF(AND(I14="Cancelled",H14=""),"CHECK timestamps",IF(OR(AND(G14<>"",G14<F14),AND(H14<>"",H14<IF(G14<>"",G14,F14))),"CHECK order",IF(AND(OR(I14="Rejected",I14="Reversed"),J14=""),"CHECK reason","OK"))))))) -> OK | L14: =IF(OR(I14="Requested",I14="Under Review",I14="Processing"),1,0) -> 0 | M14: =IF(G14="","",(G14-F14)*24) -> 2.3541264 | N14: =IF(AND(I14="Completed",G14<>"",H14<>""),(H14-G14)*24,"") -> 37.125745 | O14: =IF(AND(I14="Completed",H14<>""),(H14-F14)*24,"") -> 39.479871 | P14: =IF(O14="","",IF(O14<=Settings!$B$8,"Yes","No")) -> Yes | Q14: =IF(AND(I14="Rejected",H14<>""),(H14-F14)*24,"") | R14: =IF(L14=1,(Settings!$B$5-F14)*24,"") | S14: =IF(COUNTIF($B$5:B14,B14)=1,1,0) -> 0 | T14: =IF(I14="Completed",IF(COUNTIFS(Wallet_Transactions!$I$5:$I$3000,A14,Wallet_Transactions!$D$5:$D$3000,"Redemption",Wallet_Transactions!$G$5:$G$3000,"Posted")>=1,"OK","CHECK no debit"),IF(I14="Reversed",IF(AND(COUNTIFS(Wallet_Transactions!$I$5:$I$3000,A14,Wallet_Transactions!$D$5:$D$3000,"Redemption",Wallet_Transactions!$G$5:$G$3000,"Posted")>=1,COUNTIFS(Wallet_Transactions!$I$5:$I$3000,A14,Wallet_Transactions!$D$5:$D$3000,"Reversal",Wallet_Transactions!$G$5:$G$3000,"Posted")>=1),"OK","CHECK no reversal"),IF(COUNTIFS(Wallet_Transactions!$I$5:$I$3000,A14,Wallet_Transactions!$D$5:$D$3000,"Redemption",Wallet_Transactions!$G$5:$G$3000,"Posted")>0,"CHECK unexpected debit","OK"))) -> OK
A15: WD-0011 | B15: U011 | C15: 2000 | D15: Points | E15: E-Wallet | F15: 46280.321 | H15: 46280.365 | I15: Cancelled | J15: User Request | K15: =IF(ISNA(MATCH(I15,Withdrawal_Lifecycle!$A$5:$A$11,0)),"CHECK status",IF(AND(I15="Requested",OR(G15<>"",H15<>"")),"CHECK timestamps",IF(AND(OR(I15="Under Review",I15="Processing"),OR(G15="",H15<>"")),"CHECK timestamps",IF(AND(OR(I15="Completed",I15="Reversed",I15="Rejected"),OR(G15="",H15="")),"CHECK timestamps",IF(AND(I15="Cancelled",H15=""),"CHECK timestamps",IF(OR(AND(G15<>"",G15<F15),AND(H15<>"",H15<IF(G15<>"",G15,F15))),"CHECK order",IF(AND(OR(I15="Rejected",I15="Reversed"),J15=""),"CHECK reason","OK"))))))) -> OK | L15: =IF(OR(I15="Requested",I15="Under Review",I15="Processing"),1,0) -> 0 | M15: =IF(G15="","",(G15-F15)*24) | N15: =IF(AND(I15="Completed",G15<>"",H15<>""),(H15-G15)*24,"") | O15: =IF(AND(I15="Completed",H15<>""),(H15-F15)*24,"") | P15: =IF(O15="","",IF(O15<=Settings!$B$8,"Yes","No")) | Q15: =IF(AND(I15="Rejected",H15<>""),(H15-F15)*24,"") | R15: =IF(L15=1,(Settings!$B$5-F15)*24,"") | S15: =IF(COUNTIF($B$5:B15,B15)=1,1,0) -> 1 | T15: =IF(I15="Completed",IF(COUNTIFS(Wallet_Transactions!$I$5:$I$3000,A15,Wallet_Transactions!$D$5:$D$3000,"Redemption",Wallet_Transactions!$G$5:$G$3000,"Posted")>=1,"OK","CHECK no debit"),IF(I15="Reversed",IF(AND(COUNTIFS(Wallet_Transactions!$I$5:$I$3000,A15,Wallet_Transactions!$D$5:$D$3000,"Redemption",Wallet_Transactions!$G$5:$G$3000,"Posted")>=1,COUNTIFS(Wallet_Transactions!$I$5:$I$3000,A15,Wallet_Transactions!$D$5:$D$3000,"Reversal",Wallet_Transactions!$G$5:$G$3000,"Posted")>=1),"OK","CHECK no reversal"),IF(COUNTIFS(Wallet_Transactions!$I$5:$I$3000,A15,Wallet_Transactions!$D$5:$D$3000,"Redemption",Wallet_Transactions!$G$5:$G$3000,"Posted")>0,"CHECK unexpected debit","OK"))) -> OK
A16: WD-0012 | B16: U011 | C16: 1950 | D16: Points | E16: Gift Card | F16: 46280.369 | G16: 46280.394 | H16: 46282.304 | I16: Completed | K16: =IF(ISNA(MATCH(I16,Withdrawal_Lifecycle!$A$5:$A$11,0)),"CHECK status",IF(AND(I16="Requested",OR(G16<>"",H16<>"")),"CHECK timestamps",IF(AND(OR(I16="Under Review",I16="Processing"),OR(G16="",H16<>"")),"CHECK timestamps",IF(AND(OR(I16="Completed",I16="Reversed",I16="Rejected"),OR(G16="",H16="")),"CHECK timestamps",IF(AND(I16="Cancelled",H16=""),"CHECK timestamps",IF(OR(AND(G16<>"",G16<F16),AND(H16<>"",H16<IF(G16<>"",G16,F16))),"CHECK order",IF(AND(OR(I16="Rejected",I16="Reversed"),J16=""),"CHECK reason","OK"))))))) -> OK | L16: =IF(OR(I16="Requested",I16="Under Review",I16="Processing"),1,0) -> 0 | M16: =IF(G16="","",(G16-F16)*24) -> 0.61126267 | N16: =IF(AND(I16="Completed",G16<>"",H16<>""),(H16-G16)*24,"") -> 45.827838 | O16: =IF(AND(I16="Completed",H16<>""),(H16-F16)*24,"") -> 46.4391 | P16: =IF(O16="","",IF(O16<=Settings!$B$8,"Yes","No")) -> Yes | Q16: =IF(AND(I16="Rejected",H16<>""),(H16-F16)*24,"") | R16: =IF(L16=1,(Settings!$B$5-F16)*24,"") | S16: =IF(COUNTIF($B$5:B16,B16)=1,1,0) -> 0 | T16: =IF(I16="Completed",IF(COUNTIFS(Wallet_Transactions!$I$5:$I$3000,A16,Wallet_Transactions!$D$5:$D$3000,"Redemption",Wallet_Transactions!$G$5:$G$3000,"Posted")>=1,"OK","CHECK no debit"),IF(I16="Reversed",IF(AND(COUNTIFS(Wallet_Transactions!$I$5:$I$3000,A16,Wallet_Transactions!$D$5:$D$3000,"Redemption",Wallet_Transactions!$G$5:$G$3000,"Posted")>=1,COUNTIFS(Wallet_Transactions!$I$5:$I$3000,A16,Wallet_Transactions!$D$5:$D$3000,"Reversal",Wallet_Transactions!$G$5:$G$3000,"Posted")>=1),"OK","CHECK no reversal"),IF(COUNTIFS(Wallet_Transactions!$I$5:$I$3000,A16,Wallet_Transactions!$D$5:$D$3000,"Redemption",Wallet_Transactions!$G$5:$G$3000,"Posted")>0,"CHECK unexpected debit","OK"))) -> OK
A17: WD-0013 | B17: U003 | C17: 500 | D17: Points | E17: Gift Card | F17: 46280.504 | G17: 46280.657 | H17: 46281.861 | I17: Rejected | J17: Suspected Fraud | K17: =IF(ISNA(MATCH(I17,Withdrawal_Lifecycle!$A$5:$A$11,0)),"CHECK status",IF(AND(I17="Requested",OR(G17<>"",H17<>"")),"CHECK timestamps",IF(AND(OR(I17="Under Review",I17="Processing"),OR(G17="",H17<>"")),"CHECK timestamps",IF(AND(OR(I17="Completed",I17="Reversed",I17="Rejected"),OR(G17="",H17="")),"CHECK timestamps",IF(AND(I17="Cancelled",H17=""),"CHECK timestamps",IF(OR(AND(G17<>"",G17<F17),AND(H17<>"",H17<IF(G17<>"",G17,F17))),"CHECK order",IF(AND(OR(I17="Rejected",I17="Reversed"),J17=""),"CHECK reason","OK"))))))) -> OK | L17: =IF(OR(I17="Requested",I17="Under Review",I17="Processing"),1,0) -> 0 | M17: =IF(G17="","",(G17-F17)*24) -> 3.6642104 | N17: =IF(AND(I17="Completed",G17<>"",H17<>""),(H17-G17)*24,"") | O17: =IF(AND(I17="Completed",H17<>""),(H17-F17)*24,"") | P17: =IF(O17="","",IF(O17<=Settings!$B$8,"Yes","No")) | Q17: =IF(AND(I17="Rejected",H17<>""),(H17-F17)*24,"") -> 32.571487 | R17: =IF(L17=1,(Settings!$B$5-F17)*24,"") | S17: =IF(COUNTIF($B$5:B17,B17)=1,1,0) -> 0 | T17: =IF(I17="Completed",IF(COUNTIFS(Wallet_Transactions!$I$5:$I$3000,A17,Wallet_Transactions!$D$5:$D$3000,"Redemption",Wallet_Transactions!$G$5:$G$3000,"Posted")>=1,"OK","CHECK no debit"),IF(I17="Reversed",IF(AND(COUNTIFS(Wallet_Transactions!$I$5:$I$3000,A17,Wallet_Transactions!$D$5:$D$3000,"Redemption",Wallet_Transactions!$G$5:$G$3000,"Posted")>=1,COUNTIFS(Wallet_Transactions!$I$5:$I$3000,A17,Wallet_Transactions!$D$5:$D$3000,"Reversal",Wallet_Transactions!$G$5:$G$3000,"Posted")>=1),"OK","CHECK no reversal"),IF(COUNTIFS(Wallet_Transactions!$I$5:$I$3000,A17,Wallet_Transactions!$D$5:$D$3000,"Redemption",Wallet_Transactions!$G$5:$G$3000,"Posted")>0,"CHECK unexpected debit","OK"))) -> OK
A18: WD-0014 | B18: U009 | C18: 1950 | D18: Points | E18: Bank Transfer | F18: 46281.708 | G18: 46282.335 | H18: 46284.661 | I18: Completed | K18: =IF(ISNA(MATCH(I18,Withdrawal_Lifecycle!$A$5:$A$11,0)),"CHECK status",IF(AND(I18="Requested",OR(G18<>"",H18<>"")),"CHECK timestamps",IF(AND(OR(I18="Under Review",I18="Processing"),OR(G18="",H18<>"")),"CHECK timestamps",IF(AND(OR(I18="Completed",I18="Reversed",I18="Rejected"),OR(G18="",H18="")),"CHECK timestamps",IF(AND(I18="Cancelled",H18=""),"CHECK timestamps",IF(OR(AND(G18<>"",G18<F18),AND(H18<>"",H18<IF(G18<>"",G18,F18))),"CHECK order",IF(AND(OR(I18="Rejected",I18="Reversed"),J18=""),"CHECK reason","OK"))))))) -> OK | L18: =IF(OR(I18="Requested",I18="Under Review",I18="Processing"),1,0) -> 0 | M18: =IF(G18="","",(G18-F18)*24) -> 15.057478 | N18: =IF(AND(I18="Completed",G18<>"",H18<>""),(H18-G18)*24,"") -> 55.829766 | O18: =IF(AND(I18="Completed",H18<>""),(H18-F18)*24,"") -> 70.887245 | P18: =IF(O18="","",IF(O18<=Settings!$B$8,"Yes","No")) -> No | Q18: =IF(AND(I18="Rejected",H18<>""),(H18-F18)*24,"") | R18: =IF(L18=1,(Settings!$B$5-F18)*24,"") | S18: =IF(COUNTIF($B$5:B18,B18)=1,1,0) -> 1 | T18: =IF(I18="Completed",IF(COUNTIFS(Wallet_Transactions!$I$5:$I$3000,A18,Wallet_Transactions!$D$5:$D$3000,"Redemption",Wallet_Transactions!$G$5:$G$3000,"Posted")>=1,"OK","CHECK no debit"),IF(I18="Reversed",IF(AND(COUNTIFS(Wallet_Transactions!$I$5:$I$3000,A18,Wallet_Transactions!$D$5:$D$3000,"Redemption",Wallet_Transactions!$G$5:$G$3000,"Posted")>=1,COUNTIFS(Wallet_Transactions!$I$5:$I$3000,A18,Wallet_Transactions!$D$5:$D$3000,"Reversal",Wallet_Transactions!$G$5:$G$3000,"Posted")>=1),"OK","CHECK no reversal"),IF(COUNTIFS(Wallet_Transactions!$I$5:$I$3000,A18,Wallet_Transactions!$D$5:$D$3000,"Redemption",Wallet_Transactions!$G$5:$G$3000,"Posted")>0,"CHECK unexpected debit","OK"))) -> OK
A19: WD-0015 | B19: U010 | C19: 1800 | D19: Points | E19: E-Wallet | F19: 46282.061 | G19: 46282.268 | H19: 46282.693 | I19: Rejected | J19: Duplicate Request | K19: =IF(ISNA(MATCH(I19,Withdrawal_Lifecycle!$A$5:$A$11,0)),"CHECK status",IF(AND(I19="Requested",OR(G19<>"",H19<>"")),"CHECK timestamps",IF(AND(OR(I19="Under Review",I19="Processing"),OR(G19="",H19<>"")),"CHECK timestamps",IF(AND(OR(I19="Completed",I19="Reversed",I19="Rejected"),OR(G19="",H19="")),"CHECK timestamps",IF(AND(I19="Cancelled",H19=""),"CHECK timestamps",IF(OR(AND(G19<>"",G19<F19),AND(H19<>"",H19<IF(G19<>"",G19,F19))),"CHECK order",IF(AND(OR(I19="Rejected",I19="Reversed"),J19=""),"CHECK reason","OK"))))))) -> OK | L19: =IF(OR(I19="Requested",I19="Under Review",I19="Processing"),1,0) -> 0 | M19: =IF(G19="","",(G19-F19)*24) -> 4.9637993 | N19: =IF(AND(I19="Completed",G19<>"",H19<>""),(H19-G19)*24,"") | O19: =IF(AND(I19="Completed",H19<>""),(H19-F19)*24,"") | P19: =IF(O19="","",IF(O19<=Settings!$B$8,"Yes","No")) | Q19: =IF(AND(I19="Rejected",H19<>""),(H19-F19)*24,"") -> 15.173357 | R19: =IF(L19=1,(Settings!$B$5-F19)*24,"") | S19: =IF(COUNTIF($B$5:B19,B19)=1,1,0) -> 0 | T19: =IF(I19="Completed",IF(COUNTIFS(Wallet_Transactions!$I$5:$I$3000,A19,Wallet_Transactions!$D$5:$D$3000,"Redemption",Wallet_Transactions!$G$5:$G$3000,"Posted")>=1,"OK","CHECK no debit"),IF(I19="Reversed",IF(AND(COUNTIFS(Wallet_Transactions!$I$5:$I$3000,A19,Wallet_Transactions!$D$5:$D$3000,"Redemption",Wallet_Transactions!$G$5:$G$3000,"Posted")>=1,COUNTIFS(Wallet_Transactions!$I$5:$I$3000,A19,Wallet_Transactions!$D$5:$D$3000,"Reversal",Wallet_Transactions!$G$5:$G$3000,"Posted")>=1),"OK","CHECK no reversal"),IF(COUNTIFS(Wallet_Transactions!$I$5:$I$3000,A19,Wallet_Transactions!$D$5:$D$3000,"Redemption",Wallet_Transactions!$G$5:$G$3000,"Posted")>0,"CHECK unexpected debit","OK"))) -> OK
A20: WD-0016 | B20: U020 | C20: 600 | D20: Points | E20: Bank Transfer | F20: 46283.294 | G20: 46283.796 | H20: 46284.266 | I20: Completed | K20: =IF(ISNA(MATCH(I20,Withdrawal_Lifecycle!$A$5:$A$11,0)),"CHECK status",IF(AND(I20="Requested",OR(G20<>"",H20<>"")),"CHECK timestamps",IF(AND(OR(I20="Under Review",I20="Processing"),OR(G20="",H20<>"")),"CHECK timestamps",IF(AND(OR(I20="Completed",I20="Reversed",I20="Rejected"),OR(G20="",H20="")),"CHECK timestamps",IF(AND(I20="Cancelled",H20=""),"CHECK timestamps",IF(OR(AND(G20<>"",G20<F20),AND(H20<>"",H20<IF(G20<>"",G20,F20))),"CHECK order",IF(AND(OR(I20="Rejected",I20="Reversed"),J20=""),"CHECK reason","OK"))))))) -> OK | L20: =IF(OR(I20="Requested",I20="Under Review",I20="Processing"),1,0) -> 0 | M20: =IF(G20="","",(G20-F20)*24) -> 12.05472 | N20: =IF(AND(I20="Completed",G20<>"",H20<>""),(H20-G20)*24,"") -> 11.276368 | O20: =IF(AND(I20="Completed",H20<>""),(H20-F20)*24,"") -> 23.331088 | P20: =IF(O20="","",IF(O20<=Settings!$B$8,"Yes","No")) -> Yes | Q20: =IF(AND(I20="Rejected",H20<>""),(H20-F20)*24,"") | R20: =IF(L20=1,(Settings!$B$5-F20)*24,"") | S20: =IF(COUNTIF($B$5:B20,B20)=1,1,0) -> 1 | T20: =IF(I20="Completed",IF(COUNTIFS(Wallet_Transactions!$I$5:$I$3000,A20,Wallet_Transactions!$D$5:$D$3000,"Redemption",Wallet_Transactions!$G$5:$G$3000,"Posted")>=1,"OK","CHECK no debit"),IF(I20="Reversed",IF(AND(COUNTIFS(Wallet_Transactions!$I$5:$I$3000,A20,Wallet_Transactions!$D$5:$D$3000,"Redemption",Wallet_Transactions!$G$5:$G$3000,"Posted")>=1,COUNTIFS(Wallet_Transactions!$I$5:$I$3000,A20,Wallet_Transactions!$D$5:$D$3000,"Reversal",Wallet_Transactions!$G$5:$G$3000,"Posted")>=1),"OK","CHECK no reversal"),IF(COUNTIFS(Wallet_Transactions!$I$5:$I$3000,A20,Wallet_Transactions!$D$5:$D$3000,"Redemption",Wallet_Transactions!$G$5:$G$3000,"Posted")>0,"CHECK unexpected debit","OK"))) -> OK
A21: WD-0017 | B21: U002 | C21: 1250 | D21: Points | E21: Gift Card | F21: 46283.422 | G21: 46283.843 | H21: 46286.296 | I21: Completed | K21: =IF(ISNA(MATCH(I21,Withdrawal_Lifecycle!$A$5:$A$11,0)),"CHECK status",IF(AND(I21="Requested",OR(G21<>"",H21<>"")),"CHECK timestamps",IF(AND(OR(I21="Under Review",I21="Processing"),OR(G21="",H21<>"")),"CHECK timestamps",IF(AND(OR(I21="Completed",I21="Reversed",I21="Rejected"),OR(G21="",H21="")),"CHECK timestamps",IF(AND(I21="Cancelled",H21=""),"CHECK timestamps",IF(OR(AND(G21<>"",G21<F21),AND(H21<>"",H21<IF(G21<>"",G21,F21))),"CHECK order",IF(AND(OR(I21="Rejected",I21="Reversed"),J21=""),"CHECK reason","OK"))))))) -> OK | L21: =IF(OR(I21="Requested",I21="Under Review",I21="Processing"),1,0) -> 0 | M21: =IF(G21="","",(G21-F21)*24) -> 10.109871 | N21: =IF(AND(I21="Completed",G21<>"",H21<>""),(H21-G21)*24,"") -> 58.854835 | O21: =IF(AND(I21="Completed",H21<>""),(H21-F21)*24,"") -> 68.964706 | P21: =IF(O21="","",IF(O21<=Settings!$B$8,"Yes","No")) -> No | Q21: =IF(AND(I21="Rejected",H21<>""),(H21-F21)*24,"") | R21: =IF(L21=1,(Settings!$B$5-F21)*24,"") | S21: =IF(COUNTIF($B$5:B21,B21)=1,1,0) -> 0 | T21: =IF(I21="Completed",IF(COUNTIFS(Wallet_Transactions!$I$5:$I$3000,A21,Wallet_Transactions!$D$5:$D$3000,"Redemption",Wallet_Transactions!$G$5:$G$3000,"Posted")>=1,"OK","CHECK no debit"),IF(I21="Reversed",IF(AND(COUNTIFS(Wallet_Transactions!$I$5:$I$3000,A21,Wallet_Transactions!$D$5:$D$3000,"Redemption",Wallet_Transactions!$G$5:$G$3000,"Posted")>=1,COUNTIFS(Wallet_Transactions!$I$5:$I$3000,A21,Wallet_Transactions!$D$5:$D$3000,"Reversal",Wallet_Transactions!$G$5:$G$3000,"Posted")>=1),"OK","CHECK no reversal"),IF(COUNTIFS(Wallet_Transactions!$I$5:$I$3000,A21,Wallet_Transactions!$D$5:$D$3000,"Redemption",Wallet_Transactions!$G$5:$G$3000,"Posted")>0,"CHECK unexpected debit","OK"))) -> OK
A22: WD-0018 | B22: U003 | C22: 900 | D22: Points | E22: Other | F22: 46284.186 | G22: 46284.463 | H22: 46285.564 | I22: Completed | K22: =IF(ISNA(MATCH(I22,Withdrawal_Lifecycle!$A$5:$A$11,0)),"CHECK status",IF(AND(I22="Requested",OR(G22<>"",H22<>"")),"CHECK timestamps",IF(AND(OR(I22="Under Review",I22="Processing"),OR(G22="",H22<>"")),"CHECK timestamps",IF(AND(OR(I22="Completed",I22="Reversed",I22="Rejected"),OR(G22="",H22="")),"CHECK timestamps",IF(AND(I22="Cancelled",H22=""),"CHECK timestamps",IF(OR(AND(G22<>"",G22<F22),AND(H22<>"",H22<IF(G22<>"",G22,F22))),"CHECK order",IF(AND(OR(I22="Rejected",I22="Reversed"),J22=""),"CHECK reason","OK"))))))) -> OK | L22: =IF(OR(I22="Requested",I22="Under Review",I22="Processing"),1,0) -> 0 | M22: =IF(G22="","",(G22-F22)*24) -> 6.6460607 | N22: =IF(AND(I22="Completed",G22<>"",H22<>""),(H22-G22)*24,"") -> 26.421496 | O22: =IF(AND(I22="Completed",H22<>""),(H22-F22)*24,"") -> 33.067557 | P22: =IF(O22="","",IF(O22<=Settings!$B$8,"Yes","No")) -> Yes | Q22: =IF(AND(I22="Rejected",H22<>""),(H22-F22)*24,"") | R22: =IF(L22=1,(Settings!$B$5-F22)*24,"") | S22: =IF(COUNTIF($B$5:B22,B22)=1,1,0) -> 0 | T22: =IF(I22="Completed",IF(COUNTIFS(Wallet_Transactions!$I$5:$I$3000,A22,Wallet_Transactions!$D$5:$D$3000,"Redemption",Wallet_Transactions!$G$5:$G$3000,"Posted")>=1,"OK","CHECK no debit"),IF(I22="Reversed",IF(AND(COUNTIFS(Wallet_Transactions!$I$5:$I$3000,A22,Wallet_Transactions!$D$5:$D$3000,"Redemption",Wallet_Transactions!$G$5:$G$3000,"Posted")>=1,COUNTIFS(Wallet_Transactions!$I$5:$I$3000,A22,Wallet_Transactions!$D$5:$D$3000,"Reversal",Wallet_Transactions!$G$5:$G$3000,"Posted")>=1),"OK","CHECK no reversal"),IF(COUNTIFS(Wallet_Transactions!$I$5:$I$3000,A22,Wallet_Transactions!$D$5:$D$3000,"Redemption",Wallet_Transactions!$G$5:$G$3000,"Posted")>0,"CHECK unexpected debit","OK"))) -> OK
A23: WD-0019 | B23: U015 | C23: 750 | D23: Points | E23: E-Wallet | F23: 46285.385 | G23: 46285.918 | H23: 46287.5 | I23: Completed | K23: =IF(ISNA(MATCH(I23,Withdrawal_Lifecycle!$A$5:$A$11,0)),"CHECK status",IF(AND(I23="Requested",OR(G23<>"",H23<>"")),"CHECK timestamps",IF(AND(OR(I23="Under Review",I23="Processing"),OR(G23="",H23<>"")),"CHECK timestamps",IF(AND(OR(I23="Completed",I23="Reversed",I23="Rejected"),OR(G23="",H23="")),"CHECK timestamps",IF(AND(I23="Cancelled",H23=""),"CHECK timestamps",IF(OR(AND(G23<>"",G23<F23),AND(H23<>"",H23<IF(G23<>"",G23,F23))),"CHECK order",IF(AND(OR(I23="Rejected",I23="Reversed"),J23=""),"CHECK reason","OK"))))))) -> OK | L23: =IF(OR(I23="Requested",I23="Under Review",I23="Processing"),1,0) -> 0 | M23: =IF(G23="","",(G23-F23)*24) -> 12.796799 | N23: =IF(AND(I23="Completed",G23<>"",H23<>""),(H23-G23)*24,"") -> 37.977843 | O23: =IF(AND(I23="Completed",H23<>""),(H23-F23)*24,"") -> 50.774642 | P23: =IF(O23="","",IF(O23<=Settings!$B$8,"Yes","No")) -> No | Q23: =IF(AND(I23="Rejected",H23<>""),(H23-F23)*24,"") | R23: =IF(L23=1,(Settings!$B$5-F23)*24,"") | S23: =IF(COUNTIF($B$5:B23,B23)=1,1,0) -> 0 | T23: =IF(I23="Completed",IF(COUNTIFS(Wallet_Transactions!$I$5:$I$3000,A23,Wallet_Transactions!$D$5:$D$3000,"Redemption",Wallet_Transactions!$G$5:$G$3000,"Posted")>=1,"OK","CHECK no debit"),IF(I23="Reversed",IF(AND(COUNTIFS(Wallet_Transactions!$I$5:$I$3000,A23,Wallet_Transactions!$D$5:$D$3000,"Redemption",Wallet_Transactions!$G$5:$G$3000,"Posted")>=1,COUNTIFS(Wallet_Transactions!$I$5:$I$3000,A23,Wallet_Transactions!$D$5:$D$3000,"Reversal",Wallet_Transactions!$G$5:$G$3000,"Posted")>=1),"OK","CHECK no reversal"),IF(COUNTIFS(Wallet_Transactions!$I$5:$I$3000,A23,Wallet_Transactions!$D$5:$D$3000,"Redemption",Wallet_Transactions!$G$5:$G$3000,"Posted")>0,"CHECK unexpected debit","OK"))) -> OK
A24: WD-0020 | B24: U018 | C24: 1850 | D24: Points | E24: Bank Transfer | F24: 46286.489 | G24: 46287.443 | H24: 46288.752 | I24: Rejected | J24: Verification Failed | K24: =IF(ISNA(MATCH(I24,Withdrawal_Lifecycle!$A$5:$A$11,0)),"CHECK status",IF(AND(I24="Requested",OR(G24<>"",H24<>"")),"CHECK timestamps",IF(AND(OR(I24="Under Review",I24="Processing"),OR(G24="",H24<>"")),"CHECK timestamps",IF(AND(OR(I24="Completed",I24="Reversed",I24="Rejected"),OR(G24="",H24="")),"CHECK timestamps",IF(AND(I24="Cancelled",H24=""),"CHECK timestamps",IF(OR(AND(G24<>"",G24<F24),AND(H24<>"",H24<IF(G24<>"",G24,F24))),"CHECK order",IF(AND(OR(I24="Rejected",I24="Reversed"),J24=""),"CHECK reason","OK"))))))) -> OK | L24: =IF(OR(I24="Requested",I24="Under Review",I24="Processing"),1,0) -> 0 | M24: =IF(G24="","",(G24-F24)*24) -> 22.907216 | N24: =IF(AND(I24="Completed",G24<>"",H24<>""),(H24-G24)*24,"") | O24: =IF(AND(I24="Completed",H24<>""),(H24-F24)*24,"") | P24: =IF(O24="","",IF(O24<=Settings!$B$8,"Yes","No")) | Q24: =IF(AND(I24="Rejected",H24<>""),(H24-F24)*24,"") -> 54.317489 | R24: =IF(L24=1,(Settings!$B$5-F24)*24,"") | S24: =IF(COUNTIF($B$5:B24,B24)=1,1,0) -> 1 | T24: =IF(I24="Completed",IF(COUNTIFS(Wallet_Transactions!$I$5:$I$3000,A24,Wallet_Transactions!$D$5:$D$3000,"Redemption",Wallet_Transactions!$G$5:$G$3000,"Posted")>=1,"OK","CHECK no debit"),IF(I24="Reversed",IF(AND(COUNTIFS(Wallet_Transactions!$I$5:$I$3000,A24,Wallet_Transactions!$D$5:$D$3000,"Redemption",Wallet_Transactions!$G$5:$G$3000,"Posted")>=1,COUNTIFS(Wallet_Transactions!$I$5:$I$3000,A24,Wallet_Transactions!$D$5:$D$3000,"Reversal",Wallet_Transactions!$G$5:$G$3000,"Posted")>=1),"OK","CHECK no reversal"),IF(COUNTIFS(Wallet_Transactions!$I$5:$I$3000,A24,Wallet_Transactions!$D$5:$D$3000,"Redemption",Wallet_Transactions!$G$5:$G$3000,"Posted")>0,"CHECK unexpected debit","OK"))) -> OK
A25: WD-0021 | B25: U009 | C25: 750 | D25: Points | E25: Bank Transfer | F25: 46286.849 | G25: 46287.189 | H25: 46288.335 | I25: Completed | K25: =IF(ISNA(MATCH(I25,Withdrawal_Lifecycle!$A$5:$A$11,0)),"CHECK status",IF(AND(I25="Requested",OR(G25<>"",H25<>"")),"CHECK timestamps",IF(AND(OR(I25="Under Review",I25="Processing"),OR(G25="",H25<>"")),"CHECK timestamps",IF(AND(OR(I25="Completed",I25="Reversed",I25="Rejected"),OR(G25="",H25="")),"CHECK timestamps",IF(AND(I25="Cancelled",H25=""),"CHECK timestamps",IF(OR(AND(G25<>"",G25<F25),AND(H25<>"",H25<IF(G25<>"",G25,F25))),"CHECK order",IF(AND(OR(I25="Rejected",I25="Reversed"),J25=""),"CHECK reason","OK"))))))) -> OK | L25: =IF(OR(I25="Requested",I25="Under Review",I25="Processing"),1,0) -> 0 | M25: =IF(G25="","",(G25-F25)*24) -> 8.179884 | N25: =IF(AND(I25="Completed",G25<>"",H25<>""),(H25-G25)*24,"") -> 27.48507 | O25: =IF(AND(I25="Completed",H25<>""),(H25-F25)*24,"") -> 35.664954 | P25: =IF(O25="","",IF(O25<=Settings!$B$8,"Yes","No")) -> Yes | Q25: =IF(AND(I25="Rejected",H25<>""),(H25-F25)*24,"") | R25: =IF(L25=1,(Settings!$B$5-F25)*24,"") | S25: =IF(COUNTIF($B$5:B25,B25)=1,1,0) -> 0 | T25: =IF(I25="Completed",IF(COUNTIFS(Wallet_Transactions!$I$5:$I$3000,A25,Wallet_Transactions!$D$5:$D$3000,"Redemption",Wallet_Transactions!$G$5:$G$3000,"Posted")>=1,"OK","CHECK no debit"),IF(I25="Reversed",IF(AND(COUNTIFS(Wallet_Transactions!$I$5:$I$3000,A25,Wallet_Transactions!$D$5:$D$3000,"Redemption",Wallet_Transactions!$G$5:$G$3000,"Posted")>=1,COUNTIFS(Wallet_Transactions!$I$5:$I$3000,A25,Wallet_Transactions!$D$5:$D$3000,"Reversal",Wallet_Transactions!$G$5:$G$3000,"Posted")>=1),"OK","CHECK no reversal"),IF(COUNTIFS(Wallet_Transactions!$I$5:$I$3000,A25,Wallet_Transactions!$D$5:$D$3000,"Redemption",Wallet_Transactions!$G$5:$G$3000,"Posted")>0,"CHECK unexpected debit","OK"))) -> OK
A26: WD-0022 | B26: U008 | C26: 700 | D26: Points | E26: Bank Transfer | F26: 46288.038 | G26: 46289.175 | H26: 46289.713 | I26: Completed | K26: =IF(ISNA(MATCH(I26,Withdrawal_Lifecycle!$A$5:$A$11,0)),"CHECK status",IF(AND(I26="Requested",OR(G26<>"",H26<>"")),"CHECK timestamps",IF(AND(OR(I26="Under Review",I26="Processing"),OR(G26="",H26<>"")),"CHECK timestamps",IF(AND(OR(I26="Completed",I26="Reversed",I26="Rejected"),OR(G26="",H26="")),"CHECK timestamps",IF(AND(I26="Cancelled",H26=""),"CHECK timestamps",IF(OR(AND(G26<>"",G26<F26),AND(H26<>"",H26<IF(G26<>"",G26,F26))),"CHECK order",IF(AND(OR(I26="Rejected",I26="Reversed"),J26=""),"CHECK reason","OK"))))))) -> OK | L26: =IF(OR(I26="Requested",I26="Under Review",I26="Processing"),1,0) -> 0 | M26: =IF(G26="","",(G26-F26)*24) -> 27.273263 | N26: =IF(AND(I26="Completed",G26<>"",H26<>""),(H26-G26)*24,"") -> 12.918508 | O26: =IF(AND(I26="Completed",H26<>""),(H26-F26)*24,"") -> 40.191771 | P26: =IF(O26="","",IF(O26<=Settings!$B$8,"Yes","No")) -> Yes | Q26: =IF(AND(I26="Rejected",H26<>""),(H26-F26)*24,"") | R26: =IF(L26=1,(Settings!$B$5-F26)*24,"") | S26: =IF(COUNTIF($B$5:B26,B26)=1,1,0) -> 0 | T26: =IF(I26="Completed",IF(COUNTIFS(Wallet_Transactions!$I$5:$I$3000,A26,Wallet_Transactions!$D$5:$D$3000,"Redemption",Wallet_Transactions!$G$5:$G$3000,"Posted")>=1,"OK","CHECK no debit"),IF(I26="Reversed",IF(AND(COUNTIFS(Wallet_Transactions!$I$5:$I$3000,A26,Wallet_Transactions!$D$5:$D$3000,"Redemption",Wallet_Transactions!$G$5:$G$3000,"Posted")>=1,COUNTIFS(Wallet_Transactions!$I$5:$I$3000,A26,Wallet_Transactions!$D$5:$D$3000,"Reversal",Wallet_Transactions!$G$5:$G$3000,"Posted")>=1),"OK","CHECK no reversal"),IF(COUNTIFS(Wallet_Transactions!$I$5:$I$3000,A26,Wallet_Transactions!$D$5:$D$3000,"Redemption",Wallet_Transactions!$G$5:$G$3000,"Posted")>0,"CHECK unexpected debit","OK"))) -> OK
A27: WD-0023 | B27: U010 | C27: 850 | D27: Points | E27: E-Wallet | F27: 46289.14 | G27: 46289.445 | H27: 46291.482 | I27: Completed | K27: =IF(ISNA(MATCH(I27,Withdrawal_Lifecycle!$A$5:$A$11,0)),"CHECK status",IF(AND(I27="Requested",OR(G27<>"",H27<>"")),"CHECK timestamps",IF(AND(OR(I27="Under Review",I27="Processing"),OR(G27="",H27<>"")),"CHECK timestamps",IF(AND(OR(I27="Completed",I27="Reversed",I27="Rejected"),OR(G27="",H27="")),"CHECK timestamps",IF(AND(I27="Cancelled",H27=""),"CHECK timestamps",IF(OR(AND(G27<>"",G27<F27),AND(H27<>"",H27<IF(G27<>"",G27,F27))),"CHECK order",IF(AND(OR(I27="Rejected",I27="Reversed"),J27=""),"CHECK reason","OK"))))))) -> OK | L27: =IF(OR(I27="Requested",I27="Under Review",I27="Processing"),1,0) -> 0 | M27: =IF(G27="","",(G27-F27)*24) -> 7.3257379 | N27: =IF(AND(I27="Completed",G27<>"",H27<>""),(H27-G27)*24,"") -> 48.889688 | O27: =IF(AND(I27="Completed",H27<>""),(H27-F27)*24,"") -> 56.215426 | P27: =IF(O27="","",IF(O27<=Settings!$B$8,"Yes","No")) -> No | Q27: =IF(AND(I27="Rejected",H27<>""),(H27-F27)*24,"") | R27: =IF(L27=1,(Settings!$B$5-F27)*24,"") | S27: =IF(COUNTIF($B$5:B27,B27)=1,1,0) -> 0 | T27: =IF(I27="Completed",IF(COUNTIFS(Wallet_Transactions!$I$5:$I$3000,A27,Wallet_Transactions!$D$5:$D$3000,"Redemption",Wallet_Transactions!$G$5:$G$3000,"Posted")>=1,"OK","CHECK no debit"),IF(I27="Reversed",IF(AND(COUNTIFS(Wallet_Transactions!$I$5:$I$3000,A27,Wallet_Transactions!$D$5:$D$3000,"Redemption",Wallet_Transactions!$G$5:$G$3000,"Posted")>=1,COUNTIFS(Wallet_Transactions!$I$5:$I$3000,A27,Wallet_Transactions!$D$5:$D$3000,"Reversal",Wallet_Transactions!$G$5:$G$3000,"Posted")>=1),"OK","CHECK no reversal"),IF(COUNTIFS(Wallet_Transactions!$I$5:$I$3000,A27,Wallet_Transactions!$D$5:$D$3000,"Redemption",Wallet_Transactions!$G$5:$G$3000,"Posted")>0,"CHECK unexpected debit","OK"))) -> OK
A28: WD-0024 | B28: U002 | C28: 550 | D28: Points | E28: Bank Transfer | F28: 46289.311 | G28: 46290.417 | H28: 46291.059 | I28: Completed | K28: =IF(ISNA(MATCH(I28,Withdrawal_Lifecycle!$A$5:$A$11,0)),"CHECK status",IF(AND(I28="Requested",OR(G28<>"",H28<>"")),"CHECK timestamps",IF(AND(OR(I28="Under Review",I28="Processing"),OR(G28="",H28<>"")),"CHECK timestamps",IF(AND(OR(I28="Completed",I28="Reversed",I28="Rejected"),OR(G28="",H28="")),"CHECK timestamps",IF(AND(I28="Cancelled",H28=""),"CHECK timestamps",IF(OR(AND(G28<>"",G28<F28),AND(H28<>"",H28<IF(G28<>"",G28,F28))),"CHECK order",IF(AND(OR(I28="Rejected",I28="Reversed"),J28=""),"CHECK reason","OK"))))))) -> OK | L28: =IF(OR(I28="Requested",I28="Under Review",I28="Processing"),1,0) -> 0 | M28: =IF(G28="","",(G28-F28)*24) -> 26.543338 | N28: =IF(AND(I28="Completed",G28<>"",H28<>""),(H28-G28)*24,"") -> 15.404586 | O28: =IF(AND(I28="Completed",H28<>""),(H28-F28)*24,"") -> 41.947925 | P28: =IF(O28="","",IF(O28<=Settings!$B$8,"Yes","No")) -> Yes | Q28: =IF(AND(I28="Rejected",H28<>""),(H28-F28)*24,"") | R28: =IF(L28=1,(Settings!$B$5-F28)*24,"") | S28: =IF(COUNTIF($B$5:B28,B28)=1,1,0) -> 0 | T28: =IF(I28="Completed",IF(COUNTIFS(Wallet_Transactions!$I$5:$I$3000,A28,Wallet_Transactions!$D$5:$D$3000,"Redemption",Wallet_Transactions!$G$5:$G$3000,"Posted")>=1,"OK","CHECK no debit"),IF(I28="Reversed",IF(AND(COUNTIFS(Wallet_Transactions!$I$5:$I$3000,A28,Wallet_Transactions!$D$5:$D$3000,"Redemption",Wallet_Transactions!$G$5:$G$3000,"Posted")>=1,COUNTIFS(Wallet_Transactions!$I$5:$I$3000,A28,Wallet_Transactions!$D$5:$D$3000,"Reversal",Wallet_Transactions!$G$5:$G$3000,"Posted")>=1),"OK","CHECK no reversal"),IF(COUNTIFS(Wallet_Transactions!$I$5:$I$3000,A28,Wallet_Transactions!$D$5:$D$3000,"Redemption",Wallet_Transactions!$G$5:$G$3000,"Posted")>0,"CHECK unexpected debit","OK"))) -> OK
A29: WD-0025 | B29: U014 | C29: 550 | D29: Points | E29: Bank Transfer | F29: 46291.167 | G29: 46291.474 | H29: 46295.079 | I29: Reversed | J29: Duplicate Request | K29: =IF(ISNA(MATCH(I29,Withdrawal_Lifecycle!$A$5:$A$11,0)),"CHECK status",IF(AND(I29="Requested",OR(G29<>"",H29<>"")),"CHECK timestamps",IF(AND(OR(I29="Under Review",I29="Processing"),OR(G29="",H29<>"")),"CHECK timestamps",IF(AND(OR(I29="Completed",I29="Reversed",I29="Rejected"),OR(G29="",H29="")),"CHECK timestamps",IF(AND(I29="Cancelled",H29=""),"CHECK timestamps",IF(OR(AND(G29<>"",G29<F29),AND(H29<>"",H29<IF(G29<>"",G29,F29))),"CHECK order",IF(AND(OR(I29="Rejected",I29="Reversed"),J29=""),"CHECK reason","OK"))))))) -> OK | L29: =IF(OR(I29="Requested",I29="Under Review",I29="Processing"),1,0) -> 0 | M29: =IF(G29="","",(G29-F29)*24) -> 7.370334 | N29: =IF(AND(I29="Completed",G29<>"",H29<>""),(H29-G29)*24,"") | O29: =IF(AND(I29="Completed",H29<>""),(H29-F29)*24,"") | P29: =IF(O29="","",IF(O29<=Settings!$B$8,"Yes","No")) | Q29: =IF(AND(I29="Rejected",H29<>""),(H29-F29)*24,"") | R29: =IF(L29=1,(Settings!$B$5-F29)*24,"") | S29: =IF(COUNTIF($B$5:B29,B29)=1,1,0) -> 1 | T29: =IF(I29="Completed",IF(COUNTIFS(Wallet_Transactions!$I$5:$I$3000,A29,Wallet_Transactions!$D$5:$D$3000,"Redemption",Wallet_Transactions!$G$5:$G$3000,"Posted")>=1,"OK","CHECK no debit"),IF(I29="Reversed",IF(AND(COUNTIFS(Wallet_Transactions!$I$5:$I$3000,A29,Wallet_Transactions!$D$5:$D$3000,"Redemption",Wallet_Transactions!$G$5:$G$3000,"Posted")>=1,COUNTIFS(Wallet_Transactions!$I$5:$I$3000,A29,Wallet_Transactions!$D$5:$D$3000,"Reversal",Wallet_Transactions!$G$5:$G$3000,"Posted")>=1),"OK","CHECK no reversal"),IF(COUNTIFS(Wallet_Transactions!$I$5:$I$3000,A29,Wallet_Transactions!$D$5:$D$3000,"Redemption",Wallet_Transactions!$G$5:$G$3000,"Posted")>0,"CHECK unexpected debit","OK"))) -> OK
A30: WD-0026 | B30: U004 | C30: 1050 | D30: Points | E30: Gift Card | F30: 46292.434 | G30: 46292.673 | H30: 46294.214 | I30: Completed | K30: =IF(ISNA(MATCH(I30,Withdrawal_Lifecycle!$A$5:$A$11,0)),"CHECK status",IF(AND(I30="Requested",OR(G30<>"",H30<>"")),"CHECK timestamps",IF(AND(OR(I30="Under Review",I30="Processing"),OR(G30="",H30<>"")),"CHECK timestamps",IF(AND(OR(I30="Completed",I30="Reversed",I30="Rejected"),OR(G30="",H30="")),"CHECK timestamps",IF(AND(I30="Cancelled",H30=""),"CHECK timestamps",IF(OR(AND(G30<>"",G30<F30),AND(H30<>"",H30<IF(G30<>"",G30,F30))),"CHECK order",IF(AND(OR(I30="Rejected",I30="Reversed"),J30=""),"CHECK reason","OK"))))))) -> OK | L30: =IF(OR(I30="Requested",I30="Under Review",I30="Processing"),1,0) -> 0 | M30: =IF(G30="","",(G30-F30)*24) -> 5.7438906 | N30: =IF(AND(I30="Completed",G30<>"",H30<>""),(H30-G30)*24,"") -> 36.976447 | O30: =IF(AND(I30="Completed",H30<>""),(H30-F30)*24,"") -> 42.720337 | P30: =IF(O30="","",IF(O30<=Settings!$B$8,"Yes","No")) -> Yes | Q30: =IF(AND(I30="Rejected",H30<>""),(H30-F30)*24,"") | R30: =IF(L30=1,(Settings!$B$5-F30)*24,"") | S30: =IF(COUNTIF($B$5:B30,B30)=1,1,0) -> 0 | T30: =IF(I30="Completed",IF(COUNTIFS(Wallet_Transactions!$I$5:$I$3000,A30,Wallet_Transactions!$D$5:$D$3000,"Redemption",Wallet_Transactions!$G$5:$G$3000,"Posted")>=1,"OK","CHECK no debit"),IF(I30="Reversed",IF(AND(COUNTIFS(Wallet_Transactions!$I$5:$I$3000,A30,Wallet_Transactions!$D$5:$D$3000,"Redemption",Wallet_Transactions!$G$5:$G$3000,"Posted")>=1,COUNTIFS(Wallet_Transactions!$I$5:$I$3000,A30,Wallet_Transactions!$D$5:$D$3000,"Reversal",Wallet_Transactions!$G$5:$G$3000,"Posted")>=1),"OK","CHECK no reversal"),IF(COUNTIFS(Wallet_Transactions!$I$5:$I$3000,A30,Wallet_Transactions!$D$5:$D$3000,"Redemption",Wallet_Transactions!$G$5:$G$3000,"Posted")>0,"CHECK unexpected debit","OK"))) -> OK
A31: WD-0027 | B31: U001 | C31: 650 | D31: Points | E31: Bank Transfer | F31: 46292.559 | G31: 46293.452 | H31: 46294.381 | I31: Completed | K31: =IF(ISNA(MATCH(I31,Withdrawal_Lifecycle!$A$5:$A$11,0)),"CHECK status",IF(AND(I31="Requested",OR(G31<>"",H31<>"")),"CHECK timestamps",IF(AND(OR(I31="Under Review",I31="Processing"),OR(G31="",H31<>"")),"CHECK timestamps",IF(AND(OR(I31="Completed",I31="Reversed",I31="Rejected"),OR(G31="",H31="")),"CHECK timestamps",IF(AND(I31="Cancelled",H31=""),"CHECK timestamps",IF(OR(AND(G31<>"",G31<F31),AND(H31<>"",H31<IF(G31<>"",G31,F31))),"CHECK order",IF(AND(OR(I31="Rejected",I31="Reversed"),J31=""),"CHECK reason","OK"))))))) -> OK | L31: =IF(OR(I31="Requested",I31="Under Review",I31="Processing"),1,0) -> 0 | M31: =IF(G31="","",(G31-F31)*24) -> 21.43633 | N31: =IF(AND(I31="Completed",G31<>"",H31<>""),(H31-G31)*24,"") -> 22.282578 | O31: =IF(AND(I31="Completed",H31<>""),(H31-F31)*24,"") -> 43.718908 | P31: =IF(O31="","",IF(O31<=Settings!$B$8,"Yes","No")) -> Yes | Q31: =IF(AND(I31="Rejected",H31<>""),(H31-F31)*24,"") | R31: =IF(L31=1,(Settings!$B$5-F31)*24,"") | S31: =IF(COUNTIF($B$5:B31,B31)=1,1,0) -> 1 | T31: =IF(I31="Completed",IF(COUNTIFS(Wallet_Transactions!$I$5:$I$3000,A31,Wallet_Transactions!$D$5:$D$3000,"Redemption",Wallet_Transactions!$G$5:$G$3000,"Posted")>=1,"OK","CHECK no debit"),IF(I31="Reversed",IF(AND(COUNTIFS(Wallet_Transactions!$I$5:$I$3000,A31,Wallet_Transactions!$D$5:$D$3000,"Redemption",Wallet_Transactions!$G$5:$G$3000,"Posted")>=1,COUNTIFS(Wallet_Transactions!$I$5:$I$3000,A31,Wallet_Transactions!$D$5:$D$3000,"Reversal",Wallet_Transactions!$G$5:$G$3000,"Posted")>=1),"OK","CHECK no reversal"),IF(COUNTIFS(Wallet_Transactions!$I$5:$I$3000,A31,Wallet_Transactions!$D$5:$D$3000,"Redemption",Wallet_Transactions!$G$5:$G$3000,"Posted")>0,"CHECK unexpected debit","OK"))) -> OK
A32: WD-0028 | B32: U013 | C32: 700 | D32: Points | E32: E-Wallet | F32: 46292.562 | G32: 46293.812 | H32: 46293.988 | I32: Completed | K32: =IF(ISNA(MATCH(I32,Withdrawal_Lifecycle!$A$5:$A$11,0)),"CHECK status",IF(AND(I32="Requested",OR(G32<>"",H32<>"")),"CHECK timestamps",IF(AND(OR(I32="Under Review",I32="Processing"),OR(G32="",H32<>"")),"CHECK timestamps",IF(AND(OR(I32="Completed",I32="Reversed",I32="Rejected"),OR(G32="",H32="")),"CHECK timestamps",IF(AND(I32="Cancelled",H32=""),"CHECK timestamps",IF(OR(AND(G32<>"",G32<F32),AND(H32<>"",H32<IF(G32<>"",G32,F32))),"CHECK order",IF(AND(OR(I32="Rejected",I32="Reversed"),J32=""),"CHECK reason","OK"))))))) -> OK | L32: =IF(OR(I32="Requested",I32="Under Review",I32="Processing"),1,0) -> 0 | M32: =IF(G32="","",(G32-F32)*24) -> 29.996276 | N32: =IF(AND(I32="Completed",G32<>"",H32<>""),(H32-G32)*24,"") -> 4.2176878 | O32: =IF(AND(I32="Completed",H32<>""),(H32-F32)*24,"") -> 34.213964 | P32: =IF(O32="","",IF(O32<=Settings!$B$8,"Yes","No")) -> Yes | Q32: =IF(AND(I32="Rejected",H32<>""),(H32-F32)*24,"") | R32: =IF(L32=1,(Settings!$B$5-F32)*24,"") | S32: =IF(COUNTIF($B$5:B32,B32)=1,1,0) -> 1 | T32: =IF(I32="Completed",IF(COUNTIFS(Wallet_Transactions!$I$5:$I$3000,A32,Wallet_Transactions!$D$5:$D$3000,"Redemption",Wallet_Transactions!$G$5:$G$3000,"Posted")>=1,"OK","CHECK no debit"),IF(I32="Reversed",IF(AND(COUNTIFS(Wallet_Transactions!$I$5:$I$3000,A32,Wallet_Transactions!$D$5:$D$3000,"Redemption",Wallet_Transactions!$G$5:$G$3000,"Posted")>=1,COUNTIFS(Wallet_Transactions!$I$5:$I$3000,A32,Wallet_Transactions!$D$5:$D$3000,"Reversal",Wallet_Transactions!$G$5:$G$3000,"Posted")>=1),"OK","CHECK no reversal"),IF(COUNTIFS(Wallet_Transactions!$I$5:$I$3000,A32,Wallet_Transactions!$D$5:$D$3000,"Redemption",Wallet_Transactions!$G$5:$G$3000,"Posted")>0,"CHECK unexpected debit","OK"))) -> OK
A33: WD-0029 | B33: U008 | C33: 500 | D33: Points | E33: Bank Transfer | F33: 46292.977 | G33: 46293.501 | H33: 46294.146 | I33: Rejected | J33: Suspected Fraud | K33: =IF(ISNA(MATCH(I33,Withdrawal_Lifecycle!$A$5:$A$11,0)),"CHECK status",IF(AND(I33="Requested",OR(G33<>"",H33<>"")),"CHECK timestamps",IF(AND(OR(I33="Under Review",I33="Processing"),OR(G33="",H33<>"")),"CHECK timestamps",IF(AND(OR(I33="Completed",I33="Reversed",I33="Rejected"),OR(G33="",H33="")),"CHECK timestamps",IF(AND(I33="Cancelled",H33=""),"CHECK timestamps",IF(OR(AND(G33<>"",G33<F33),AND(H33<>"",H33<IF(G33<>"",G33,F33))),"CHECK order",IF(AND(OR(I33="Rejected",I33="Reversed"),J33=""),"CHECK reason","OK"))))))) -> OK | L33: =IF(OR(I33="Requested",I33="Under Review",I33="Processing"),1,0) -> 0 | M33: =IF(G33="","",(G33-F33)*24) -> 12.565349 | N33: =IF(AND(I33="Completed",G33<>"",H33<>""),(H33-G33)*24,"") | O33: =IF(AND(I33="Completed",H33<>""),(H33-F33)*24,"") | P33: =IF(O33="","",IF(O33<=Settings!$B$8,"Yes","No")) | Q33: =IF(AND(I33="Rejected",H33<>""),(H33-F33)*24,"") -> 28.06591 | R33: =IF(L33=1,(Settings!$B$5-F33)*24,"") | S33: =IF(COUNTIF($B$5:B33,B33)=1,1,0) -> 0 | T33: =IF(I33="Completed",IF(COUNTIFS(Wallet_Transactions!$I$5:$I$3000,A33,Wallet_Transactions!$D$5:$D$3000,"Redemption",Wallet_Transactions!$G$5:$G$3000,"Posted")>=1,"OK","CHECK no debit"),IF(I33="Reversed",IF(AND(COUNTIFS(Wallet_Transactions!$I$5:$I$3000,A33,Wallet_Transactions!$D$5:$D$3000,"Redemption",Wallet_Transactions!$G$5:$G$3000,"Posted")>=1,COUNTIFS(Wallet_Transactions!$I$5:$I$3000,A33,Wallet_Transactions!$D$5:$D$3000,"Reversal",Wallet_Transactions!$G$5:$G$3000,"Posted")>=1),"OK","CHECK no reversal"),IF(COUNTIFS(Wallet_Transactions!$I$5:$I$3000,A33,Wallet_Transactions!$D$5:$D$3000,"Redemption",Wallet_Transactions!$G$5:$G$3000,"Posted")>0,"CHECK unexpected debit","OK"))) -> OK
A34: WD-0030 | B34: U003 | C34: 850 | D34: Points | E34: Bank Transfer | F34: 46297.766 | G34: 46297.865 | H34: 46298.193 | I34: Completed | K34: =IF(ISNA(MATCH(I34,Withdrawal_Lifecycle!$A$5:$A$11,0)),"CHECK status",IF(AND(I34="Requested",OR(G34<>"",H34<>"")),"CHECK timestamps",IF(AND(OR(I34="Under Review",I34="Processing"),OR(G34="",H34<>"")),"CHECK timestamps",IF(AND(OR(I34="Completed",I34="Reversed",I34="Rejected"),OR(G34="",H34="")),"CHECK timestamps",IF(AND(I34="Cancelled",H34=""),"CHECK timestamps",IF(OR(AND(G34<>"",G34<F34),AND(H34<>"",H34<IF(G34<>"",G34,F34))),"CHECK order",IF(AND(OR(I34="Rejected",I34="Reversed"),J34=""),"CHECK reason","OK"))))))) -> OK | L34: =IF(OR(I34="Requested",I34="Under Review",I34="Processing"),1,0) -> 0 | M34: =IF(G34="","",(G34-F34)*24) -> 2.3664968 | N34: =IF(AND(I34="Completed",G34<>"",H34<>""),(H34-G34)*24,"") -> 7.8804905 | O34: =IF(AND(I34="Completed",H34<>""),(H34-F34)*24,"") -> 10.246987 | P34: =IF(O34="","",IF(O34<=Settings!$B$8,"Yes","No")) -> Yes | Q34: =IF(AND(I34="Rejected",H34<>""),(H34-F34)*24,"") | R34: =IF(L34=1,(Settings!$B$5-F34)*24,"") | S34: =IF(COUNTIF($B$5:B34,B34)=1,1,0) -> 0 | T34: =IF(I34="Completed",IF(COUNTIFS(Wallet_Transactions!$I$5:$I$3000,A34,Wallet_Transactions!$D$5:$D$3000,"Redemption",Wallet_Transactions!$G$5:$G$3000,"Posted")>=1,"OK","CHECK no debit"),IF(I34="Reversed",IF(AND(COUNTIFS(Wallet_Transactions!$I$5:$I$3000,A34,Wallet_Transactions!$D$5:$D$3000,"Redemption",Wallet_Transactions!$G$5:$G$3000,"Posted")>=1,COUNTIFS(Wallet_Transactions!$I$5:$I$3000,A34,Wallet_Transactions!$D$5:$D$3000,"Reversal",Wallet_Transactions!$G$5:$G$3000,"Posted")>=1),"OK","CHECK no reversal"),IF(COUNTIFS(Wallet_Transactions!$I$5:$I$3000,A34,Wallet_Transactions!$D$5:$D$3000,"Redemption",Wallet_Transactions!$G$5:$G$3000,"Posted")>0,"CHECK unexpected debit","OK"))) -> OK
A35: WD-0031 | B35: U007 | C35: 1500 | D35: Points | E35: Bank Transfer | F35: 46298.381 | G35: 46299.204 | H35: 46300.249 | I35: Completed | K35: =IF(ISNA(MATCH(I35,Withdrawal_Lifecycle!$A$5:$A$11,0)),"CHECK status",IF(AND(I35="Requested",OR(G35<>"",H35<>"")),"CHECK timestamps",IF(AND(OR(I35="Under Review",I35="Processing"),OR(G35="",H35<>"")),"CHECK timestamps",IF(AND(OR(I35="Completed",I35="Reversed",I35="Rejected"),OR(G35="",H35="")),"CHECK timestamps",IF(AND(I35="Cancelled",H35=""),"CHECK timestamps",IF(OR(AND(G35<>"",G35<F35),AND(H35<>"",H35<IF(G35<>"",G35,F35))),"CHECK order",IF(AND(OR(I35="Rejected",I35="Reversed"),J35=""),"CHECK reason","OK"))))))) -> OK | L35: =IF(OR(I35="Requested",I35="Under Review",I35="Processing"),1,0) -> 0 | M35: =IF(G35="","",(G35-F35)*24) -> 19.765221 | N35: =IF(AND(I35="Completed",G35<>"",H35<>""),(H35-G35)*24,"") -> 25.070784 | O35: =IF(AND(I35="Completed",H35<>""),(H35-F35)*24,"") -> 44.836005 | P35: =IF(O35="","",IF(O35<=Settings!$B$8,"Yes","No")) -> Yes | Q35: =IF(AND(I35="Rejected",H35<>""),(H35-F35)*24,"") | R35: =IF(L35=1,(Settings!$B$5-F35)*24,"") | S35: =IF(COUNTIF($B$5:B35,B35)=1,1,0) -> 1 | T35: =IF(I35="Completed",IF(COUNTIFS(Wallet_Transactions!$I$5:$I$3000,A35,Wallet_Transactions!$D$5:$D$3000,"Redemption",Wallet_Transactions!$G$5:$G$3000,"Posted")>=1,"OK","CHECK no debit"),IF(I35="Reversed",IF(AND(COUNTIFS(Wallet_Transactions!$I$5:$I$3000,A35,Wallet_Transactions!$D$5:$D$3000,"Redemption",Wallet_Transactions!$G$5:$G$3000,"Posted")>=1,COUNTIFS(Wallet_Transactions!$I$5:$I$3000,A35,Wallet_Transactions!$D$5:$D$3000,"Reversal",Wallet_Transactions!$G$5:$G$3000,"Posted")>=1),"OK","CHECK no reversal"),IF(COUNTIFS(Wallet_Transactions!$I$5:$I$3000,A35,Wallet_Transactions!$D$5:$D$3000,"Redemption",Wallet_Transactions!$G$5:$G$3000,"Posted")>0,"CHECK unexpected debit","OK"))) -> OK
A36: WD-0032 | B36: U013 | C36: 1550 | D36: Points | E36: E-Wallet | F36: 46300.372 | G36: 46301.564 | H36: 46302.402 | I36: Completed | K36: =IF(ISNA(MATCH(I36,Withdrawal_Lifecycle!$A$5:$A$11,0)),"CHECK status",IF(AND(I36="Requested",OR(G36<>"",H36<>"")),"CHECK timestamps",IF(AND(OR(I36="Under Review",I36="Processing"),OR(G36="",H36<>"")),"CHECK timestamps",IF(AND(OR(I36="Completed",I36="Reversed",I36="Rejected"),OR(G36="",H36="")),"CHECK timestamps",IF(AND(I36="Cancelled",H36=""),"CHECK timestamps",IF(OR(AND(G36<>"",G36<F36),AND(H36<>"",H36<IF(G36<>"",G36,F36))),"CHECK order",IF(AND(OR(I36="Rejected",I36="Reversed"),J36=""),"CHECK reason","OK"))))))) -> OK | L36: =IF(OR(I36="Requested",I36="Under Review",I36="Processing"),1,0) -> 0 | M36: =IF(G36="","",(G36-F36)*24) -> 28.619071 | N36: =IF(AND(I36="Completed",G36<>"",H36<>""),(H36-G36)*24,"") -> 20.116989 | O36: =IF(AND(I36="Completed",H36<>""),(H36-F36)*24,"") -> 48.73606 | P36: =IF(O36="","",IF(O36<=Settings!$B$8,"Yes","No")) -> No | Q36: =IF(AND(I36="Rejected",H36<>""),(H36-F36)*24,"") | R36: =IF(L36=1,(Settings!$B$5-F36)*24,"") | S36: =IF(COUNTIF($B$5:B36,B36)=1,1,0) -> 0 | T36: =IF(I36="Completed",IF(COUNTIFS(Wallet_Transactions!$I$5:$I$3000,A36,Wallet_Transactions!$D$5:$D$3000,"Redemption",Wallet_Transactions!$G$5:$G$3000,"Posted")>=1,"OK","CHECK no debit"),IF(I36="Reversed",IF(AND(COUNTIFS(Wallet_Transactions!$I$5:$I$3000,A36,Wallet_Transactions!$D$5:$D$3000,"Redemption",Wallet_Transactions!$G$5:$G$3000,"Posted")>=1,COUNTIFS(Wallet_Transactions!$I$5:$I$3000,A36,Wallet_Transactions!$D$5:$D$3000,"Reversal",Wallet_Transactions!$G$5:$G$3000,"Posted")>=1),"OK","CHECK no reversal"),IF(COUNTIFS(Wallet_Transactions!$I$5:$I$3000,A36,Wallet_Transactions!$D$5:$D$3000,"Redemption",Wallet_Transactions!$G$5:$G$3000,"Posted")>0,"CHECK unexpected debit","OK"))) -> OK
A37: WD-0033 | B37: U015 | C37: 800 | D37: Points | E37: Bank Transfer | F37: 46301.064 | G37: 46302.147 | H37: 46304.639 | I37: Completed | K37: =IF(ISNA(MATCH(I37,Withdrawal_Lifecycle!$A$5:$A$11,0)),"CHECK status",IF(AND(I37="Requested",OR(G37<>"",H37<>"")),"CHECK timestamps",IF(AND(OR(I37="Under Review",I37="Processing"),OR(G37="",H37<>"")),"CHECK timestamps",IF(AND(OR(I37="Completed",I37="Reversed",I37="Rejected"),OR(G37="",H37="")),"CHECK timestamps",IF(AND(I37="Cancelled",H37=""),"CHECK timestamps",IF(OR(AND(G37<>"",G37<F37),AND(H37<>"",H37<IF(G37<>"",G37,F37))),"CHECK order",IF(AND(OR(I37="Rejected",I37="Reversed"),J37=""),"CHECK reason","OK"))))))) -> OK | L37: =IF(OR(I37="Requested",I37="Under Review",I37="Processing"),1,0) -> 0 | M37: =IF(G37="","",(G37-F37)*24) -> 25.995268 | N37: =IF(AND(I37="Completed",G37<>"",H37<>""),(H37-G37)*24,"") -> 59.803981 | O37: =IF(AND(I37="Completed",H37<>""),(H37-F37)*24,"") -> 85.799249 | P37: =IF(O37="","",IF(O37<=Settings!$B$8,"Yes","No")) -> No | Q37: =IF(AND(I37="Rejected",H37<>""),(H37-F37)*24,"") | R37: =IF(L37=1,(Settings!$B$5-F37)*24,"") | S37: =IF(COUNTIF($B$5:B37,B37)=1,1,0) -> 0 | T37: =IF(I37="Completed",IF(COUNTIFS(Wallet_Transactions!$I$5:$I$3000,A37,Wallet_Transactions!$D$5:$D$3000,"Redemption",Wallet_Transactions!$G$5:$G$3000,"Posted")>=1,"OK","CHECK no debit"),IF(I37="Reversed",IF(AND(COUNTIFS(Wallet_Transactions!$I$5:$I$3000,A37,Wallet_Transactions!$D$5:$D$3000,"Redemption",Wallet_Transactions!$G$5:$G$3000,"Posted")>=1,COUNTIFS(Wallet_Transactions!$I$5:$I$3000,A37,Wallet_Transactions!$D$5:$D$3000,"Reversal",Wallet_Transactions!$G$5:$G$3000,"Posted")>=1),"OK","CHECK no reversal"),IF(COUNTIFS(Wallet_Transactions!$I$5:$I$3000,A37,Wallet_Transactions!$D$5:$D$3000,"Redemption",Wallet_Transactions!$G$5:$G$3000,"Posted")>0,"CHECK unexpected debit","OK"))) -> OK
A38: WD-0034 | B38: U010 | C38: 1100 | D38: Points | E38: Bank Transfer | F38: 46301.667 | G38: 46302.331 | I38: Under Review | K38: =IF(ISNA(MATCH(I38,Withdrawal_Lifecycle!$A$5:$A$11,0)),"CHECK status",IF(AND(I38="Requested",OR(G38<>"",H38<>"")),"CHECK timestamps",IF(AND(OR(I38="Under Review",I38="Processing"),OR(G38="",H38<>"")),"CHECK timestamps",IF(AND(OR(I38="Completed",I38="Reversed",I38="Rejected"),OR(G38="",H38="")),"CHECK timestamps",IF(AND(I38="Cancelled",H38=""),"CHECK timestamps",IF(OR(AND(G38<>"",G38<F38),AND(H38<>"",H38<IF(G38<>"",G38,F38))),"CHECK order",IF(AND(OR(I38="Rejected",I38="Reversed"),J38=""),"CHECK reason","OK"))))))) -> OK | L38: =IF(OR(I38="Requested",I38="Under Review",I38="Processing"),1,0) -> 1 | M38: =IF(G38="","",(G38-F38)*24) -> 15.920475 | N38: =IF(AND(I38="Completed",G38<>"",H38<>""),(H38-G38)*24,"") | O38: =IF(AND(I38="Completed",H38<>""),(H38-F38)*24,"") | P38: =IF(O38="","",IF(O38<=Settings!$B$8,"Yes","No")) | Q38: =IF(AND(I38="Rejected",H38<>""),(H38-F38)*24,"") | R38: =IF(L38=1,(Settings!$B$5-F38)*24,"") -> 217.98333 | S38: =IF(COUNTIF($B$5:B38,B38)=1,1,0) -> 0 | T38: =IF(I38="Completed",IF(COUNTIFS(Wallet_Transactions!$I$5:$I$3000,A38,Wallet_Transactions!$D$5:$D$3000,"Redemption",Wallet_Transactions!$G$5:$G$3000,"Posted")>=1,"OK","CHECK no debit"),IF(I38="Reversed",IF(AND(COUNTIFS(Wallet_Transactions!$I$5:$I$3000,A38,Wallet_Transactions!$D$5:$D$3000,"Redemption",Wallet_Transactions!$G$5:$G$3000,"Posted")>=1,COUNTIFS(Wallet_Transactions!$I$5:$I$3000,A38,Wallet_Transactions!$D$5:$D$3000,"Reversal",Wallet_Transactions!$G$5:$G$3000,"Posted")>=1),"OK","CHECK no reversal"),IF(COUNTIFS(Wallet_Transactions!$I$5:$I$3000,A38,Wallet_Transactions!$D$5:$D$3000,"Redemption",Wallet_Transactions!$G$5:$G$3000,"Posted")>0,"CHECK unexpected debit","OK"))) -> OK
A39: WD-0035 | B39: U001 | C39: 1150 | D39: Points | E39: Bank Transfer | F39: 46302.692 | G39: 46303.464 | I39: Under Review | K39: =IF(ISNA(MATCH(I39,Withdrawal_Lifecycle!$A$5:$A$11,0)),"CHECK status",IF(AND(I39="Requested",OR(G39<>"",H39<>"")),"CHECK timestamps",IF(AND(OR(I39="Under Review",I39="Processing"),OR(G39="",H39<>"")),"CHECK timestamps",IF(AND(OR(I39="Completed",I39="Reversed",I39="Rejected"),OR(G39="",H39="")),"CHECK timestamps",IF(AND(I39="Cancelled",H39=""),"CHECK timestamps",IF(OR(AND(G39<>"",G39<F39),AND(H39<>"",H39<IF(G39<>"",G39,F39))),"CHECK order",IF(AND(OR(I39="Rejected",I39="Reversed"),J39=""),"CHECK reason","OK"))))))) -> OK | L39: =IF(OR(I39="Requested",I39="Under Review",I39="Processing"),1,0) -> 1 | M39: =IF(G39="","",(G39-F39)*24) -> 18.524459 | N39: =IF(AND(I39="Completed",G39<>"",H39<>""),(H39-G39)*24,"") | O39: =IF(AND(I39="Completed",H39<>""),(H39-F39)*24,"") | P39: =IF(O39="","",IF(O39<=Settings!$B$8,"Yes","No")) | Q39: =IF(AND(I39="Rejected",H39<>""),(H39-F39)*24,"") | R39: =IF(L39=1,(Settings!$B$5-F39)*24,"") -> 193.4 | S39: =IF(COUNTIF($B$5:B39,B39)=1,1,0) -> 0 | T39: =IF(I39="Completed",IF(COUNTIFS(Wallet_Transactions!$I$5:$I$3000,A39,Wallet_Transactions!$D$5:$D$3000,"Redemption",Wallet_Transactions!$G$5:$G$3000,"Posted")>=1,"OK","CHECK no debit"),IF(I39="Reversed",IF(AND(COUNTIFS(Wallet_Transactions!$I$5:$I$3000,A39,Wallet_Transactions!$D$5:$D$3000,"Redemption",Wallet_Transactions!$G$5:$G$3000,"Posted")>=1,COUNTIFS(Wallet_Transactions!$I$5:$I$3000,A39,Wallet_Transactions!$D$5:$D$3000,"Reversal",Wallet_Transactions!$G$5:$G$3000,"Posted")>=1),"OK","CHECK no reversal"),IF(COUNTIFS(Wallet_Transactions!$I$5:$I$3000,A39,Wallet_Transactions!$D$5:$D$3000,"Redemption",Wallet_Transactions!$G$5:$G$3000,"Posted")>0,"CHECK unexpected debit","OK"))) -> OK
A40: WD-0036 | B40: U019 | C40: 600 | D40: Points | E40: Gift Card | F40: 46303.638 | G40: 46304.1 | I40: Under Review | K40: =IF(ISNA(MATCH(I40,Withdrawal_Lifecycle!$A$5:$A$11,0)),"CHECK status",IF(AND(I40="Requested",OR(G40<>"",H40<>"")),"CHECK timestamps",IF(AND(OR(I40="Under Review",I40="Processing"),OR(G40="",H40<>"")),"CHECK timestamps",IF(AND(OR(I40="Completed",I40="Reversed",I40="Rejected"),OR(G40="",H40="")),"CHECK timestamps",IF(AND(I40="Cancelled",H40=""),"CHECK timestamps",IF(OR(AND(G40<>"",G40<F40),AND(H40<>"",H40<IF(G40<>"",G40,F40))),"CHECK order",IF(AND(OR(I40="Rejected",I40="Reversed"),J40=""),"CHECK reason","OK"))))))) -> OK | L40: =IF(OR(I40="Requested",I40="Under Review",I40="Processing"),1,0) -> 1 | M40: =IF(G40="","",(G40-F40)*24) -> 11.093265 | N40: =IF(AND(I40="Completed",G40<>"",H40<>""),(H40-G40)*24,"") | O40: =IF(AND(I40="Completed",H40<>""),(H40-F40)*24,"") | P40: =IF(O40="","",IF(O40<=Settings!$B$8,"Yes","No")) | Q40: =IF(AND(I40="Rejected",H40<>""),(H40-F40)*24,"") | R40: =IF(L40=1,(Settings!$B$5-F40)*24,"") -> 170.68333 | S40: =IF(COUNTIF($B$5:B40,B40)=1,1,0) -> 1 | T40: =IF(I40="Completed",IF(COUNTIFS(Wallet_Transactions!$I$5:$I$3000,A40,Wallet_Transactions!$D$5:$D$3000,"Redemption",Wallet_Transactions!$G$5:$G$3000,"Posted")>=1,"OK","CHECK no debit"),IF(I40="Reversed",IF(AND(COUNTIFS(Wallet_Transactions!$I$5:$I$3000,A40,Wallet_Transactions!$D$5:$D$3000,"Redemption",Wallet_Transactions!$G$5:$G$3000,"Posted")>=1,COUNTIFS(Wallet_Transactions!$I$5:$I$3000,A40,Wallet_Transactions!$D$5:$D$3000,"Reversal",Wallet_Transactions!$G$5:$G$3000,"Posted")>=1),"OK","CHECK no reversal"),IF(COUNTIFS(Wallet_Transactions!$I$5:$I$3000,A40,Wallet_Transactions!$D$5:$D$3000,"Redemption",Wallet_Transactions!$G$5:$G$3000,"Posted")>0,"CHECK unexpected debit","OK"))) -> OK
A41: WD-0037 | B41: U012 | C41: 1700 | D41: Points | E41: E-Wallet | F41: 46304.61 | G41: 46304.649 | H41: 46306.065 | I41: Completed | K41: =IF(ISNA(MATCH(I41,Withdrawal_Lifecycle!$A$5:$A$11,0)),"CHECK status",IF(AND(I41="Requested",OR(G41<>"",H41<>"")),"CHECK timestamps",IF(AND(OR(I41="Under Review",I41="Processing"),OR(G41="",H41<>"")),"CHECK timestamps",IF(AND(OR(I41="Completed",I41="Reversed",I41="Rejected"),OR(G41="",H41="")),"CHECK timestamps",IF(AND(I41="Cancelled",H41=""),"CHECK timestamps",IF(OR(AND(G41<>"",G41<F41),AND(H41<>"",H41<IF(G41<>"",G41,F41))),"CHECK order",IF(AND(OR(I41="Rejected",I41="Reversed"),J41=""),"CHECK reason","OK"))))))) -> OK | L41: =IF(OR(I41="Requested",I41="Under Review",I41="Processing"),1,0) -> 0 | M41: =IF(G41="","",(G41-F41)*24) -> 0.93761405 | N41: =IF(AND(I41="Completed",G41<>"",H41<>""),(H41-G41)*24,"") -> 33.989776 | O41: =IF(AND(I41="Completed",H41<>""),(H41-F41)*24,"") -> 34.92739 | P41: =IF(O41="","",IF(O41<=Settings!$B$8,"Yes","No")) -> Yes | Q41: =IF(AND(I41="Rejected",H41<>""),(H41-F41)*24,"") | R41: =IF(L41=1,(Settings!$B$5-F41)*24,"") | S41: =IF(COUNTIF($B$5:B41,B41)=1,1,0) -> 1 | T41: =IF(I41="Completed",IF(COUNTIFS(Wallet_Transactions!$I$5:$I$3000,A41,Wallet_Transactions!$D$5:$D$3000,"Redemption",Wallet_Transactions!$G$5:$G$3000,"Posted")>=1,"OK","CHECK no debit"),IF(I41="Reversed",IF(AND(COUNTIFS(Wallet_Transactions!$I$5:$I$3000,A41,Wallet_Transactions!$D$5:$D$3000,"Redemption",Wallet_Transactions!$G$5:$G$3000,"Posted")>=1,COUNTIFS(Wallet_Transactions!$I$5:$I$3000,A41,Wallet_Transactions!$D$5:$D$3000,"Reversal",Wallet_Transactions!$G$5:$G$3000,"Posted")>=1),"OK","CHECK no reversal"),IF(COUNTIFS(Wallet_Transactions!$I$5:$I$3000,A41,Wallet_Transactions!$D$5:$D$3000,"Redemption",Wallet_Transactions!$G$5:$G$3000,"Posted")>0,"CHECK unexpected debit","OK"))) -> OK
A42: WD-0038 | B42: U011 | C42: 500 | D42: Points | E42: Bank Transfer | F42: 46304.855 | G42: 46306.015 | H42: 46307.88 | I42: Completed | K42: =IF(ISNA(MATCH(I42,Withdrawal_Lifecycle!$A$5:$A$11,0)),"CHECK status",IF(AND(I42="Requested",OR(G42<>"",H42<>"")),"CHECK timestamps",IF(AND(OR(I42="Under Review",I42="Processing"),OR(G42="",H42<>"")),"CHECK timestamps",IF(AND(OR(I42="Completed",I42="Reversed",I42="Rejected"),OR(G42="",H42="")),"CHECK timestamps",IF(AND(I42="Cancelled",H42=""),"CHECK timestamps",IF(OR(AND(G42<>"",G42<F42),AND(H42<>"",H42<IF(G42<>"",G42,F42))),"CHECK order",IF(AND(OR(I42="Rejected",I42="Reversed"),J42=""),"CHECK reason","OK"))))))) -> OK | L42: =IF(OR(I42="Requested",I42="Under Review",I42="Processing"),1,0) -> 0 | M42: =IF(G42="","",(G42-F42)*24) -> 27.853213 | N42: =IF(AND(I42="Completed",G42<>"",H42<>""),(H42-G42)*24,"") -> 44.760438 | O42: =IF(AND(I42="Completed",H42<>""),(H42-F42)*24,"") -> 72.613651 | P42: =IF(O42="","",IF(O42<=Settings!$B$8,"Yes","No")) -> No | Q42: =IF(AND(I42="Rejected",H42<>""),(H42-F42)*24,"") | R42: =IF(L42=1,(Settings!$B$5-F42)*24,"") | S42: =IF(COUNTIF($B$5:B42,B42)=1,1,0) -> 0 | T42: =IF(I42="Completed",IF(COUNTIFS(Wallet_Transactions!$I$5:$I$3000,A42,Wallet_Transactions!$D$5:$D$3000,"Redemption",Wallet_Transactions!$G$5:$G$3000,"Posted")>=1,"OK","CHECK no debit"),IF(I42="Reversed",IF(AND(COUNTIFS(Wallet_Transactions!$I$5:$I$3000,A42,Wallet_Transactions!$D$5:$D$3000,"Redemption",Wallet_Transactions!$G$5:$G$3000,"Posted")>=1,COUNTIFS(Wallet_Transactions!$I$5:$I$3000,A42,Wallet_Transactions!$D$5:$D$3000,"Reversal",Wallet_Transactions!$G$5:$G$3000,"Posted")>=1),"OK","CHECK no reversal"),IF(COUNTIFS(Wallet_Transactions!$I$5:$I$3000,A42,Wallet_Transactions!$D$5:$D$3000,"Redemption",Wallet_Transactions!$G$5:$G$3000,"Posted")>0,"CHECK unexpected debit","OK"))) -> OK
A43: WD-0039 | B43: U010 | C43: 550 | D43: Points | E43: Bank Transfer | F43: 46306.275 | G43: 46306.507 | H43: 46306.752 | I43: Completed | K43: =IF(ISNA(MATCH(I43,Withdrawal_Lifecycle!$A$5:$A$11,0)),"CHECK status",IF(AND(I43="Requested",OR(G43<>"",H43<>"")),"CHECK timestamps",IF(AND(OR(I43="Under Review",I43="Processing"),OR(G43="",H43<>"")),"CHECK timestamps",IF(AND(OR(I43="Completed",I43="Reversed",I43="Rejected"),OR(G43="",H43="")),"CHECK timestamps",IF(AND(I43="Cancelled",H43=""),"CHECK timestamps",IF(OR(AND(G43<>"",G43<F43),AND(H43<>"",H43<IF(G43<>"",G43,F43))),"CHECK order",IF(AND(OR(I43="Rejected",I43="Reversed"),J43=""),"CHECK reason","OK"))))))) -> OK | L43: =IF(OR(I43="Requested",I43="Under Review",I43="Processing"),1,0) -> 0 | M43: =IF(G43="","",(G43-F43)*24) -> 5.5676664 | N43: =IF(AND(I43="Completed",G43<>"",H43<>""),(H43-G43)*24,"") -> 5.891611 | O43: =IF(AND(I43="Completed",H43<>""),(H43-F43)*24,"") -> 11.459277 | P43: =IF(O43="","",IF(O43<=Settings!$B$8,"Yes","No")) -> Yes | Q43: =IF(AND(I43="Rejected",H43<>""),(H43-F43)*24,"") | R43: =IF(L43=1,(Settings!$B$5-F43)*24,"") | S43: =IF(COUNTIF($B$5:B43,B43)=1,1,0) -> 0 | T43: =IF(I43="Completed",IF(COUNTIFS(Wallet_Transactions!$I$5:$I$3000,A43,Wallet_Transactions!$D$5:$D$3000,"Redemption",Wallet_Transactions!$G$5:$G$3000,"Posted")>=1,"OK","CHECK no debit"),IF(I43="Reversed",IF(AND(COUNTIFS(Wallet_Transactions!$I$5:$I$3000,A43,Wallet_Transactions!$D$5:$D$3000,"Redemption",Wallet_Transactions!$G$5:$G$3000,"Posted")>=1,COUNTIFS(Wallet_Transactions!$I$5:$I$3000,A43,Wallet_Transactions!$D$5:$D$3000,"Reversal",Wallet_Transactions!$G$5:$G$3000,"Posted")>=1),"OK","CHECK no reversal"),IF(COUNTIFS(Wallet_Transactions!$I$5:$I$3000,A43,Wallet_Transactions!$D$5:$D$3000,"Redemption",Wallet_Transactions!$G$5:$G$3000,"Posted")>0,"CHECK unexpected debit","OK"))) -> OK
A44: WD-0040 | B44: U007 | C44: 950 | D44: Points | E44: E-Wallet | F44: 46307.319 | G44: 46308.499 | I44: Processing | K44: =IF(ISNA(MATCH(I44,Withdrawal_Lifecycle!$A$5:$A$11,0)),"CHECK status",IF(AND(I44="Requested",OR(G44<>"",H44<>"")),"CHECK timestamps",IF(AND(OR(I44="Under Review",I44="Processing"),OR(G44="",H44<>"")),"CHECK timestamps",IF(AND(OR(I44="Completed",I44="Reversed",I44="Rejected"),OR(G44="",H44="")),"CHECK timestamps",IF(AND(I44="Cancelled",H44=""),"CHECK timestamps",IF(OR(AND(G44<>"",G44<F44),AND(H44<>"",H44<IF(G44<>"",G44,F44))),"CHECK order",IF(AND(OR(I44="Rejected",I44="Reversed"),J44=""),"CHECK reason","OK"))))))) -> OK | L44: =IF(OR(I44="Requested",I44="Under Review",I44="Processing"),1,0) -> 1 | M44: =IF(G44="","",(G44-F44)*24) -> 28.320733 | N44: =IF(AND(I44="Completed",G44<>"",H44<>""),(H44-G44)*24,"") | O44: =IF(AND(I44="Completed",H44<>""),(H44-F44)*24,"") | P44: =IF(O44="","",IF(O44<=Settings!$B$8,"Yes","No")) | Q44: =IF(AND(I44="Rejected",H44<>""),(H44-F44)*24,"") | R44: =IF(L44=1,(Settings!$B$5-F44)*24,"") -> 82.35 | S44: =IF(COUNTIF($B$5:B44,B44)=1,1,0) -> 0 | T44: =IF(I44="Completed",IF(COUNTIFS(Wallet_Transactions!$I$5:$I$3000,A44,Wallet_Transactions!$D$5:$D$3000,"Redemption",Wallet_Transactions!$G$5:$G$3000,"Posted")>=1,"OK","CHECK no debit"),IF(I44="Reversed",IF(AND(COUNTIFS(Wallet_Transactions!$I$5:$I$3000,A44,Wallet_Transactions!$D$5:$D$3000,"Redemption",Wallet_Transactions!$G$5:$G$3000,"Posted")>=1,COUNTIFS(Wallet_Transactions!$I$5:$I$3000,A44,Wallet_Transactions!$D$5:$D$3000,"Reversal",Wallet_Transactions!$G$5:$G$3000,"Posted")>=1),"OK","CHECK no reversal"),IF(COUNTIFS(Wallet_Transactions!$I$5:$I$3000,A44,Wallet_Transactions!$D$5:$D$3000,"Redemption",Wallet_Transactions!$G$5:$G$3000,"Posted")>0,"CHECK unexpected debit","OK"))) -> OK
A45: WD-0041 | B45: U004 | C45: 950 | D45: Points | E45: Gift Card | F45: 46308.463 | G45: 46308.961 | H45: 46310.48 | I45: Completed | K45: =IF(ISNA(MATCH(I45,Withdrawal_Lifecycle!$A$5:$A$11,0)),"CHECK status",IF(AND(I45="Requested",OR(G45<>"",H45<>"")),"CHECK timestamps",IF(AND(OR(I45="Under Review",I45="Processing"),OR(G45="",H45<>"")),"CHECK timestamps",IF(AND(OR(I45="Completed",I45="Reversed",I45="Rejected"),OR(G45="",H45="")),"CHECK timestamps",IF(AND(I45="Cancelled",H45=""),"CHECK timestamps",IF(OR(AND(G45<>"",G45<F45),AND(H45<>"",H45<IF(G45<>"",G45,F45))),"CHECK order",IF(AND(OR(I45="Rejected",I45="Reversed"),J45=""),"CHECK reason","OK"))))))) -> OK | L45: =IF(OR(I45="Requested",I45="Under Review",I45="Processing"),1,0) -> 0 | M45: =IF(G45="","",(G45-F45)*24) -> 11.942908 | N45: =IF(AND(I45="Completed",G45<>"",H45<>""),(H45-G45)*24,"") -> 36.456171 | O45: =IF(AND(I45="Completed",H45<>""),(H45-F45)*24,"") -> 48.399079 | P45: =IF(O45="","",IF(O45<=Settings!$B$8,"Yes","No")) -> No | Q45: =IF(AND(I45="Rejected",H45<>""),(H45-F45)*24,"") | R45: =IF(L45=1,(Settings!$B$5-F45)*24,"") | S45: =IF(COUNTIF($B$5:B45,B45)=1,1,0) -> 0 | T45: =IF(I45="Completed",IF(COUNTIFS(Wallet_Transactions!$I$5:$I$3000,A45,Wallet_Transactions!$D$5:$D$3000,"Redemption",Wallet_Transactions!$G$5:$G$3000,"Posted")>=1,"OK","CHECK no debit"),IF(I45="Reversed",IF(AND(COUNTIFS(Wallet_Transactions!$I$5:$I$3000,A45,Wallet_Transactions!$D$5:$D$3000,"Redemption",Wallet_Transactions!$G$5:$G$3000,"Posted")>=1,COUNTIFS(Wallet_Transactions!$I$5:$I$3000,A45,Wallet_Transactions!$D$5:$D$3000,"Reversal",Wallet_Transactions!$G$5:$G$3000,"Posted")>=1),"OK","CHECK no reversal"),IF(COUNTIFS(Wallet_Transactions!$I$5:$I$3000,A45,Wallet_Transactions!$D$5:$D$3000,"Redemption",Wallet_Transactions!$G$5:$G$3000,"Posted")>0,"CHECK unexpected debit","OK"))) -> OK
A46: WD-0042 | B46: U007 | C46: 550 | D46: Points | E46: Bank Transfer | F46: 46308.98 | G46: 46309.5 | I46: Under Review | K46: =IF(ISNA(MATCH(I46,Withdrawal_Lifecycle!$A$5:$A$11,0)),"CHECK status",IF(AND(I46="Requested",OR(G46<>"",H46<>"")),"CHECK timestamps",IF(AND(OR(I46="Under Review",I46="Processing"),OR(G46="",H46<>"")),"CHECK timestamps",IF(AND(OR(I46="Completed",I46="Reversed",I46="Rejected"),OR(G46="",H46="")),"CHECK timestamps",IF(AND(I46="Cancelled",H46=""),"CHECK timestamps",IF(OR(AND(G46<>"",G46<F46),AND(H46<>"",H46<IF(G46<>"",G46,F46))),"CHECK order",IF(AND(OR(I46="Rejected",I46="Reversed"),J46=""),"CHECK reason","OK"))))))) -> OK | L46: =IF(OR(I46="Requested",I46="Under Review",I46="Processing"),1,0) -> 1 | M46: =IF(G46="","",(G46-F46)*24) -> 12.487218 | N46: =IF(AND(I46="Completed",G46<>"",H46<>""),(H46-G46)*24,"") | O46: =IF(AND(I46="Completed",H46<>""),(H46-F46)*24,"") | P46: =IF(O46="","",IF(O46<=Settings!$B$8,"Yes","No")) | Q46: =IF(AND(I46="Rejected",H46<>""),(H46-F46)*24,"") | R46: =IF(L46=1,(Settings!$B$5-F46)*24,"") -> 42.486559 | S46: =IF(COUNTIF($B$5:B46,B46)=1,1,0) -> 0 | T46: =IF(I46="Completed",IF(COUNTIFS(Wallet_Transactions!$I$5:$I$3000,A46,Wallet_Transactions!$D$5:$D$3000,"Redemption",Wallet_Transactions!$G$5:$G$3000,"Posted")>=1,"OK","CHECK no debit"),IF(I46="Reversed",IF(AND(COUNTIFS(Wallet_Transactions!$I$5:$I$3000,A46,Wallet_Transactions!$D$5:$D$3000,"Redemption",Wallet_Transactions!$G$5:$G$3000,"Posted")>=1,COUNTIFS(Wallet_Transactions!$I$5:$I$3000,A46,Wallet_Transactions!$D$5:$D$3000,"Reversal",Wallet_Transactions!$G$5:$G$3000,"Posted")>=1),"OK","CHECK no reversal"),IF(COUNTIFS(Wallet_Transactions!$I$5:$I$3000,A46,Wallet_Transactions!$D$5:$D$3000,"Redemption",Wallet_Transactions!$G$5:$G$3000,"Posted")>0,"CHECK unexpected debit","OK"))) -> OK
A47: WD-0043 | B47: U018 | C47: 750 | D47: Points | E47: Gift Card | F47: 46309.001 | G47: 46309.056 | I47: Under Review | K47: =IF(ISNA(MATCH(I47,Withdrawal_Lifecycle!$A$5:$A$11,0)),"CHECK status",IF(AND(I47="Requested",OR(G47<>"",H47<>"")),"CHECK timestamps",IF(AND(OR(I47="Under Review",I47="Processing"),OR(G47="",H47<>"")),"CHECK timestamps",IF(AND(OR(I47="Completed",I47="Reversed",I47="Rejected"),OR(G47="",H47="")),"CHECK timestamps",IF(AND(I47="Cancelled",H47=""),"CHECK timestamps",IF(OR(AND(G47<>"",G47<F47),AND(H47<>"",H47<IF(G47<>"",G47,F47))),"CHECK order",IF(AND(OR(I47="Rejected",I47="Reversed"),J47=""),"CHECK reason","OK"))))))) -> OK | L47: =IF(OR(I47="Requested",I47="Under Review",I47="Processing"),1,0) -> 1 | M47: =IF(G47="","",(G47-F47)*24) -> 1.3133953 | N47: =IF(AND(I47="Completed",G47<>"",H47<>""),(H47-G47)*24,"") | O47: =IF(AND(I47="Completed",H47<>""),(H47-F47)*24,"") | P47: =IF(O47="","",IF(O47<=Settings!$B$8,"Yes","No")) | Q47: =IF(AND(I47="Rejected",H47<>""),(H47-F47)*24,"") | R47: =IF(L47=1,(Settings!$B$5-F47)*24,"") -> 41.96782 | S47: =IF(COUNTIF($B$5:B47,B47)=1,1,0) -> 0 | T47: =IF(I47="Completed",IF(COUNTIFS(Wallet_Transactions!$I$5:$I$3000,A47,Wallet_Transactions!$D$5:$D$3000,"Redemption",Wallet_Transactions!$G$5:$G$3000,"Posted")>=1,"OK","CHECK no debit"),IF(I47="Reversed",IF(AND(COUNTIFS(Wallet_Transactions!$I$5:$I$3000,A47,Wallet_Transactions!$D$5:$D$3000,"Redemption",Wallet_Transactions!$G$5:$G$3000,"Posted")>=1,COUNTIFS(Wallet_Transactions!$I$5:$I$3000,A47,Wallet_Transactions!$D$5:$D$3000,"Reversal",Wallet_Transactions!$G$5:$G$3000,"Posted")>=1),"OK","CHECK no reversal"),IF(COUNTIFS(Wallet_Transactions!$I$5:$I$3000,A47,Wallet_Transactions!$D$5:$D$3000,"Redemption",Wallet_Transactions!$G$5:$G$3000,"Posted")>0,"CHECK unexpected debit","OK"))) -> OK
A48: WD-0044 | B48: U008 | C48: 1100 | D48: Points | E48: Other | F48: 46309.027 | G48: 46309.17 | I48: Under Review | K48: =IF(ISNA(MATCH(I48,Withdrawal_Lifecycle!$A$5:$A$11,0)),"CHECK status",IF(AND(I48="Requested",OR(G48<>"",H48<>"")),"CHECK timestamps",IF(AND(OR(I48="Under Review",I48="Processing"),OR(G48="",H48<>"")),"CHECK timestamps",IF(AND(OR(I48="Completed",I48="Reversed",I48="Rejected"),OR(G48="",H48="")),"CHECK timestamps",IF(AND(I48="Cancelled",H48=""),"CHECK timestamps",IF(OR(AND(G48<>"",G48<F48),AND(H48<>"",H48<IF(G48<>"",G48,F48))),"CHECK order",IF(AND(OR(I48="Rejected",I48="Reversed"),J48=""),"CHECK reason","OK"))))))) -> OK | L48: =IF(OR(I48="Requested",I48="Under Review",I48="Processing"),1,0) -> 1 | M48: =IF(G48="","",(G48-F48)*24) -> 3.4146093 | N48: =IF(AND(I48="Completed",G48<>"",H48<>""),(H48-G48)*24,"") | O48: =IF(AND(I48="Completed",H48<>""),(H48-F48)*24,"") | P48: =IF(O48="","",IF(O48<=Settings!$B$8,"Yes","No")) | Q48: =IF(AND(I48="Rejected",H48<>""),(H48-F48)*24,"") | R48: =IF(L48=1,(Settings!$B$5-F48)*24,"") -> 41.341428 | S48: =IF(COUNTIF($B$5:B48,B48)=1,1,0) -> 0 | T48: =IF(I48="Completed",IF(COUNTIFS(Wallet_Transactions!$I$5:$I$3000,A48,Wallet_Transactions!$D$5:$D$3000,"Redemption",Wallet_Transactions!$G$5:$G$3000,"Posted")>=1,"OK","CHECK no debit"),IF(I48="Reversed",IF(AND(COUNTIFS(Wallet_Transactions!$I$5:$I$3000,A48,Wallet_Transactions!$D$5:$D$3000,"Redemption",Wallet_Transactions!$G$5:$G$3000,"Posted")>=1,COUNTIFS(Wallet_Transactions!$I$5:$I$3000,A48,Wallet_Transactions!$D$5:$D$3000,"Reversal",Wallet_Transactions!$G$5:$G$3000,"Posted")>=1),"OK","CHECK no reversal"),IF(COUNTIFS(Wallet_Transactions!$I$5:$I$3000,A48,Wallet_Transactions!$D$5:$D$3000,"Redemption",Wallet_Transactions!$G$5:$G$3000,"Posted")>0,"CHECK unexpected debit","OK"))) -> OK
A49: WD-0045 | B49: U014 | C49: 550 | D49: Points | E49: E-Wallet | F49: 46309.593 | G49: 46310.298 | I49: Processing | K49: =IF(ISNA(MATCH(I49,Withdrawal_Lifecycle!$A$5:$A$11,0)),"CHECK status",IF(AND(I49="Requested",OR(G49<>"",H49<>"")),"CHECK timestamps",IF(AND(OR(I49="Under Review",I49="Processing"),OR(G49="",H49<>"")),"CHECK timestamps",IF(AND(OR(I49="Completed",I49="Reversed",I49="Rejected"),OR(G49="",H49="")),"CHECK timestamps",IF(AND(I49="Cancelled",H49=""),"CHECK timestamps",IF(OR(AND(G49<>"",G49<F49),AND(H49<>"",H49<IF(G49<>"",G49,F49))),"CHECK order",IF(AND(OR(I49="Rejected",I49="Reversed"),J49=""),"CHECK reason","OK"))))))) -> OK | L49: =IF(OR(I49="Requested",I49="Under Review",I49="Processing"),1,0) -> 1 | M49: =IF(G49="","",(G49-F49)*24) -> 16.928457 | N49: =IF(AND(I49="Completed",G49<>"",H49<>""),(H49-G49)*24,"") | O49: =IF(AND(I49="Completed",H49<>""),(H49-F49)*24,"") | P49: =IF(O49="","",IF(O49<=Settings!$B$8,"Yes","No")) | Q49: =IF(AND(I49="Rejected",H49<>""),(H49-F49)*24,"") | R49: =IF(L49=1,(Settings!$B$5-F49)*24,"") -> 27.766097 | S49: =IF(COUNTIF($B$5:B49,B49)=1,1,0) -> 0 | T49: =IF(I49="Completed",IF(COUNTIFS(Wallet_Transactions!$I$5:$I$3000,A49,Wallet_Transactions!$D$5:$D$3000,"Redemption",Wallet_Transactions!$G$5:$G$3000,"Posted")>=1,"OK","CHECK no debit"),IF(I49="Reversed",IF(AND(COUNTIFS(Wallet_Transactions!$I$5:$I$3000,A49,Wallet_Transactions!$D$5:$D$3000,"Redemption",Wallet_Transactions!$G$5:$G$3000,"Posted")>=1,COUNTIFS(Wallet_Transactions!$I$5:$I$3000,A49,Wallet_Transactions!$D$5:$D$3000,"Reversal",Wallet_Transactions!$G$5:$G$3000,"Posted")>=1),"OK","CHECK no reversal"),IF(COUNTIFS(Wallet_Transactions!$I$5:$I$3000,A49,Wallet_Transactions!$D$5:$D$3000,"Redemption",Wallet_Transactions!$G$5:$G$3000,"Posted")>0,"CHECK unexpected debit","OK"))) -> OK
A50: WD-0046 | B50: U017 | C50: 650 | D50: Points | E50: Gift Card | F50: 46309.799 | G50: 46310.157 | I50: Under Review | K50: =IF(ISNA(MATCH(I50,Withdrawal_Lifecycle!$A$5:$A$11,0)),"CHECK status",IF(AND(I50="Requested",OR(G50<>"",H50<>"")),"CHECK timestamps",IF(AND(OR(I50="Under Review",I50="Processing"),OR(G50="",H50<>"")),"CHECK timestamps",IF(AND(OR(I50="Completed",I50="Reversed",I50="Rejected"),OR(G50="",H50="")),"CHECK timestamps",IF(AND(I50="Cancelled",H50=""),"CHECK timestamps",IF(OR(AND(G50<>"",G50<F50),AND(H50<>"",H50<IF(G50<>"",G50,F50))),"CHECK order",IF(AND(OR(I50="Rejected",I50="Reversed"),J50=""),"CHECK reason","OK"))))))) -> OK | L50: =IF(OR(I50="Requested",I50="Under Review",I50="Processing"),1,0) -> 1 | M50: =IF(G50="","",(G50-F50)*24) -> 8.5946921 | N50: =IF(AND(I50="Completed",G50<>"",H50<>""),(H50-G50)*24,"") | O50: =IF(AND(I50="Completed",H50<>""),(H50-F50)*24,"") | P50: =IF(O50="","",IF(O50<=Settings!$B$8,"Yes","No")) | Q50: =IF(AND(I50="Rejected",H50<>""),(H50-F50)*24,"") | R50: =IF(L50=1,(Settings!$B$5-F50)*24,"") -> 22.827373 | S50: =IF(COUNTIF($B$5:B50,B50)=1,1,0) -> 1 | T50: =IF(I50="Completed",IF(COUNTIFS(Wallet_Transactions!$I$5:$I$3000,A50,Wallet_Transactions!$D$5:$D$3000,"Redemption",Wallet_Transactions!$G$5:$G$3000,"Posted")>=1,"OK","CHECK no debit"),IF(I50="Reversed",IF(AND(COUNTIFS(Wallet_Transactions!$I$5:$I$3000,A50,Wallet_Transactions!$D$5:$D$3000,"Redemption",Wallet_Transactions!$G$5:$G$3000,"Posted")>=1,COUNTIFS(Wallet_Transactions!$I$5:$I$3000,A50,Wallet_Transactions!$D$5:$D$3000,"Reversal",Wallet_Transactions!$G$5:$G$3000,"Posted")>=1),"OK","CHECK no reversal"),IF(COUNTIFS(Wallet_Transactions!$I$5:$I$3000,A50,Wallet_Transactions!$D$5:$D$3000,"Redemption",Wallet_Transactions!$G$5:$G$3000,"Posted")>0,"CHECK unexpected debit","OK"))) -> OK
A51: WD-0047 | B51: U016 | C51: 1500 | D51: Points | E51: Bank Transfer | F51: 46310.474 | G51: 46310.612 | I51: Under Review | K51: =IF(ISNA(MATCH(I51,Withdrawal_Lifecycle!$A$5:$A$11,0)),"CHECK status",IF(AND(I51="Requested",OR(G51<>"",H51<>"")),"CHECK timestamps",IF(AND(OR(I51="Under Review",I51="Processing"),OR(G51="",H51<>"")),"CHECK timestamps",IF(AND(OR(I51="Completed",I51="Reversed",I51="Rejected"),OR(G51="",H51="")),"CHECK timestamps",IF(AND(I51="Cancelled",H51=""),"CHECK timestamps",IF(OR(AND(G51<>"",G51<F51),AND(H51<>"",H51<IF(G51<>"",G51,F51))),"CHECK order",IF(AND(OR(I51="Rejected",I51="Reversed"),J51=""),"CHECK reason","OK"))))))) -> OK | L51: =IF(OR(I51="Requested",I51="Under Review",I51="Processing"),1,0) -> 1 | M51: =IF(G51="","",(G51-F51)*24) -> 3.2927142 | N51: =IF(AND(I51="Completed",G51<>"",H51<>""),(H51-G51)*24,"") | O51: =IF(AND(I51="Completed",H51<>""),(H51-F51)*24,"") | P51: =IF(O51="","",IF(O51<=Settings!$B$8,"Yes","No")) | Q51: =IF(AND(I51="Rejected",H51<>""),(H51-F51)*24,"") | R51: =IF(L51=1,(Settings!$B$5-F51)*24,"") -> 6.6166667 | S51: =IF(COUNTIF($B$5:B51,B51)=1,1,0) -> 1 | T51: =IF(I51="Completed",IF(COUNTIFS(Wallet_Transactions!$I$5:$I$3000,A51,Wallet_Transactions!$D$5:$D$3000,"Redemption",Wallet_Transactions!$G$5:$G$3000,"Posted")>=1,"OK","CHECK no debit"),IF(I51="Reversed",IF(AND(COUNTIFS(Wallet_Transactions!$I$5:$I$3000,A51,Wallet_Transactions!$D$5:$D$3000,"Redemption",Wallet_Transactions!$G$5:$G$3000,"Posted")>=1,COUNTIFS(Wallet_Transactions!$I$5:$I$3000,A51,Wallet_Transactions!$D$5:$D$3000,"Reversal",Wallet_Transactions!$G$5:$G$3000,"Posted")>=1),"OK","CHECK no reversal"),IF(COUNTIFS(Wallet_Transactions!$I$5:$I$3000,A51,Wallet_Transactions!$D$5:$D$3000,"Redemption",Wallet_Transactions!$G$5:$G$3000,"Posted")>0,"CHECK unexpected debit","OK"))) -> OK
A52: WD-0048 | B52: U017 | C52: 1200 | D52: Points | E52: Bank Transfer | F52: 46310.603 | G52: 46310.641 | I52: Under Review | K52: =IF(ISNA(MATCH(I52,Withdrawal_Lifecycle!$A$5:$A$11,0)),"CHECK status",IF(AND(I52="Requested",OR(G52<>"",H52<>"")),"CHECK timestamps",IF(AND(OR(I52="Under Review",I52="Processing"),OR(G52="",H52<>"")),"CHECK timestamps",IF(AND(OR(I52="Completed",I52="Reversed",I52="Rejected"),OR(G52="",H52="")),"CHECK timestamps",IF(AND(I52="Cancelled",H52=""),"CHECK timestamps",IF(OR(AND(G52<>"",G52<F52),AND(H52<>"",H52<IF(G52<>"",G52,F52))),"CHECK order",IF(AND(OR(I52="Rejected",I52="Reversed"),J52=""),"CHECK reason","OK"))))))) -> OK | L52: =IF(OR(I52="Requested",I52="Under Review",I52="Processing"),1,0) -> 1 | M52: =IF(G52="","",(G52-F52)*24) -> 0.91670134 | N52: =IF(AND(I52="Completed",G52<>"",H52<>""),(H52-G52)*24,"") | O52: =IF(AND(I52="Completed",H52<>""),(H52-F52)*24,"") | P52: =IF(O52="","",IF(O52<=Settings!$B$8,"Yes","No")) | Q52: =IF(AND(I52="Rejected",H52<>""),(H52-F52)*24,"") | R52: =IF(L52=1,(Settings!$B$5-F52)*24,"") -> 3.5387685 | S52: =IF(COUNTIF($B$5:B52,B52)=1,1,0) -> 0 | T52: =IF(I52="Completed",IF(COUNTIFS(Wallet_Transactions!$I$5:$I$3000,A52,Wallet_Transactions!$D$5:$D$3000,"Redemption",Wallet_Transactions!$G$5:$G$3000,"Posted")>=1,"OK","CHECK no debit"),IF(I52="Reversed",IF(AND(COUNTIFS(Wallet_Transactions!$I$5:$I$3000,A52,Wallet_Transactions!$D$5:$D$3000,"Redemption",Wallet_Transactions!$G$5:$G$3000,"Posted")>=1,COUNTIFS(Wallet_Transactions!$I$5:$I$3000,A52,Wallet_Transactions!$D$5:$D$3000,"Reversal",Wallet_Transactions!$G$5:$G$3000,"Posted")>=1),"OK","CHECK no reversal"),IF(COUNTIFS(Wallet_Transactions!$I$5:$I$3000,A52,Wallet_Transactions!$D$5:$D$3000,"Redemption",Wallet_Transactions!$G$5:$G$3000,"Posted")>0,"CHECK unexpected debit","OK"))) -> OK

Sheet Wallet_Transactions
A1: Wallet Transactions (D1) - one row per ledger entry
A2: Blue = input. Grey = formulas (copy down). Amount is SIGNED: credits positive, debits negative. A Reversal/Correction row points to the original row via Related Transaction ID. Types marked Proposed in Transaction_Types are flagged in column L.
A4: Transaction ID | B4: User ID | C4: Timestamp | D4: Transaction Type | E4: Amount (signed) | F4: Unit | G4: Status | H4: Source | I4: Reference ID | J4: Related Transaction ID (reversal / correction) | K4: Relationship | L4: Type Support Status | M4: Expected Direction | N4: Posted Signed Amount | O4: Times Reversed | P4: Net Effect incl. Linked Rows | Q4: Data Check | R4: Date
A5: WTX-00001 | B5: U019 | C5: 46266.008 | D5: Reward Credit | E5: 500 | F5: Points | G5: Posted | H5: Task Reward | I5: TASK-1237 | L5: =IFERROR(INDEX(Transaction_Types!$B$5:$B$20,MATCH(D5,Transaction_Types!$A$5:$A$20,0)),"Not in catalogue") -> Supported | M5: =IFERROR(INDEX(Transaction_Types!$C$5:$C$20,MATCH(D5,Transaction_Types!$A$5:$A$20,0)),"") -> Credit | N5: =IF(G5="Posted",E5,0) -> 500 | O5: =COUNTIFS($J$5:$J$3000,A5,$K$5:$K$3000,"Reverses") -> 0 | P5: =IF(K5<>"","",IF(G5="Posted",E5+SUMIFS($N$5:$N$3000,$J$5:$J$3000,A5),0)) -> 500 | Q5: =IF(L5="Not in catalogue","CHECK type",IF(F5<>Settings!$B$6,"CHECK unit",IF(OR(AND(M5="Credit",E5<=0),AND(M5="Debit",E5>=0)),"CHECK sign",IF(D5="Reversal",IF(OR(J5="",COUNTIF($A$5:$A$3000,J5)=0),"CHECK reversal link",IF(E5<>-INDEX($E$5:$E$3000,MATCH(J5,$A$5:$A$3000,0)),"CHECK reversal amount","OK")),IF(AND(D5="Adjustment",K5<>"",COUNTIF($A$5:$A$3000,J5)=0),"CHECK correction link","OK"))))) -> OK | R5: =INT(C5) -> 46266
A6: WTX-00002 | B6: U017 | C6: 46266.163 | D6: Reward Credit | E6: 400 | F6: Points | G6: Posted | H6: Campaign Bonus | I6: CMP-001 | L6: =IFERROR(INDEX(Transaction_Types!$B$5:$B$20,MATCH(D6,Transaction_Types!$A$5:$A$20,0)),"Not in catalogue") -> Supported | M6: =IFERROR(INDEX(Transaction_Types!$C$5:$C$20,MATCH(D6,Transaction_Types!$A$5:$A$20,0)),"") -> Credit | N6: =IF(G6="Posted",E6,0) -> 400 | O6: =COUNTIFS($J$5:$J$3000,A6,$K$5:$K$3000,"Reverses") -> 0 | P6: =IF(K6<>"","",IF(G6="Posted",E6+SUMIFS($N$5:$N$3000,$J$5:$J$3000,A6),0)) -> 400 | Q6: =IF(L6="Not in catalogue","CHECK type",IF(F6<>Settings!$B$6,"CHECK unit",IF(OR(AND(M6="Credit",E6<=0),AND(M6="Debit",E6>=0)),"CHECK sign",IF(D6="Reversal",IF(OR(J6="",COUNTIF($A$5:$A$3000,J6)=0),"CHECK reversal link",IF(E6<>-INDEX($E$5:$E$3000,MATCH(J6,$A$5:$A$3000,0)),"CHECK reversal amount","OK")),IF(AND(D6="Adjustment",K6<>"",COUNTIF($A$5:$A$3000,J6)=0),"CHECK correction link","OK"))))) -> OK | R6: =INT(C6) -> 46266
A7: WTX-00003 | B7: U008 | C7: 46266.178 | D7: Reward Credit | E7: 150 | F7: Points | G7: Posted | H7: Referral Reward | I7: REF-0012 | L7: =IFERROR(INDEX(Transaction_Types!$B$5:$B$20,MATCH(D7,Transaction_Types!$A$5:$A$20,0)),"Not in catalogue") -> Supported | M7: =IFERROR(INDEX(Transaction_Types!$C$5:$C$20,MATCH(D7,Transaction_Types!$A$5:$A$20,0)),"") -> Credit | N7: =IF(G7="Posted",E7,0) -> 150 | O7: =COUNTIFS($J$5:$J$3000,A7,$K$5:$K$3000,"Reverses") -> 0 | P7: =IF(K7<>"","",IF(G7="Posted",E7+SUMIFS($N$5:$N$3000,$J$5:$J$3000,A7),0)) -> 150 | Q7: =IF(L7="Not in catalogue","CHECK type",IF(F7<>Settings!$B$6,"CHECK unit",IF(OR(AND(M7="Credit",E7<=0),AND(M7="Debit",E7>=0)),"CHECK sign",IF(D7="Reversal",IF(OR(J7="",COUNTIF($A$5:$A$3000,J7)=0),"CHECK reversal link",IF(E7<>-INDEX($E$5:$E$3000,MATCH(J7,$A$5:$A$3000,0)),"CHECK reversal amount","OK")),IF(AND(D7="Adjustment",K7<>"",COUNTIF($A$5:$A$3000,J7)=0),"CHECK correction link","OK"))))) -> OK | R7: =INT(C7) -> 46266
A8: WTX-00004 | B8: U017 | C8: 46266.533 | D8: Reward Credit | E8: 200 | F8: Points | G8: Posted | H8: Campaign Bonus | I8: CMP-001 | L8: =IFERROR(INDEX(Transaction_Types!$B$5:$B$20,MATCH(D8,Transaction_Types!$A$5:$A$20,0)),"Not in catalogue") -> Supported | M8: =IFERROR(INDEX(Transaction_Types!$C$5:$C$20,MATCH(D8,Transaction_Types!$A$5:$A$20,0)),"") -> Credit | N8: =IF(G8="Posted",E8,0) -> 200 | O8: =COUNTIFS($J$5:$J$3000,A8,$K$5:$K$3000,"Reverses") -> 0 | P8: =IF(K8<>"","",IF(G8="Posted",E8+SUMIFS($N$5:$N$3000,$J$5:$J$3000,A8),0)) -> 200 | Q8: =IF(L8="Not in catalogue","CHECK type",IF(F8<>Settings!$B$6,"CHECK unit",IF(OR(AND(M8="Credit",E8<=0),AND(M8="Debit",E8>=0)),"CHECK sign",IF(D8="Reversal",IF(OR(J8="",COUNTIF($A$5:$A$3000,J8)=0),"CHECK reversal link",IF(E8<>-INDEX($E$5:$E$3000,MATCH(J8,$A$5:$A$3000,0)),"CHECK reversal amount","OK")),IF(AND(D8="Adjustment",K8<>"",COUNTIF($A$5:$A$3000,J8)=0),"CHECK correction link","OK"))))) -> OK | R8: =INT(C8) -> 46266
A9: WTX-00005 | B9: U015 | C9: 46266.857 | D9: Reward Credit | E9: 400 | F9: Points | G9: Posted | H9: Referral Reward | I9: REF-0016 | L9: =IFERROR(INDEX(Transaction_Types!$B$5:$B$20,MATCH(D9,Transaction_Types!$A$5:$A$20,0)),"Not in catalogue") -> Supported | M9: =IFERROR(INDEX(Transaction_Types!$C$5:$C$20,MATCH(D9,Transaction_Types!$A$5:$A$20,0)),"") -> Credit | N9: =IF(G9="Posted",E9,0) -> 400 | O9: =COUNTIFS($J$5:$J$3000,A9,$K$5:$K$3000,"Reverses") -> 0 | P9: =IF(K9<>"","",IF(G9="Posted",E9+SUMIFS($N$5:$N$3000,$J$5:$J$3000,A9),0)) -> 400 | Q9: =IF(L9="Not in catalogue","CHECK type",IF(F9<>Settings!$B$6,"CHECK unit",IF(OR(AND(M9="Credit",E9<=0),AND(M9="Debit",E9>=0)),"CHECK sign",IF(D9="Reversal",IF(OR(J9="",COUNTIF($A$5:$A$3000,J9)=0),"CHECK reversal link",IF(E9<>-INDEX($E$5:$E$3000,MATCH(J9,$A$5:$A$3000,0)),"CHECK reversal amount","OK")),IF(AND(D9="Adjustment",K9<>"",COUNTIF($A$5:$A$3000,J9)=0),"CHECK correction link","OK"))))) -> OK | R9: =INT(C9) -> 46266
A10: WTX-00006 | B10: U003 | C10: 46267.026 | D10: Reward Credit | E10: 200 | F10: Points | G10: Posted | H10: Campaign Bonus | I10: CMP-001 | L10: =IFERROR(INDEX(Transaction_Types!$B$5:$B$20,MATCH(D10,Transaction_Types!$A$5:$A$20,0)),"Not in catalogue") -> Supported | M10: =IFERROR(INDEX(Transaction_Types!$C$5:$C$20,MATCH(D10,Transaction_Types!$A$5:$A$20,0)),"") -> Credit | N10: =IF(G10="Posted",E10,0) -> 200 | O10: =COUNTIFS($J$5:$J$3000,A10,$K$5:$K$3000,"Reverses") -> 0 | P10: =IF(K10<>"","",IF(G10="Posted",E10+SUMIFS($N$5:$N$3000,$J$5:$J$3000,A10),0)) -> 200 | Q10: =IF(L10="Not in catalogue","CHECK type",IF(F10<>Settings!$B$6,"CHECK unit",IF(OR(AND(M10="Credit",E10<=0),AND(M10="Debit",E10>=0)),"CHECK sign",IF(D10="Reversal",IF(OR(J10="",COUNTIF($A$5:$A$3000,J10)=0),"CHECK reversal link",IF(E10<>-INDEX($E$5:$E$3000,MATCH(J10,$A$5:$A$3000,0)),"CHECK reversal amount","OK")),IF(AND(D10="Adjustment",K10<>"",COUNTIF($A$5:$A$3000,J10)=0),"CHECK correction link","OK"))))) -> OK | R10: =INT(C10) -> 46267
A11: WTX-00007 | B11: U004 | C11: 46267.16 | D11: Reward Credit | E11: 150 | F11: Points | G11: Posted | H11: Task Reward | I11: TASK-1051 | L11: =IFERROR(INDEX(Transaction_Types!$B$5:$B$20,MATCH(D11,Transaction_Types!$A$5:$A$20,0)),"Not in catalogue") -> Supported | M11: =IFERROR(INDEX(Transaction_Types!$C$5:$C$20,MATCH(D11,Transaction_Types!$A$5:$A$20,0)),"") -> Credit | N11: =IF(G11="Posted",E11,0) -> 150 | O11: =COUNTIFS($J$5:$J$3000,A11,$K$5:$K$3000,"Reverses") -> 0 | P11: =IF(K11<>"","",IF(G11="Posted",E11+SUMIFS($N$5:$N$3000,$J$5:$J$3000,A11),0)) -> 150 | Q11: =IF(L11="Not in catalogue","CHECK type",IF(F11<>Settings!$B$6,"CHECK unit",IF(OR(AND(M11="Credit",E11<=0),AND(M11="Debit",E11>=0)),"CHECK sign",IF(D11="Reversal",IF(OR(J11="",COUNTIF($A$5:$A$3000,J11)=0),"CHECK reversal link",IF(E11<>-INDEX($E$5:$E$3000,MATCH(J11,$A$5:$A$3000,0)),"CHECK reversal amount","OK")),IF(AND(D11="Adjustment",K11<>"",COUNTIF($A$5:$A$3000,J11)=0),"CHECK correction link","OK"))))) -> OK | R11: =INT(C11) -> 46267
A12: WTX-00008 | B12: U019 | C12: 46267.467 | D12: Reward Credit | E12: 500 | F12: Points | G12: Posted | H12: Task Reward | I12: TASK-1235 | L12: =IFERROR(INDEX(Transaction_Types!$B$5:$B$20,MATCH(D12,Transaction_Types!$A$5:$A$20,0)),"Not in catalogue") -> Supported | M12: =IFERROR(INDEX(Transaction_Types!$C$5:$C$20,MATCH(D12,Transaction_Types!$A$5:$A$20,0)),"") -> Credit | N12: =IF(G12="Posted",E12,0) -> 500 | O12: =COUNTIFS($J$5:$J$3000,A12,$K$5:$K$3000,"Reverses") -> 0 | P12: =IF(K12<>"","",IF(G12="Posted",E12+SUMIFS($N$5:$N$3000,$J$5:$J$3000,A12),0)) -> 500 | Q12: =IF(L12="Not in catalogue","CHECK type",IF(F12<>Settings!$B$6,"CHECK unit",IF(OR(AND(M12="Credit",E12<=0),AND(M12="Debit",E12>=0)),"CHECK sign",IF(D12="Reversal",IF(OR(J12="",COUNTIF($A$5:$A$3000,J12)=0),"CHECK reversal link",IF(E12<>-INDEX($E$5:$E$3000,MATCH(J12,$A$5:$A$3000,0)),"CHECK reversal amount","OK")),IF(AND(D12="Adjustment",K12<>"",COUNTIF($A$5:$A$3000,J12)=0),"CHECK correction link","OK"))))) -> OK | R12: =INT(C12) -> 46267
A13: WTX-00009 | B13: U002 | C13: 46267.784 | D13: Reward Credit | E13: 100 | F13: Points | G13: Posted | H13: Campaign Bonus | I13: CMP-001 | L13: =IFERROR(INDEX(Transaction_Types!$B$5:$B$20,MATCH(D13,Transaction_Types!$A$5:$A$20,0)),"Not in catalogue") -> Supported | M13: =IFERROR(INDEX(Transaction_Types!$C$5:$C$20,MATCH(D13,Transaction_Types!$A$5:$A$20,0)),"") -> Credit | N13: =IF(G13="Posted",E13,0) -> 100 | O13: =COUNTIFS($J$5:$J$3000,A13,$K$5:$K$3000,"Reverses") -> 0 | P13: =IF(K13<>"","",IF(G13="Posted",E13+SUMIFS($N$5:$N$3000,$J$5:$J$3000,A13),0)) -> 100 | Q13: =IF(L13="Not in catalogue","CHECK type",IF(F13<>Settings!$B$6,"CHECK unit",IF(OR(AND(M13="Credit",E13<=0),AND(M13="Debit",E13>=0)),"CHECK sign",IF(D13="Reversal",IF(OR(J13="",COUNTIF($A$5:$A$3000,J13)=0),"CHECK reversal link",IF(E13<>-INDEX($E$5:$E$3000,MATCH(J13,$A$5:$A$3000,0)),"CHECK reversal amount","OK")),IF(AND(D13="Adjustment",K13<>"",COUNTIF($A$5:$A$3000,J13)=0),"CHECK correction link","OK"))))) -> OK | R13: =INT(C13) -> 46267
A14: WTX-00010 | B14: U014 | C14: 46267.905 | D14: Reward Credit | E14: 200 | F14: Points | G14: Posted | H14: Task Reward | I14: TASK-1170 | L14: =IFERROR(INDEX(Transaction_Types!$B$5:$B$20,MATCH(D14,Transaction_Types!$A$5:$A$20,0)),"Not in catalogue") -> Supported | M14: =IFERROR(INDEX(Transaction_Types!$C$5:$C$20,MATCH(D14,Transaction_Types!$A$5:$A$20,0)),"") -> Credit | N14: =IF(G14="Posted",E14,0) -> 200 | O14: =COUNTIFS($J$5:$J$3000,A14,$K$5:$K$3000,"Reverses") -> 0 | P14: =IF(K14<>"","",IF(G14="Posted",E14+SUMIFS($N$5:$N$3000,$J$5:$J$3000,A14),0)) -> 200 | Q14: =IF(L14="Not in catalogue","CHECK type",IF(F14<>Settings!$B$6,"CHECK unit",IF(OR(AND(M14="Credit",E14<=0),AND(M14="Debit",E14>=0)),"CHECK sign",IF(D14="Reversal",IF(OR(J14="",COUNTIF($A$5:$A$3000,J14)=0),"CHECK reversal link",IF(E14<>-INDEX($E$5:$E$3000,MATCH(J14,$A$5:$A$3000,0)),"CHECK reversal amount","OK")),IF(AND(D14="Adjustment",K14<>"",COUNTIF($A$5:$A$3000,J14)=0),"CHECK correction link","OK"))))) -> OK | R14: =INT(C14) -> 46267
A15: WTX-00011 | B15: U011 | C15: 46267.966 | D15: Reward Credit | E15: 150 | F15: Points | G15: Posted | H15: Task Reward | I15: TASK-1133 | L15: =IFERROR(INDEX(Transaction_Types!$B$5:$B$20,MATCH(D15,Transaction_Types!$A$5:$A$20,0)),"Not in catalogue") -> Supported | M15: =IFERROR(INDEX(Transaction_Types!$C$5:$C$20,MATCH(D15,Transaction_Types!$A$5:$A$20,0)),"") -> Credit | N15: =IF(G15="Posted",E15,0) -> 150 | O15: =COUNTIFS($J$5:$J$3000,A15,$K$5:$K$3000,"Reverses") -> 0 | P15: =IF(K15<>"","",IF(G15="Posted",E15+SUMIFS($N$5:$N$3000,$J$5:$J$3000,A15),0)) -> 150 | Q15: =IF(L15="Not in catalogue","CHECK type",IF(F15<>Settings!$B$6,"CHECK unit",IF(OR(AND(M15="Credit",E15<=0),AND(M15="Debit",E15>=0)),"CHECK sign",IF(D15="Reversal",IF(OR(J15="",COUNTIF($A$5:$A$3000,J15)=0),"CHECK reversal link",IF(E15<>-INDEX($E$5:$E$3000,MATCH(J15,$A$5:$A$3000,0)),"CHECK reversal amount","OK")),IF(AND(D15="Adjustment",K15<>"",COUNTIF($A$5:$A$3000,J15)=0),"CHECK correction link","OK"))))) -> OK | R15: =INT(C15) -> 46267
A16: WTX-00012 | B16: U013 | C16: 46268.058 | D16: Reward Credit | E16: 150 | F16: Points | G16: Posted | H16: Task Reward | I16: TASK-1150 | L16: =IFERROR(INDEX(Transaction_Types!$B$5:$B$20,MATCH(D16,Transaction_Types!$A$5:$A$20,0)),"Not in catalogue") -> Supported | M16: =IFERROR(INDEX(Transaction_Types!$C$5:$C$20,MATCH(D16,Transaction_Types!$A$5:$A$20,0)),"") -> Credit | N16: =IF(G16="Posted",E16,0) -> 150 | O16: =COUNTIFS($J$5:$J$3000,A16,$K$5:$K$3000,"Reverses") -> 0 | P16: =IF(K16<>"","",IF(G16="Posted",E16+SUMIFS($N$5:$N$3000,$J$5:$J$3000,A16),0)) -> 150 | Q16: =IF(L16="Not in catalogue","CHECK type",IF(F16<>Settings!$B$6,"CHECK unit",IF(OR(AND(M16="Credit",E16<=0),AND(M16="Debit",E16>=0)),"CHECK sign",IF(D16="Reversal",IF(OR(J16="",COUNTIF($A$5:$A$3000,J16)=0),"CHECK reversal link",IF(E16<>-INDEX($E$5:$E$3000,MATCH(J16,$A$5:$A$3000,0)),"CHECK reversal amount","OK")),IF(AND(D16="Adjustment",K16<>"",COUNTIF($A$5:$A$3000,J16)=0),"CHECK correction link","OK"))))) -> OK | R16: =INT(C16) -> 46268
... A92: WTX-00088 | B92: U016 | C92: 46279.179 | D92: Reward Credit | E92: 500 | F92: Points | G92: Posted | H92: Task Reward | I92: TASK-1190 | L92: =IFERROR(INDEX(Transaction_Types!$B$5:$B$20,MATCH(D92,Transaction_Types!$A$5:$A$20,0)),"Not in catalogue") -> Supported | M92: =IFERROR(INDEX(Transaction_Types!$C$5:$C$20,MATCH(D92,Transaction_Types!$A$5:$A$20,0)),"") -> Credit | N92: =IF(G92="Posted",E92,0) -> 500 | O92: =COUNTIFS($J$5:$J$3000,A92,$K$5:$K$3000,"Reverses") -> 0 | P92: =IF(K92<>"","",IF(G92="Posted",E92+SUMIFS($N$5:$N$3000,$J$5:$J$3000,A92),0)) -> 500 | Q92: =IF(L92="Not in catalogue","CHECK type",IF(F92<>Settings!$B$6,"CHECK unit",IF(OR(AND(M92="Credit",E92<=0),AND(M92="Debit",E92>=0)),"CHECK sign",IF(D92="Reversal",IF(OR(J92="",COUNTIF($A$5:$A$3000,J92)=0),"CHECK reversal link",IF(E92<>-INDEX($E$5:$E$3000,MATCH(J92,$A$5:$A$3000,0)),"CHECK reversal amount","OK")),IF(AND(D92="Adjustment",K92<>"",COUNTIF($A$5:$A$3000,J92)=0),"CHECK correction link","OK"))))) -> OK | R92: =INT(C92) -> 46279
A93: WTX-00089 | B93: U011 | C93: 46279.447 | D93: Adjustment | E93: -50 | F93: Points | G93: Posted | H93: Admin Console | I93: ADJ-002 | J93: WTX-00080 | K93: Corrects | L93: =IFERROR(INDEX(Transaction_Types!$B$5:$B$20,MATCH(D93,Transaction_Types!$A$5:$A$20,0)),"Not in catalogue") -> Supported | M93: =IFERROR(INDEX(Transaction_Types!$C$5:$C$20,MATCH(D93,Transaction_Types!$A$5:$A$20,0)),"") -> Either | N93: =IF(G93="Posted",E93,0) -> -50 | O93: =COUNTIFS($J$5:$J$3000,A93,$K$5:$K$3000,"Reverses") -> 0 | P93: =IF(K93<>"","",IF(G93="Posted",E93+SUMIFS($N$5:$N$3000,$J$5:$J$3000,A93),0)) | Q93: =IF(L93="Not in catalogue","CHECK type",IF(F93<>Settings!$B$6,"CHECK unit",IF(OR(AND(M93="Credit",E93<=0),AND(M93="Debit",E93>=0)),"CHECK sign",IF(D93="Reversal",IF(OR(J93="",COUNTIF($A$5:$A$3000,J93)=0),"CHECK reversal link",IF(E93<>-INDEX($E$5:$E$3000,MATCH(J93,$A$5:$A$3000,0)),"CHECK reversal amount","OK")),IF(AND(D93="Adjustment",K93<>"",COUNTIF($A$5:$A$3000,J93)=0),"CHECK correction link","OK"))))) -> OK | R93: =INT(C93) -> 46279
A94: WTX-00090 | B94: U018 | C94: 46279.551 | D94: Reward Credit | E94: 400 | F94: Points | G94: Posted | H94: Task Reward | I94: TASK-1217 | L94: =IFERROR(INDEX(Transaction_Types!$B$5:$B$20,MATCH(D94,Transaction_Types!$A$5:$A$20,0)),"Not in catalogue") -> Supported | M94: =IFERROR(INDEX(Transaction_Types!$C$5:$C$20,MATCH(D94,Transaction_Types!$A$5:$A$20,0)),"") -> Credit | N94: =IF(G94="Posted",E94,0) -> 400 | O94: =COUNTIFS($J$5:$J$3000,A94,$K$5:$K$3000,"Reverses") -> 0 | P94: =IF(K94<>"","",IF(G94="Posted",E94+SUMIFS($N$5:$N$3000,$J$5:$J$3000,A94),0)) -> 400 | Q94: =IF(L94="Not in catalogue","CHECK type",IF(F94<>Settings!$B$6,"CHECK unit",IF(OR(AND(M94="Credit",E94<=0),AND(M94="Debit",E94>=0)),"CHECK sign",IF(D94="Reversal",IF(OR(J94="",COUNTIF($A$5:$A$3000,J94)=0),"CHECK reversal link",IF(E94<>-INDEX($E$5:$E$3000,MATCH(J94,$A$5:$A$3000,0)),"CHECK reversal amount","OK")),IF(AND(D94="Adjustment",K94<>"",COUNTIF($A$5:$A$3000,J94)=0),"CHECK correction link","OK"))))) -> OK | R94: =INT(C94) -> 46279
A95: WTX-00091 | B95: U009 | C95: 46279.779 | D95: Reward Credit | E95: 500 | F95: Points | G95: Posted | H95: Referral Reward | I95: REF-0010 | L95: =IFERROR(INDEX(Transaction_Types!$B$5:$B$20,MATCH(D95,Transaction_Types!$A$5:$A$20,0)),"Not in catalogue") -> Supported | M95: =IFERROR(INDEX(Transaction_Types!$C$5:$C$20,MATCH(D95,Transaction_Types!$A$5:$A$20,0)),"") -> Credit | N95: =IF(G95="Posted",E95,0) -> 500 | O95: =COUNTIFS($J$5:$J$3000,A95,$K$5:$K$3000,"Reverses") -> 0 | P95: =IF(K95<>"","",IF(G95="Posted",E95+SUMIFS($N$5:$N$3000,$J$5:$J$3000,A95),0)) -> 500 | Q95: =IF(L95="Not in catalogue","CHECK type",IF(F95<>Settings!$B$6,"CHECK unit",IF(OR(AND(M95="Credit",E95<=0),AND(M95="Debit",E95>=0)),"CHECK sign",IF(D95="Reversal",IF(OR(J95="",COUNTIF($A$5:$A$3000,J95)=0),"CHECK reversal link",IF(E95<>-INDEX($E$5:$E$3000,MATCH(J95,$A$5:$A$3000,0)),"CHECK reversal amount","OK")),IF(AND(D95="Adjustment",K95<>"",COUNTIF($A$5:$A$3000,J95)=0),"CHECK correction link","OK"))))) -> OK | R95: =INT(C95) -> 46279
A96: WTX-00092 | B96: U012 | C96: 46280.007 | D96: Reward Credit | E96: 150 | F96: Points | G96: Posted | H96: Referral Reward | I96: REF-0022 | L96: =IFERROR(INDEX(Transaction_Types!$B$5:$B$20,MATCH(D96,Transaction_Types!$A$5:$A$20,0)),"Not in catalogue") -> Supported | M96: =IFERROR(INDEX(Transaction_Types!$C$5:$C$20,MATCH(D96,Transaction_Types!$A$5:$A$20,0)),"") -> Credit | N96: =IF(G96="Posted",E96,0) -> 150 | O96: =COUNTIFS($J$5:$J$3000,A96,$K$5:$K$3000,"Reverses") -> 0 | P96: =IF(K96<>"","",IF(G96="Posted",E96+SUMIFS($N$5:$N$3000,$J$5:$J$3000,A96),0)) -> 150 | Q96: =IF(L96="Not in catalogue","CHECK type",IF(F96<>Settings!$B$6,"CHECK unit",IF(OR(AND(M96="Credit",E96<=0),AND(M96="Debit",E96>=0)),"CHECK sign",IF(D96="Reversal",IF(OR(J96="",COUNTIF($A$5:$A$3000,J96)=0),"CHECK reversal link",IF(E96<>-INDEX($E$5:$E$3000,MATCH(J96,$A$5:$A$3000,0)),"CHECK reversal amount","OK")),IF(AND(D96="Adjustment",K96<>"",COUNTIF($A$5:$A$3000,J96)=0),"CHECK correction link","OK"))))) -> OK | R96: =INT(C96) -> 46280
A97: WTX-00093 | B97: U013 | C97: 46280.088 | D97: Reward Credit | E97: 150 | F97: Points | G97: Posted | H97: Task Reward | I97: TASK-1153 | L97: =IFERROR(INDEX(Transaction_Types!$B$5:$B$20,MATCH(D97,Transaction_Types!$A$5:$A$20,0)),"Not in catalogue") -> Supported | M97: =IFERROR(INDEX(Transaction_Types!$C$5:$C$20,MATCH(D97,Transaction_Types!$A$5:$A$20,0)),"") -> Credit | N97: =IF(G97="Posted",E97,0) -> 150 | O97: =COUNTIFS($J$5:$J$3000,A97,$K$5:$K$3000,"Reverses") -> 0 | P97: =IF(K97<>"","",IF(G97="Posted",E97+SUMIFS($N$5:$N$3000,$J$5:$J$3000,A97),0)) -> 150 | Q97: =IF(L97="Not in catalogue","CHECK type",IF(F97<>Settings!$B$6,"CHECK unit",IF(OR(AND(M97="Credit",E97<=0),AND(M97="Debit",E97>=0)),"CHECK sign",IF(D97="Reversal",IF(OR(J97="",COUNTIF($A$5:$A$3000,J97)=0),"CHECK reversal link",IF(E97<>-INDEX($E$5:$E$3000,MATCH(J97,$A$5:$A$3000,0)),"CHECK reversal amount","OK")),IF(AND(D97="Adjustment",K97<>"",COUNTIF($A$5:$A$3000,J97)=0),"CHECK correction link","OK"))))) -> OK | R97: =INT(C97) -> 46280
A98: WTX-00094 | B98: U002 | C98: 46280.09 | D98: Reward Credit | E98: 400 | F98: Points | G98: Posted | H98: Referral Reward | I98: REF-0053 | L98: =IFERROR(INDEX(Transaction_Types!$B$5:$B$20,MATCH(D98,Transaction_Types!$A$5:$A$20,0)),"Not in catalogue") -> Supported | M98: =IFERROR(INDEX(Transaction_Types!$C$5:$C$20,MATCH(D98,Transaction_Types!$A$5:$A$20,0)),"") -> Credit | N98: =IF(G98="Posted",E98,0) -> 400 | O98: =COUNTIFS($J$5:$J$3000,A98,$K$5:$K$3000,"Reverses") -> 0 | P98: =IF(K98<>"","",IF(G98="Posted",E98+SUMIFS($N$5:$N$3000,$J$5:$J$3000,A98),0)) -> 400 | Q98: =IF(L98="Not in catalogue","CHECK type",IF(F98<>Settings!$B$6,"CHECK unit",IF(OR(AND(M98="Credit",E98<=0),AND(M98="Debit",E98>=0)),"CHECK sign",IF(D98="Reversal",IF(OR(J98="",COUNTIF($A$5:$A$3000,J98)=0),"CHECK reversal link",IF(E98<>-INDEX($E$5:$E$3000,MATCH(J98,$A$5:$A$3000,0)),"CHECK reversal amount","OK")),IF(AND(D98="Adjustment",K98<>"",COUNTIF($A$5:$A$3000,J98)=0),"CHECK correction link","OK"))))) -> OK | R98: =INT(C98) -> 46280
A99: WTX-00095 | B99: U016 | C99: 46280.184 | D99: Reward Credit | E99: 250 | F99: Points | G99: Posted | H99: Campaign Bonus | I99: CMP-001 | L99: =IFERROR(INDEX(Transaction_Types!$B$5:$B$20,MATCH(D99,Transaction_Types!$A$5:$A$20,0)),"Not in catalogue") -> Supported | M99: =IFERROR(INDEX(Transaction_Types!$C$5:$C$20,MATCH(D99,Transaction_Types!$A$5:$A$20,0)),"") -> Credit | N99: =IF(G99="Posted",E99,0) -> 250 | O99: =COUNTIFS($J$5:$J$3000,A99,$K$5:$K$3000,"Reverses") -> 0 | P99: =IF(K99<>"","",IF(G99="Posted",E99+SUMIFS($N$5:$N$3000,$J$5:$J$3000,A99),0)) -> 250 | Q99: =IF(L99="Not in catalogue","CHECK type",IF(F99<>Settings!$B$6,"CHECK unit",IF(OR(AND(M99="Credit",E99<=0),AND(M99="Debit",E99>=0)),"CHECK sign",IF(D99="Reversal",IF(OR(J99="",COUNTIF($A$5:$A$3000,J99)=0),"CHECK reversal link",IF(E99<>-INDEX($E$5:$E$3000,MATCH(J99,$A$5:$A$3000,0)),"CHECK reversal amount","OK")),IF(AND(D99="Adjustment",K99<>"",COUNTIF($A$5:$A$3000,J99)=0),"CHECK correction link","OK"))))) -> OK | R99: =INT(C99) -> 46280
A100: WTX-00096 | B100: U009 | C100: 46280.496 | D100: Reward Credit | E100: 200 | F100: Points | G100: Posted | H100: Task Reward | I100: TASK-1117 | L100: =IFERROR(INDEX(Transaction_Types!$B$5:$B$20,MATCH(D100,Transaction_Types!$A$5:$A$20,0)),"Not in catalogue") -> Supported | M100: =IFERROR(INDEX(Transaction_Types!$C$5:$C$20,MATCH(D100,Transaction_Types!$A$5:$A$20,0)),"") -> Credit | N100: =IF(G100="Posted",E100,0) -> 200 | O100: =COUNTIFS($J$5:$J$3000,A100,$K$5:$K$3000,"Reverses") -> 0 | P100: =IF(K100<>"","",IF(G100="Posted",E100+SUMIFS($N$5:$N$3000,$J$5:$J$3000,A100),0)) -> 200 | Q100: =IF(L100="Not in catalogue","CHECK type",IF(F100<>Settings!$B$6,"CHECK unit",IF(OR(AND(M100="Credit",E100<=0),AND(M100="Debit",E100>=0)),"CHECK sign",IF(D100="Reversal",IF(OR(J100="",COUNTIF($A$5:$A$3000,J100)=0),"CHECK reversal link",IF(E100<>-INDEX($E$5:$E$3000,MATCH(J100,$A$5:$A$3000,0)),"CHECK reversal amount","OK")),IF(AND(D100="Adjustment",K100<>"",COUNTIF($A$5:$A$3000,J100)=0),"CHECK correction link","OK"))))) -> OK | R100: =INT(C100) -> 46280
A101: WTX-00097 | B101: U019 | C101: 46280.531 | D101: Reward Credit | E101: 200 | F101: Points | G101: Posted | H101: Task Reward | I101: TASK-1225 | L101: =IFERROR(INDEX(Transaction_Types!$B$5:$B$20,MATCH(D101,Transaction_Types!$A$5:$A$20,0)),"Not in catalogue") -> Supported | M101: =IFERROR(INDEX(Transaction_Types!$C$5:$C$20,MATCH(D101,Transaction_Types!$A$5:$A$20,0)),"") -> Credit | N101: =IF(G101="Posted",E101,0) -> 200 | O101: =COUNTIFS($J$5:$J$3000,A101,$K$5:$K$3000,"Reverses") -> 0 | P101: =IF(K101<>"","",IF(G101="Posted",E101+SUMIFS($N$5:$N$3000,$J$5:$J$3000,A101),0)) -> 200 | Q101: =IF(L101="Not in catalogue","CHECK type",IF(F101<>Settings!$B$6,"CHECK unit",IF(OR(AND(M101="Credit",E101<=0),AND(M101="Debit",E101>=0)),"CHECK sign",IF(D101="Reversal",IF(OR(J101="",COUNTIF($A$5:$A$3000,J101)=0),"CHECK reversal link",IF(E101<>-INDEX($E$5:$E$3000,MATCH(J101,$A$5:$A$3000,0)),"CHECK reversal amount","OK")),IF(AND(D101="Adjustment",K101<>"",COUNTIF($A$5:$A$3000,J101)=0),"CHECK correction link","OK"))))) -> OK | R101: =INT(C101) -> 46280
A102: WTX-00098 | B102: U008 | C102: 46280.849 | D102: Redemption | E102: -1750 | F102: Points | G102: Posted | H102: Withdrawal | I102: WD-0009 | L102: =IFERROR(INDEX(Transaction_Types!$B$5:$B$20,MATCH(D102,Transaction_Types!$A$5:$A$20,0)),"Not in catalogue") -> Supported | M102: =IFERROR(INDEX(Transaction_Types!$C$5:$C$20,MATCH(D102,Transaction_Types!$A$5:$A$20,0)),"") -> Debit | N102: =IF(G102="Posted",E102,0) -> -1750 | O102: =COUNTIFS($J$5:$J$3000,A102,$K$5:$K$3000,"Reverses") -> 0 | P102: =IF(K102<>"","",IF(G102="Posted",E102+SUMIFS($N$5:$N$3000,$J$5:$J$3000,A102),0)) -> -1750 | Q102: =IF(L102="Not in catalogue","CHECK type",IF(F102<>Settings!$B$6,"CHECK unit",IF(OR(AND(M102="Credit",E102<=0),AND(M102="Debit",E102>=0)),"CHECK sign",IF(D102="Reversal",IF(OR(J102="",COUNTIF($A$5:$A$3000,J102)=0),"CHECK reversal link",IF(E102<>-INDEX($E$5:$E$3000,MATCH(J102,$A$5:$A$3000,0)),"CHECK reversal amount","OK")),IF(AND(D102="Adjustment",K102<>"",COUNTIF($A$5:$A$3000,J102)=0),"CHECK correction link","OK"))))) -> OK | R102: =INT(C102) -> 46280
A103: WTX-00099 | B103: U005 | C103: 46281.003 | D103: Reward Credit | E103: 300 | F103: Points | G103: Posted | H103: Referral Reward | I103: REF-0052 | L103: =IFERROR(INDEX(Transaction_Types!$B$5:$B$20,MATCH(D103,Transaction_Types!$A$5:$A$20,0)),"Not in catalogue") -> Supported | M103: =IFERROR(INDEX(Transaction_Types!$C$5:$C$20,MATCH(D103,Transaction_Types!$A$5:$A$20,0)),"") -> Credit | N103: =IF(G103="Posted",E103,0) -> 300 | O103: =COUNTIFS($J$5:$J$3000,A103,$K$5:$K$3000,"Reverses") -> 0 | P103: =IF(K103<>"","",IF(G103="Posted",E103+SUMIFS($N$5:$N$3000,$J$5:$J$3000,A103),0)) -> 300 | Q103: =IF(L103="Not in catalogue","CHECK type",IF(F103<>Settings!$B$6,"CHECK unit",IF(OR(AND(M103="Credit",E103<=0),AND(M103="Debit",E103>=0)),"CHECK sign",IF(D103="Reversal",IF(OR(J103="",COUNTIF($A$5:$A$3000,J103)=0),"CHECK reversal link",IF(E103<>-INDEX($E$5:$E$3000,MATCH(J103,$A$5:$A$3000,0)),"CHECK reversal amount","OK")),IF(AND(D103="Adjustment",K103<>"",COUNTIF($A$5:$A$3000,J103)=0),"CHECK correction link","OK"))))) -> OK | R103: =INT(C103) -> 46281
A104: WTX-00100 | B104: U017 | C104: 46281.078 | D104: Reward Credit | E104: 500 | F104: Points | G104: Posted | H104: Task Reward | I104: TASK-1201 | L104: =IFERROR(INDEX(Transaction_Types!$B$5:$B$20,MATCH(D104,Transaction_Types!$A$5:$A$20,0)),"Not in catalogue") -> Supported | M104: =IFERROR(INDEX(Transaction_Types!$C$5:$C$20,MATCH(D104,Transaction_Types!$A$5:$A$20,0)),"") -> Credit | N104: =IF(G104="Posted",E104,0) -> 500 | O104: =COUNTIFS($J$5:$J$3000,A104,$K$5:$K$3000,"Reverses") -> 0 | P104: =IF(K104<>"","",IF(G104="Posted",E104+SUMIFS($N$5:$N$3000,$J$5:$J$3000,A104),0)) -> 500 | Q104: =IF(L104="Not in catalogue","CHECK type",IF(F104<>Settings!$B$6,"CHECK unit",IF(OR(AND(M104="Credit",E104<=0),AND(M104="Debit",E104>=0)),"CHECK sign",IF(D104="Reversal",IF(OR(J104="",COUNTIF($A$5:$A$3000,J104)=0),"CHECK reversal link",IF(E104<>-INDEX($E$5:$E$3000,MATCH(J104,$A$5:$A$3000,0)),"CHECK reversal amount","OK")),IF(AND(D104="Adjustment",K104<>"",COUNTIF($A$5:$A$3000,J104)=0),"CHECK correction link","OK"))))) -> OK | R104: =INT(C104) -> 46281
A105: WTX-00101 | B105: U013 | C105: 46281.261 | D105: Reward Credit | E105: 250 | F105: Points | G105: Posted | H105: Task Reward | I105: TASK-1154 | L105: =IFERROR(INDEX(Transaction_Types!$B$5:$B$20,MATCH(D105,Transaction_Types!$A$5:$A$20,0)),"Not in catalogue") -> Supported | M105: =IFERROR(INDEX(Transaction_Types!$C$5:$C$20,MATCH(D105,Transaction_Types!$A$5:$A$20,0)),"") -> Credit | N105: =IF(G105="Posted",E105,0) -> 250 | O105: =COUNTIFS($J$5:$J$3000,A105,$K$5:$K$3000,"Reverses") -> 0 | P105: =IF(K105<>"","",IF(G105="Posted",E105+SUMIFS($N$5:$N$3000,$J$5:$J$3000,A105),0)) -> 250 | Q105: =IF(L105="Not in catalogue","CHECK type",IF(F105<>Settings!$B$6,"CHECK unit",IF(OR(AND(M105="Credit",E105<=0),AND(M105="Debit",E105>=0)),"CHECK sign",IF(D105="Reversal",IF(OR(J105="",COUNTIF($A$5:$A$3000,J105)=0),"CHECK reversal link",IF(E105<>-INDEX($E$5:$E$3000,MATCH(J105,$A$5:$A$3000,0)),"CHECK reversal amount","OK")),IF(AND(D105="Adjustment",K105<>"",COUNTIF($A$5:$A$3000,J105)=0),"CHECK correction link","OK"))))) -> OK | R105: =INT(C105) -> 46281
... A203: WTX-00199 | B203: U001 | C203: 46294.555 | D203: Reward Credit | E203: 100 | F203: Points | G203: Posted | H203: Referral Reward | I203: REF-0037 | L203: =IFERROR(INDEX(Transaction_Types!$B$5:$B$20,MATCH(D203,Transaction_Types!$A$5:$A$20,0)),"Not in catalogue") -> Supported | M203: =IFERROR(INDEX(Transaction_Types!$C$5:$C$20,MATCH(D203,Transaction_Types!$A$5:$A$20,0)),"") -> Credit | N203: =IF(G203="Posted",E203,0) -> 100 | O203: =COUNTIFS($J$5:$J$3000,A203,$K$5:$K$3000,"Reverses") -> 0 | P203: =IF(K203<>"","",IF(G203="Posted",E203+SUMIFS($N$5:$N$3000,$J$5:$J$3000,A203),0)) -> 100 | Q203: =IF(L203="Not in catalogue","CHECK type",IF(F203<>Settings!$B$6,"CHECK unit",IF(OR(AND(M203="Credit",E203<=0),AND(M203="Debit",E203>=0)),"CHECK sign",IF(D203="Reversal",IF(OR(J203="",COUNTIF($A$5:$A$3000,J203)=0),"CHECK reversal link",IF(E203<>-INDEX($E$5:$E$3000,MATCH(J203,$A$5:$A$3000,0)),"CHECK reversal amount","OK")),IF(AND(D203="Adjustment",K203<>"",COUNTIF($A$5:$A$3000,J203)=0),"CHECK correction link","OK"))))) -> OK | R203: =INT(C203) -> 46294
A204: WTX-00200 | B204: U004 | C204: 46294.63 | D204: Adjustment | E204: -50 | F204: Points | G204: Posted | H204: Admin Console | I204: ADJ-001 | J204: WTX-00168 | K204: Corrects | L204: =IFERROR(INDEX(Transaction_Types!$B$5:$B$20,MATCH(D204,Transaction_Types!$A$5:$A$20,0)),"Not in catalogue") -> Supported | M204: =IFERROR(INDEX(Transaction_Types!$C$5:$C$20,MATCH(D204,Transaction_Types!$A$5:$A$20,0)),"") -> Either | N204: =IF(G204="Posted",E204,0) -> -50 | O204: =COUNTIFS($J$5:$J$3000,A204,$K$5:$K$3000,"Reverses") -> 0 | P204: =IF(K204<>"","",IF(G204="Posted",E204+SUMIFS($N$5:$N$3000,$J$5:$J$3000,A204),0)) | Q204: =IF(L204="Not in catalogue","CHECK type",IF(F204<>Settings!$B$6,"CHECK unit",IF(OR(AND(M204="Credit",E204<=0),AND(M204="Debit",E204>=0)),"CHECK sign",IF(D204="Reversal",IF(OR(J204="",COUNTIF($A$5:$A$3000,J204)=0),"CHECK reversal link",IF(E204<>-INDEX($E$5:$E$3000,MATCH(J204,$A$5:$A$3000,0)),"CHECK reversal amount","OK")),IF(AND(D204="Adjustment",K204<>"",COUNTIF($A$5:$A$3000,J204)=0),"CHECK correction link","OK"))))) -> OK | R204: =INT(C204) -> 46294
A205: WTX-00201 | B205: U019 | C205: 46294.655 | D205: Reward Credit | E205: 500 | F205: Points | G205: Posted | H205: Referral Reward | I205: REF-0014 | L205: =IFERROR(INDEX(Transaction_Types!$B$5:$B$20,MATCH(D205,Transaction_Types!$A$5:$A$20,0)),"Not in catalogue") -> Supported | M205: =IFERROR(INDEX(Transaction_Types!$C$5:$C$20,MATCH(D205,Transaction_Types!$A$5:$A$20,0)),"") -> Credit | N205: =IF(G205="Posted",E205,0) -> 500 | O205: =COUNTIFS($J$5:$J$3000,A205,$K$5:$K$3000,"Reverses") -> 0 | P205: =IF(K205<>"","",IF(G205="Posted",E205+SUMIFS($N$5:$N$3000,$J$5:$J$3000,A205),0)) -> 500 | Q205: =IF(L205="Not in catalogue","CHECK type",IF(F205<>Settings!$B$6,"CHECK unit",IF(OR(AND(M205="Credit",E205<=0),AND(M205="Debit",E205>=0)),"CHECK sign",IF(D205="Reversal",IF(OR(J205="",COUNTIF($A$5:$A$3000,J205)=0),"CHECK reversal link",IF(E205<>-INDEX($E$5:$E$3000,MATCH(J205,$A$5:$A$3000,0)),"CHECK reversal amount","OK")),IF(AND(D205="Adjustment",K205<>"",COUNTIF($A$5:$A$3000,J205)=0),"CHECK correction link","OK"))))) -> OK | R205: =INT(C205) -> 46294
A206: WTX-00202 | B206: U006 | C206: 46294.938 | D206: Reward Credit | E206: 500 | F206: Points | G206: Posted | H206: Task Reward | I206: TASK-1078 | L206: =IFERROR(INDEX(Transaction_Types!$B$5:$B$20,MATCH(D206,Transaction_Types!$A$5:$A$20,0)),"Not in catalogue") -> Supported | M206: =IFERROR(INDEX(Transaction_Types!$C$5:$C$20,MATCH(D206,Transaction_Types!$A$5:$A$20,0)),"") -> Credit | N206: =IF(G206="Posted",E206,0) -> 500 | O206: =COUNTIFS($J$5:$J$3000,A206,$K$5:$K$3000,"Reverses") -> 0 | P206: =IF(K206<>"","",IF(G206="Posted",E206+SUMIFS($N$5:$N$3000,$J$5:$J$3000,A206),0)) -> 500 | Q206: =IF(L206="Not in catalogue","CHECK type",IF(F206<>Settings!$B$6,"CHECK unit",IF(OR(AND(M206="Credit",E206<=0),AND(M206="Debit",E206>=0)),"CHECK sign",IF(D206="Reversal",IF(OR(J206="",COUNTIF($A$5:$A$3000,J206)=0),"CHECK reversal link",IF(E206<>-INDEX($E$5:$E$3000,MATCH(J206,$A$5:$A$3000,0)),"CHECK reversal amount","OK")),IF(AND(D206="Adjustment",K206<>"",COUNTIF($A$5:$A$3000,J206)=0),"CHECK correction link","OK"))))) -> OK | R206: =INT(C206) -> 46294
A207: WTX-00203 | B207: U012 | C207: 46294.944 | D207: Reward Credit | E207: 200 | F207: Points | G207: Posted | H207: Task Reward | I207: TASK-1145 | L207: =IFERROR(INDEX(Transaction_Types!$B$5:$B$20,MATCH(D207,Transaction_Types!$A$5:$A$20,0)),"Not in catalogue") -> Supported | M207: =IFERROR(INDEX(Transaction_Types!$C$5:$C$20,MATCH(D207,Transaction_Types!$A$5:$A$20,0)),"") -> Credit | N207: =IF(G207="Posted",E207,0) -> 200 | O207: =COUNTIFS($J$5:$J$3000,A207,$K$5:$K$3000,"Reverses") -> 0 | P207: =IF(K207<>"","",IF(G207="Posted",E207+SUMIFS($N$5:$N$3000,$J$5:$J$3000,A207),0)) -> 200 | Q207: =IF(L207="Not in catalogue","CHECK type",IF(F207<>Settings!$B$6,"CHECK unit",IF(OR(AND(M207="Credit",E207<=0),AND(M207="Debit",E207>=0)),"CHECK sign",IF(D207="Reversal",IF(OR(J207="",COUNTIF($A$5:$A$3000,J207)=0),"CHECK reversal link",IF(E207<>-INDEX($E$5:$E$3000,MATCH(J207,$A$5:$A$3000,0)),"CHECK reversal amount","OK")),IF(AND(D207="Adjustment",K207<>"",COUNTIF($A$5:$A$3000,J207)=0),"CHECK correction link","OK"))))) -> OK | R207: =INT(C207) -> 46294
A208: WTX-00204 | B208: U014 | C208: 46295.079 | D208: Reversal | E208: 550 | F208: Points | G208: Posted | H208: System | I208: WD-0025 | J208: WTX-00178 | K208: Reverses | L208: =IFERROR(INDEX(Transaction_Types!$B$5:$B$20,MATCH(D208,Transaction_Types!$A$5:$A$20,0)),"Not in catalogue") -> Supported | M208: =IFERROR(INDEX(Transaction_Types!$C$5:$C$20,MATCH(D208,Transaction_Types!$A$5:$A$20,0)),"") -> Either | N208: =IF(G208="Posted",E208,0) -> 550 | O208: =COUNTIFS($J$5:$J$3000,A208,$K$5:$K$3000,"Reverses") -> 0 | P208: =IF(K208<>"","",IF(G208="Posted",E208+SUMIFS($N$5:$N$3000,$J$5:$J$3000,A208),0)) | Q208: =IF(L208="Not in catalogue","CHECK type",IF(F208<>Settings!$B$6,"CHECK unit",IF(OR(AND(M208="Credit",E208<=0),AND(M208="Debit",E208>=0)),"CHECK sign",IF(D208="Reversal",IF(OR(J208="",COUNTIF($A$5:$A$3000,J208)=0),"CHECK reversal link",IF(E208<>-INDEX($E$5:$E$3000,MATCH(J208,$A$5:$A$3000,0)),"CHECK reversal amount","OK")),IF(AND(D208="Adjustment",K208<>"",COUNTIF($A$5:$A$3000,J208)=0),"CHECK correction link","OK"))))) -> OK | R208: =INT(C208) -> 46295
A209: WTX-00205 | B209: U014 | C209: 46295.274 | D209: Reward Credit | E209: 500 | F209: Points | G209: Posted | H209: Task Reward | I209: TASK-1163 | L209: =IFERROR(INDEX(Transaction_Types!$B$5:$B$20,MATCH(D209,Transaction_Types!$A$5:$A$20,0)),"Not in catalogue") -> Supported | M209: =IFERROR(INDEX(Transaction_Types!$C$5:$C$20,MATCH(D209,Transaction_Types!$A$5:$A$20,0)),"") -> Credit | N209: =IF(G209="Posted",E209,0) -> 500 | O209: =COUNTIFS($J$5:$J$3000,A209,$K$5:$K$3000,"Reverses") -> 0 | P209: =IF(K209<>"","",IF(G209="Posted",E209+SUMIFS($N$5:$N$3000,$J$5:$J$3000,A209),0)) -> 500 | Q209: =IF(L209="Not in catalogue","CHECK type",IF(F209<>Settings!$B$6,"CHECK unit",IF(OR(AND(M209="Credit",E209<=0),AND(M209="Debit",E209>=0)),"CHECK sign",IF(D209="Reversal",IF(OR(J209="",COUNTIF($A$5:$A$3000,J209)=0),"CHECK reversal link",IF(E209<>-INDEX($E$5:$E$3000,MATCH(J209,$A$5:$A$3000,0)),"CHECK reversal amount","OK")),IF(AND(D209="Adjustment",K209<>"",COUNTIF($A$5:$A$3000,J209)=0),"CHECK correction link","OK"))))) -> OK | R209: =INT(C209) -> 46295
A210: WTX-00206 | B210: U020 | C210: 46295.461 | D210: Reward Credit | E210: 250 | F210: Points | G210: Posted | H210: Referral Reward | I210: REF-0006 | L210: =IFERROR(INDEX(Transaction_Types!$B$5:$B$20,MATCH(D210,Transaction_Types!$A$5:$A$20,0)),"Not in catalogue") -> Supported | M210: =IFERROR(INDEX(Transaction_Types!$C$5:$C$20,MATCH(D210,Transaction_Types!$A$5:$A$20,0)),"") -> Credit | N210: =IF(G210="Posted",E210,0) -> 250 | O210: =COUNTIFS($J$5:$J$3000,A210,$K$5:$K$3000,"Reverses") -> 0 | P210: =IF(K210<>"","",IF(G210="Posted",E210+SUMIFS($N$5:$N$3000,$J$5:$J$3000,A210),0)) -> 250 | Q210: =IF(L210="Not in catalogue","CHECK type",IF(F210<>Settings!$B$6,"CHECK unit",IF(OR(AND(M210="Credit",E210<=0),AND(M210="Debit",E210>=0)),"CHECK sign",IF(D210="Reversal",IF(OR(J210="",COUNTIF($A$5:$A$3000,J210)=0),"CHECK reversal link",IF(E210<>-INDEX($E$5:$E$3000,MATCH(J210,$A$5:$A$3000,0)),"CHECK reversal amount","OK")),IF(AND(D210="Adjustment",K210<>"",COUNTIF($A$5:$A$3000,J210)=0),"CHECK correction link","OK"))))) -> OK | R210: =INT(C210) -> 46295
A211: WTX-00207 | B211: U015 | C211: 46295.651 | D211: Reward Credit | E211: 200 | F211: Points | G211: Posted | H211: Referral Reward | I211: REF-0040 | L211: =IFERROR(INDEX(Transaction_Types!$B$5:$B$20,MATCH(D211,Transaction_Types!$A$5:$A$20,0)),"Not in catalogue") -> Supported | M211: =IFERROR(INDEX(Transaction_Types!$C$5:$C$20,MATCH(D211,Transaction_Types!$A$5:$A$20,0)),"") -> Credit | N211: =IF(G211="Posted",E211,0) -> 200 | O211: =COUNTIFS($J$5:$J$3000,A211,$K$5:$K$3000,"Reverses") -> 0 | P211: =IF(K211<>"","",IF(G211="Posted",E211+SUMIFS($N$5:$N$3000,$J$5:$J$3000,A211),0)) -> 200 | Q211: =IF(L211="Not in catalogue","CHECK type",IF(F211<>Settings!$B$6,"CHECK unit",IF(OR(AND(M211="Credit",E211<=0),AND(M211="Debit",E211>=0)),"CHECK sign",IF(D211="Reversal",IF(OR(J211="",COUNTIF($A$5:$A$3000,J211)=0),"CHECK reversal link",IF(E211<>-INDEX($E$5:$E$3000,MATCH(J211,$A$5:$A$3000,0)),"CHECK reversal amount","OK")),IF(AND(D211="Adjustment",K211<>"",COUNTIF($A$5:$A$3000,J211)=0),"CHECK correction link","OK"))))) -> OK | R211: =INT(C211) -> 46295
A212: WTX-00208 | B212: U007 | C212: 46295.912 | D212: Reward Credit | E212: 150 | F212: Points | G212: Posted | H212: Campaign Bonus | I212: CMP-001 | L212: =IFERROR(INDEX(Transaction_Types!$B$5:$B$20,MATCH(D212,Transaction_Types!$A$5:$A$20,0)),"Not in catalogue") -> Supported | M212: =IFERROR(INDEX(Transaction_Types!$C$5:$C$20,MATCH(D212,Transaction_Types!$A$5:$A$20,0)),"") -> Credit | N212: =IF(G212="Posted",E212,0) -> 150 | O212: =COUNTIFS($J$5:$J$3000,A212,$K$5:$K$3000,"Reverses") -> 0 | P212: =IF(K212<>"","",IF(G212="Posted",E212+SUMIFS($N$5:$N$3000,$J$5:$J$3000,A212),0)) -> 150 | Q212: =IF(L212="Not in catalogue","CHECK type",IF(F212<>Settings!$B$6,"CHECK unit",IF(OR(AND(M212="Credit",E212<=0),AND(M212="Debit",E212>=0)),"CHECK sign",IF(D212="Reversal",IF(OR(J212="",COUNTIF($A$5:$A$3000,J212)=0),"CHECK reversal link",IF(E212<>-INDEX($E$5:$E$3000,MATCH(J212,$A$5:$A$3000,0)),"CHECK reversal amount","OK")),IF(AND(D212="Adjustment",K212<>"",COUNTIF($A$5:$A$3000,J212)=0),"CHECK correction link","OK"))))) -> OK | R212: =INT(C212) -> 46295
A213: WTX-00209 | B213: U014 | C213: 46295.925 | D213: Reward Credit | E213: 500 | F213: Points | G213: Posted | H213: Campaign Bonus | I213: CMP-001 | L213: =IFERROR(INDEX(Transaction_Types!$B$5:$B$20,MATCH(D213,Transaction_Types!$A$5:$A$20,0)),"Not in catalogue") -> Supported | M213: =IFERROR(INDEX(Transaction_Types!$C$5:$C$20,MATCH(D213,Transaction_Types!$A$5:$A$20,0)),"") -> Credit | N213: =IF(G213="Posted",E213,0) -> 500 | O213: =COUNTIFS($J$5:$J$3000,A213,$K$5:$K$3000,"Reverses") -> 0 | P213: =IF(K213<>"","",IF(G213="Posted",E213+SUMIFS($N$5:$N$3000,$J$5:$J$3000,A213),0)) -> 500 | Q213: =IF(L213="Not in catalogue","CHECK type",IF(F213<>Settings!$B$6,"CHECK unit",IF(OR(AND(M213="Credit",E213<=0),AND(M213="Debit",E213>=0)),"CHECK sign",IF(D213="Reversal",IF(OR(J213="",COUNTIF($A$5:$A$3000,J213)=0),"CHECK reversal link",IF(E213<>-INDEX($E$5:$E$3000,MATCH(J213,$A$5:$A$3000,0)),"CHECK reversal amount","OK")),IF(AND(D213="Adjustment",K213<>"",COUNTIF($A$5:$A$3000,J213)=0),"CHECK correction link","OK"))))) -> OK | R213: =INT(C213) -> 46295
A214: WTX-00210 | B214: U012 | C214: 46295.96 | D214: Reward Credit | E214: 250 | F214: Points | G214: Posted | H214: Referral Reward | I214: REF-0043 | L214: =IFERROR(INDEX(Transaction_Types!$B$5:$B$20,MATCH(D214,Transaction_Types!$A$5:$A$20,0)),"Not in catalogue") -> Supported | M214: =IFERROR(INDEX(Transaction_Types!$C$5:$C$20,MATCH(D214,Transaction_Types!$A$5:$A$20,0)),"") -> Credit | N214: =IF(G214="Posted",E214,0) -> 250 | O214: =COUNTIFS($J$5:$J$3000,A214,$K$5:$K$3000,"Reverses") -> 0 | P214: =IF(K214<>"","",IF(G214="Posted",E214+SUMIFS($N$5:$N$3000,$J$5:$J$3000,A214),0)) -> 250 | Q214: =IF(L214="Not in catalogue","CHECK type",IF(F214<>Settings!$B$6,"CHECK unit",IF(OR(AND(M214="Credit",E214<=0),AND(M214="Debit",E214>=0)),"CHECK sign",IF(D214="Reversal",IF(OR(J214="",COUNTIF($A$5:$A$3000,J214)=0),"CHECK reversal link",IF(E214<>-INDEX($E$5:$E$3000,MATCH(J214,$A$5:$A$3000,0)),"CHECK reversal amount","OK")),IF(AND(D214="Adjustment",K214<>"",COUNTIF($A$5:$A$3000,J214)=0),"CHECK correction link","OK"))))) -> OK | R214: =INT(C214) -> 46295
A215: WTX-00211 | B215: U003 | C215: 46295.969 | D215: Reward Credit | E215: 250 | F215: Points | G215: Posted | H215: Task Reward | I215: TASK-1039 | L215: =IFERROR(INDEX(Transaction_Types!$B$5:$B$20,MATCH(D215,Transaction_Types!$A$5:$A$20,0)),"Not in catalogue") -> Supported | M215: =IFERROR(INDEX(Transaction_Types!$C$5:$C$20,MATCH(D215,Transaction_Types!$A$5:$A$20,0)),"") -> Credit | N215: =IF(G215="Posted",E215,0) -> 250 | O215: =COUNTIFS($J$5:$J$3000,A215,$K$5:$K$3000,"Reverses") -> 0 | P215: =IF(K215<>"","",IF(G215="Posted",E215+SUMIFS($N$5:$N$3000,$J$5:$J$3000,A215),0)) -> 250 | Q215: =IF(L215="Not in catalogue","CHECK type",IF(F215<>Settings!$B$6,"CHECK unit",IF(OR(AND(M215="Credit",E215<=0),AND(M215="Debit",E215>=0)),"CHECK sign",IF(D215="Reversal",IF(OR(J215="",COUNTIF($A$5:$A$3000,J215)=0),"CHECK reversal link",IF(E215<>-INDEX($E$5:$E$3000,MATCH(J215,$A$5:$A$3000,0)),"CHECK reversal amount","OK")),IF(AND(D215="Adjustment",K215<>"",COUNTIF($A$5:$A$3000,J215)=0),"CHECK correction link","OK"))))) -> OK | R215: =INT(C215) -> 46295
A216: WTX-00212 | B216: U002 | C216: 46296.226 | D216: Reward Credit | E216: 400 | F216: Points | G216: Posted | H216: Task Reward | I216: TASK-1027 | L216: =IFERROR(INDEX(Transaction_Types!$B$5:$B$20,MATCH(D216,Transaction_Types!$A$5:$A$20,0)),"Not in catalogue") -> Supported | M216: =IFERROR(INDEX(Transaction_Types!$C$5:$C$20,MATCH(D216,Transaction_Types!$A$5:$A$20,0)),"") -> Credit | N216: =IF(G216="Posted",E216,0) -> 400 | O216: =COUNTIFS($J$5:$J$3000,A216,$K$5:$K$3000,"Reverses") -> 0 | P216: =IF(K216<>"","",IF(G216="Posted",E216+SUMIFS($N$5:$N$3000,$J$5:$J$3000,A216),0)) -> 400 | Q216: =IF(L216="Not in catalogue","CHECK type",IF(F216<>Settings!$B$6,"CHECK unit",IF(OR(AND(M216="Credit",E216<=0),AND(M216="Debit",E216>=0)),"CHECK sign",IF(D216="Reversal",IF(OR(J216="",COUNTIF($A$5:$A$3000,J216)=0),"CHECK reversal link",IF(E216<>-INDEX($E$5:$E$3000,MATCH(J216,$A$5:$A$3000,0)),"CHECK reversal amount","OK")),IF(AND(D216="Adjustment",K216<>"",COUNTIF($A$5:$A$3000,J216)=0),"CHECK correction link","OK"))))) -> OK | R216: =INT(C216) -> 46296
A217: WTX-00213 | B217: U004 | C217: 46296.417 | D217: Adjustment | E217: 100 | F217: Points | G217: Posted | H217: Admin Console | I217: ADJ-009 | L217: =IFERROR(INDEX(Transaction_Types!$B$5:$B$20,MATCH(D217,Transaction_Types!$A$5:$A$20,0)),"Not in catalogue") -> Supported | M217: =IFERROR(INDEX(Transaction_Types!$C$5:$C$20,MATCH(D217,Transaction_Types!$A$5:$A$20,0)),"") -> Either | N217: =IF(G217="Posted",E217,0) -> 100 | O217: =COUNTIFS($J$5:$J$3000,A217,$K$5:$K$3000,"Reverses") -> 0 | P217: =IF(K217<>"","",IF(G217="Posted",E217+SUMIFS($N$5:$N$3000,$J$5:$J$3000,A217),0)) -> 100 | Q217: =IF(L217="Not in catalogue","CHECK type",IF(F217<>Settings!$B$6,"CHECK unit",IF(OR(AND(M217="Credit",E217<=0),AND(M217="Debit",E217>=0)),"CHECK sign",IF(D217="Reversal",IF(OR(J217="",COUNTIF($A$5:$A$3000,J217)=0),"CHECK reversal link",IF(E217<>-INDEX($E$5:$E$3000,MATCH(J217,$A$5:$A$3000,0)),"CHECK reversal amount","OK")),IF(AND(D217="Adjustment",K217<>"",COUNTIF($A$5:$A$3000,J217)=0),"CHECK correction link","OK"))))) -> OK | R217: =INT(C217) -> 46296
A218: WTX-00214 | B218: U011 | C218: 46296.59 | D218: Reward Credit | E218: 200 | F218: Points | G218: Posted | H218: Task Reward | I218: TASK-1137 | L218: =IFERROR(INDEX(Transaction_Types!$B$5:$B$20,MATCH(D218,Transaction_Types!$A$5:$A$20,0)),"Not in catalogue") -> Supported | M218: =IFERROR(INDEX(Transaction_Types!$C$5:$C$20,MATCH(D218,Transaction_Types!$A$5:$A$20,0)),"") -> Credit | N218: =IF(G218="Posted",E218,0) -> 200 | O218: =COUNTIFS($J$5:$J$3000,A218,$K$5:$K$3000,"Reverses") -> 0 | P218: =IF(K218<>"","",IF(G218="Posted",E218+SUMIFS($N$5:$N$3000,$J$5:$J$3000,A218),0)) -> 200 | Q218: =IF(L218="Not in catalogue","CHECK type",IF(F218<>Settings!$B$6,"CHECK unit",IF(OR(AND(M218="Credit",E218<=0),AND(M218="Debit",E218>=0)),"CHECK sign",IF(D218="Reversal",IF(OR(J218="",COUNTIF($A$5:$A$3000,J218)=0),"CHECK reversal link",IF(E218<>-INDEX($E$5:$E$3000,MATCH(J218,$A$5:$A$3000,0)),"CHECK reversal amount","OK")),IF(AND(D218="Adjustment",K218<>"",COUNTIF($A$5:$A$3000,J218)=0),"CHECK correction link","OK"))))) -> OK | R218: =INT(C218) -> 46296
A219: WTX-00215 | B219: U016 | C219: 46296.752 | D219: Reward Credit | E219: 400 | F219: Points | G219: Posted | H219: Task Reward | I219: TASK-1186 | L219: =IFERROR(INDEX(Transaction_Types!$B$5:$B$20,MATCH(D219,Transaction_Types!$A$5:$A$20,0)),"Not in catalogue") -> Supported | M219: =IFERROR(INDEX(Transaction_Types!$C$5:$C$20,MATCH(D219,Transaction_Types!$A$5:$A$20,0)),"") -> Credit | N219: =IF(G219="Posted",E219,0) -> 400 | O219: =COUNTIFS($J$5:$J$3000,A219,$K$5:$K$3000,"Reverses") -> 0 | P219: =IF(K219<>"","",IF(G219="Posted",E219+SUMIFS($N$5:$N$3000,$J$5:$J$3000,A219),0)) -> 400 | Q219: =IF(L219="Not in catalogue","CHECK type",IF(F219<>Settings!$B$6,"CHECK unit",IF(OR(AND(M219="Credit",E219<=0),AND(M219="Debit",E219>=0)),"CHECK sign",IF(D219="Reversal",IF(OR(J219="",COUNTIF($A$5:$A$3000,J219)=0),"CHECK reversal link",IF(E219<>-INDEX($E$5:$E$3000,MATCH(J219,$A$5:$A$3000,0)),"CHECK reversal amount","OK")),IF(AND(D219="Adjustment",K219<>"",COUNTIF($A$5:$A$3000,J219)=0),"CHECK correction link","OK"))))) -> OK | R219: =INT(C219) -> 46296
A220: WTX-00216 | B220: U004 | C220: 46296.974 | D220: Reward Credit | E220: 250 | F220: Points | G220: Posted | H220: Referral Reward | I220: REF-0026 | L220: =IFERROR(INDEX(Transaction_Types!$B$5:$B$20,MATCH(D220,Transaction_Types!$A$5:$A$20,0)),"Not in catalogue") -> Supported | M220: =IFERROR(INDEX(Transaction_Types!$C$5:$C$20,MATCH(D220,Transaction_Types!$A$5:$A$20,0)),"") -> Credit | N220: =IF(G220="Posted",E220,0) -> 250 | O220: =COUNTIFS($J$5:$J$3000,A220,$K$5:$K$3000,"Reverses") -> 0 | P220: =IF(K220<>"","",IF(G220="Posted",E220+SUMIFS($N$5:$N$3000,$J$5:$J$3000,A220),0)) -> 250 | Q220: =IF(L220="Not in catalogue","CHECK type",IF(F220<>Settings!$B$6,"CHECK unit",IF(OR(AND(M220="Credit",E220<=0),AND(M220="Debit",E220>=0)),"CHECK sign",IF(D220="Reversal",IF(OR(J220="",COUNTIF($A$5:$A$3000,J220)=0),"CHECK reversal link",IF(E220<>-INDEX($E$5:$E$3000,MATCH(J220,$A$5:$A$3000,0)),"CHECK reversal amount","OK")),IF(AND(D220="Adjustment",K220<>"",COUNTIF($A$5:$A$3000,J220)=0),"CHECK correction link","OK"))))) -> OK | R220: =INT(C220) -> 46296
... A226: WTX-00222 | B226: U020 | C226: 46298.541 | D226: Reward Credit | E226: 150 | F226: Points | G226: Posted | H226: Task Reward | I226: TASK-1244 | L226: =IFERROR(INDEX(Transaction_Types!$B$5:$B$20,MATCH(D226,Transaction_Types!$A$5:$A$20,0)),"Not in catalogue") -> Supported | M226: =IFERROR(INDEX(Transaction_Types!$C$5:$C$20,MATCH(D226,Transaction_Types!$A$5:$A$20,0)),"") -> Credit | N226: =IF(G226="Posted",E226,0) -> 150 | O226: =COUNTIFS($J$5:$J$3000,A226,$K$5:$K$3000,"Reverses") -> 0 | P226: =IF(K226<>"","",IF(G226="Posted",E226+SUMIFS($N$5:$N$3000,$J$5:$J$3000,A226),0)) -> 150 | Q226: =IF(L226="Not in catalogue","CHECK type",IF(F226<>Settings!$B$6,"CHECK unit",IF(OR(AND(M226="Credit",E226<=0),AND(M226="Debit",E226>=0)),"CHECK sign",IF(D226="Reversal",IF(OR(J226="",COUNTIF($A$5:$A$3000,J226)=0),"CHECK reversal link",IF(E226<>-INDEX($E$5:$E$3000,MATCH(J226,$A$5:$A$3000,0)),"CHECK reversal amount","OK")),IF(AND(D226="Adjustment",K226<>"",COUNTIF($A$5:$A$3000,J226)=0),"CHECK correction link","OK"))))) -> OK | R226: =INT(C226) -> 46298
A227: WTX-00223 | B227: U001 | C227: 46298.774 | D227: Reversal | E227: -150 | F227: Points | G227: Posted | H227: Admin Console | I227: TASK-1008 | J227: WTX-00187 | K227: Reverses | L227: =IFERROR(INDEX(Transaction_Types!$B$5:$B$20,MATCH(D227,Transaction_Types!$A$5:$A$20,0)),"Not in catalogue") -> Supported | M227: =IFERROR(INDEX(Transaction_Types!$C$5:$C$20,MATCH(D227,Transaction_Types!$A$5:$A$20,0)),"") -> Either | N227: =IF(G227="Posted",E227,0) -> -150 | O227: =COUNTIFS($J$5:$J$3000,A227,$K$5:$K$3000,"Reverses") -> 0 | P227: =IF(K227<>"","",IF(G227="Posted",E227+SUMIFS($N$5:$N$3000,$J$5:$J$3000,A227),0)) | Q227: =IF(L227="Not in catalogue","CHECK type",IF(F227<>Settings!$B$6,"CHECK unit",IF(OR(AND(M227="Credit",E227<=0),AND(M227="Debit",E227>=0)),"CHECK sign",IF(D227="Reversal",IF(OR(J227="",COUNTIF($A$5:$A$3000,J227)=0),"CHECK reversal link",IF(E227<>-INDEX($E$5:$E$3000,MATCH(J227,$A$5:$A$3000,0)),"CHECK reversal amount","OK")),IF(AND(D227="Adjustment",K227<>"",COUNTIF($A$5:$A$3000,J227)=0),"CHECK correction link","OK"))))) -> OK | R227: =INT(C227) -> 46298
A228: WTX-00224 | B228: U006 | C228: 46298.986 | D228: Reward Credit | E228: 150 | F228: Points | G228: Posted | H228: Task Reward | I228: TASK-1080 | L228: =IFERROR(INDEX(Transaction_Types!$B$5:$B$20,MATCH(D228,Transaction_Types!$A$5:$A$20,0)),"Not in catalogue") -> Supported | M228: =IFERROR(INDEX(Transaction_Types!$C$5:$C$20,MATCH(D228,Transaction_Types!$A$5:$A$20,0)),"") -> Credit | N228: =IF(G228="Posted",E228,0) -> 150 | O228: =COUNTIFS($J$5:$J$3000,A228,$K$5:$K$3000,"Reverses") -> 0 | P228: =IF(K228<>"","",IF(G228="Posted",E228+SUMIFS($N$5:$N$3000,$J$5:$J$3000,A228),0)) -> 150 | Q228: =IF(L228="Not in catalogue","CHECK type",IF(F228<>Settings!$B$6,"CHECK unit",IF(OR(AND(M228="Credit",E228<=0),AND(M228="Debit",E228>=0)),"CHECK sign",IF(D228="Reversal",IF(OR(J228="",COUNTIF($A$5:$A$3000,J228)=0),"CHECK reversal link",IF(E228<>-INDEX($E$5:$E$3000,MATCH(J228,$A$5:$A$3000,0)),"CHECK reversal amount","OK")),IF(AND(D228="Adjustment",K228<>"",COUNTIF($A$5:$A$3000,J228)=0),"CHECK correction link","OK"))))) -> OK | R228: =INT(C228) -> 46298
A229: WTX-00225 | B229: U007 | C229: 46299.058 | D229: Reward Credit | E229: 300 | F229: Points | G229: Posted | H229: Referral Reward | I229: REF-0048 | L229: =IFERROR(INDEX(Transaction_Types!$B$5:$B$20,MATCH(D229,Transaction_Types!$A$5:$A$20,0)),"Not in catalogue") -> Supported | M229: =IFERROR(INDEX(Transaction_Types!$C$5:$C$20,MATCH(D229,Transaction_Types!$A$5:$A$20,0)),"") -> Credit | N229: =IF(G229="Posted",E229,0) -> 300 | O229: =COUNTIFS($J$5:$J$3000,A229,$K$5:$K$3000,"Reverses") -> 0 | P229: =IF(K229<>"","",IF(G229="Posted",E229+SUMIFS($N$5:$N$3000,$J$5:$J$3000,A229),0)) -> 300 | Q229: =IF(L229="Not in catalogue","CHECK type",IF(F229<>Settings!$B$6,"CHECK unit",IF(OR(AND(M229="Credit",E229<=0),AND(M229="Debit",E229>=0)),"CHECK sign",IF(D229="Reversal",IF(OR(J229="",COUNTIF($A$5:$A$3000,J229)=0),"CHECK reversal link",IF(E229<>-INDEX($E$5:$E$3000,MATCH(J229,$A$5:$A$3000,0)),"CHECK reversal amount","OK")),IF(AND(D229="Adjustment",K229<>"",COUNTIF($A$5:$A$3000,J229)=0),"CHECK correction link","OK"))))) -> OK | R229: =INT(C229) -> 46299
A230: WTX-00226 | B230: U006 | C230: 46299.269 | D230: Reward Credit | E230: 100 | F230: Points | G230: Posted | H230: Task Reward | I230: TASK-1067 | L230: =IFERROR(INDEX(Transaction_Types!$B$5:$B$20,MATCH(D230,Transaction_Types!$A$5:$A$20,0)),"Not in catalogue") -> Supported | M230: =IFERROR(INDEX(Transaction_Types!$C$5:$C$20,MATCH(D230,Transaction_Types!$A$5:$A$20,0)),"") -> Credit | N230: =IF(G230="Posted",E230,0) -> 100 | O230: =COUNTIFS($J$5:$J$3000,A230,$K$5:$K$3000,"Reverses") -> 0 | P230: =IF(K230<>"","",IF(G230="Posted",E230+SUMIFS($N$5:$N$3000,$J$5:$J$3000,A230),0)) -> 100 | Q230: =IF(L230="Not in catalogue","CHECK type",IF(F230<>Settings!$B$6,"CHECK unit",IF(OR(AND(M230="Credit",E230<=0),AND(M230="Debit",E230>=0)),"CHECK sign",IF(D230="Reversal",IF(OR(J230="",COUNTIF($A$5:$A$3000,J230)=0),"CHECK reversal link",IF(E230<>-INDEX($E$5:$E$3000,MATCH(J230,$A$5:$A$3000,0)),"CHECK reversal amount","OK")),IF(AND(D230="Adjustment",K230<>"",COUNTIF($A$5:$A$3000,J230)=0),"CHECK correction link","OK"))))) -> OK | R230: =INT(C230) -> 46299
A231: WTX-00227 | B231: U018 | C231: 46299.33 | D231: Reward Credit | E231: 300 | F231: Points | G231: Posted | H231: Task Reward | I231: TASK-1213 | L231: =IFERROR(INDEX(Transaction_Types!$B$5:$B$20,MATCH(D231,Transaction_Types!$A$5:$A$20,0)),"Not in catalogue") -> Supported | M231: =IFERROR(INDEX(Transaction_Types!$C$5:$C$20,MATCH(D231,Transaction_Types!$A$5:$A$20,0)),"") -> Credit | N231: =IF(G231="Posted",E231,0) -> 300 | O231: =COUNTIFS($J$5:$J$3000,A231,$K$5:$K$3000,"Reverses") -> 0 | P231: =IF(K231<>"","",IF(G231="Posted",E231+SUMIFS($N$5:$N$3000,$J$5:$J$3000,A231),0)) -> 300 | Q231: =IF(L231="Not in catalogue","CHECK type",IF(F231<>Settings!$B$6,"CHECK unit",IF(OR(AND(M231="Credit",E231<=0),AND(M231="Debit",E231>=0)),"CHECK sign",IF(D231="Reversal",IF(OR(J231="",COUNTIF($A$5:$A$3000,J231)=0),"CHECK reversal link",IF(E231<>-INDEX($E$5:$E$3000,MATCH(J231,$A$5:$A$3000,0)),"CHECK reversal amount","OK")),IF(AND(D231="Adjustment",K231<>"",COUNTIF($A$5:$A$3000,J231)=0),"CHECK correction link","OK"))))) -> OK | R231: =INT(C231) -> 46299
A232: WTX-00228 | B232: U014 | C232: 46299.398 | D232: Reward Credit | E232: 300 | F232: Points | G232: Posted | H232: Referral Reward | I232: REF-0009 | L232: =IFERROR(INDEX(Transaction_Types!$B$5:$B$20,MATCH(D232,Transaction_Types!$A$5:$A$20,0)),"Not in catalogue") -> Supported | M232: =IFERROR(INDEX(Transaction_Types!$C$5:$C$20,MATCH(D232,Transaction_Types!$A$5:$A$20,0)),"") -> Credit | N232: =IF(G232="Posted",E232,0) -> 300 | O232: =COUNTIFS($J$5:$J$3000,A232,$K$5:$K$3000,"Reverses") -> 0 | P232: =IF(K232<>"","",IF(G232="Posted",E232+SUMIFS($N$5:$N$3000,$J$5:$J$3000,A232),0)) -> 300 | Q232: =IF(L232="Not in catalogue","CHECK type",IF(F232<>Settings!$B$6,"CHECK unit",IF(OR(AND(M232="Credit",E232<=0),AND(M232="Debit",E232>=0)),"CHECK sign",IF(D232="Reversal",IF(OR(J232="",COUNTIF($A$5:$A$3000,J232)=0),"CHECK reversal link",IF(E232<>-INDEX($E$5:$E$3000,MATCH(J232,$A$5:$A$3000,0)),"CHECK reversal amount","OK")),IF(AND(D232="Adjustment",K232<>"",COUNTIF($A$5:$A$3000,J232)=0),"CHECK correction link","OK"))))) -> OK | R232: =INT(C232) -> 46299
A233: WTX-00229 | B233: U015 | C233: 46299.939 | D233: Reward Credit | E233: 200 | F233: Points | G233: Posted | H233: Referral Reward | I233: REF-0052 | L233: =IFERROR(INDEX(Transaction_Types!$B$5:$B$20,MATCH(D233,Transaction_Types!$A$5:$A$20,0)),"Not in catalogue") -> Supported | M233: =IFERROR(INDEX(Transaction_Types!$C$5:$C$20,MATCH(D233,Transaction_Types!$A$5:$A$20,0)),"") -> Credit | N233: =IF(G233="Posted",E233,0) -> 200 | O233: =COUNTIFS($J$5:$J$3000,A233,$K$5:$K$3000,"Reverses") -> 0 | P233: =IF(K233<>"","",IF(G233="Posted",E233+SUMIFS($N$5:$N$3000,$J$5:$J$3000,A233),0)) -> 200 | Q233: =IF(L233="Not in catalogue","CHECK type",IF(F233<>Settings!$B$6,"CHECK unit",IF(OR(AND(M233="Credit",E233<=0),AND(M233="Debit",E233>=0)),"CHECK sign",IF(D233="Reversal",IF(OR(J233="",COUNTIF($A$5:$A$3000,J233)=0),"CHECK reversal link",IF(E233<>-INDEX($E$5:$E$3000,MATCH(J233,$A$5:$A$3000,0)),"CHECK reversal amount","OK")),IF(AND(D233="Adjustment",K233<>"",COUNTIF($A$5:$A$3000,J233)=0),"CHECK correction link","OK"))))) -> OK | R233: =INT(C233) -> 46299
A234: WTX-00230 | B234: U008 | C234: 46299.947 | D234: Reversal | E234: -200 | F234: Points | G234: Posted | H234: Admin Console | I234: TASK-1106 | J234: WTX-00219 | K234: Reverses | L234: =IFERROR(INDEX(Transaction_Types!$B$5:$B$20,MATCH(D234,Transaction_Types!$A$5:$A$20,0)),"Not in catalogue") -> Supported | M234: =IFERROR(INDEX(Transaction_Types!$C$5:$C$20,MATCH(D234,Transaction_Types!$A$5:$A$20,0)),"") -> Either | N234: =IF(G234="Posted",E234,0) -> -200 | O234: =COUNTIFS($J$5:$J$3000,A234,$K$5:$K$3000,"Reverses") -> 0 | P234: =IF(K234<>"","",IF(G234="Posted",E234+SUMIFS($N$5:$N$3000,$J$5:$J$3000,A234),0)) | Q234: =IF(L234="Not in catalogue","CHECK type",IF(F234<>Settings!$B$6,"CHECK unit",IF(OR(AND(M234="Credit",E234<=0),AND(M234="Debit",E234>=0)),"CHECK sign",IF(D234="Reversal",IF(OR(J234="",COUNTIF($A$5:$A$3000,J234)=0),"CHECK reversal link",IF(E234<>-INDEX($E$5:$E$3000,MATCH(J234,$A$5:$A$3000,0)),"CHECK reversal amount","OK")),IF(AND(D234="Adjustment",K234<>"",COUNTIF($A$5:$A$3000,J234)=0),"CHECK correction link","OK"))))) -> OK | R234: =INT(C234) -> 46299
A235: WTX-00231 | B235: U019 | C235: 46300.229 | D235: Reward Credit | E235: 200 | F235: Points | G235: Posted | H235: Task Reward | I235: TASK-1229 | L235: =IFERROR(INDEX(Transaction_Types!$B$5:$B$20,MATCH(D235,Transaction_Types!$A$5:$A$20,0)),"Not in catalogue") -> Supported | M235: =IFERROR(INDEX(Transaction_Types!$C$5:$C$20,MATCH(D235,Transaction_Types!$A$5:$A$20,0)),"") -> Credit | N235: =IF(G235="Posted",E235,0) -> 200 | O235: =COUNTIFS($J$5:$J$3000,A235,$K$5:$K$3000,"Reverses") -> 0 | P235: =IF(K235<>"","",IF(G235="Posted",E235+SUMIFS($N$5:$N$3000,$J$5:$J$3000,A235),0)) -> 200 | Q235: =IF(L235="Not in catalogue","CHECK type",IF(F235<>Settings!$B$6,"CHECK unit",IF(OR(AND(M235="Credit",E235<=0),AND(M235="Debit",E235>=0)),"CHECK sign",IF(D235="Reversal",IF(OR(J235="",COUNTIF($A$5:$A$3000,J235)=0),"CHECK reversal link",IF(E235<>-INDEX($E$5:$E$3000,MATCH(J235,$A$5:$A$3000,0)),"CHECK reversal amount","OK")),IF(AND(D235="Adjustment",K235<>"",COUNTIF($A$5:$A$3000,J235)=0),"CHECK correction link","OK"))))) -> OK | R235: =INT(C235) -> 46300
A236: WTX-00232 | B236: U007 | C236: 46300.249 | D236: Redemption | E236: -1500 | F236: Points | G236: Posted | H236: Withdrawal | I236: WD-0031 | L236: =IFERROR(INDEX(Transaction_Types!$B$5:$B$20,MATCH(D236,Transaction_Types!$A$5:$A$20,0)),"Not in catalogue") -> Supported | M236: =IFERROR(INDEX(Transaction_Types!$C$5:$C$20,MATCH(D236,Transaction_Types!$A$5:$A$20,0)),"") -> Debit | N236: =IF(G236="Posted",E236,0) -> -1500 | O236: =COUNTIFS($J$5:$J$3000,A236,$K$5:$K$3000,"Reverses") -> 0 | P236: =IF(K236<>"","",IF(G236="Posted",E236+SUMIFS($N$5:$N$3000,$J$5:$J$3000,A236),0)) -> -1500 | Q236: =IF(L236="Not in catalogue","CHECK type",IF(F236<>Settings!$B$6,"CHECK unit",IF(OR(AND(M236="Credit",E236<=0),AND(M236="Debit",E236>=0)),"CHECK sign",IF(D236="Reversal",IF(OR(J236="",COUNTIF($A$5:$A$3000,J236)=0),"CHECK reversal link",IF(E236<>-INDEX($E$5:$E$3000,MATCH(J236,$A$5:$A$3000,0)),"CHECK reversal amount","OK")),IF(AND(D236="Adjustment",K236<>"",COUNTIF($A$5:$A$3000,J236)=0),"CHECK correction link","OK"))))) -> OK | R236: =INT(C236) -> 46300
A237: WTX-00233 | B237: U015 | C237: 46300.426 | D237: Reward Credit | E237: 400 | F237: Points | G237: Posted | H237: Task Reward | I237: TASK-1178 | L237: =IFERROR(INDEX(Transaction_Types!$B$5:$B$20,MATCH(D237,Transaction_Types!$A$5:$A$20,0)),"Not in catalogue") -> Supported | M237: =IFERROR(INDEX(Transaction_Types!$C$5:$C$20,MATCH(D237,Transaction_Types!$A$5:$A$20,0)),"") -> Credit | N237: =IF(G237="Posted",E237,0) -> 400 | O237: =COUNTIFS($J$5:$J$3000,A237,$K$5:$K$3000,"Reverses") -> 0 | P237: =IF(K237<>"","",IF(G237="Posted",E237+SUMIFS($N$5:$N$3000,$J$5:$J$3000,A237),0)) -> 400 | Q237: =IF(L237="Not in catalogue","CHECK type",IF(F237<>Settings!$B$6,"CHECK unit",IF(OR(AND(M237="Credit",E237<=0),AND(M237="Debit",E237>=0)),"CHECK sign",IF(D237="Reversal",IF(OR(J237="",COUNTIF($A$5:$A$3000,J237)=0),"CHECK reversal link",IF(E237<>-INDEX($E$5:$E$3000,MATCH(J237,$A$5:$A$3000,0)),"CHECK reversal amount","OK")),IF(AND(D237="Adjustment",K237<>"",COUNTIF($A$5:$A$3000,J237)=0),"CHECK correction link","OK"))))) -> OK | R237: =INT(C237) -> 46300
A238: WTX-00234 | B238: U002 | C238: 46300.458 | D238: Reward Credit | E238: 250 | F238: Points | G238: Posted | H238: Task Reward | I238: TASK-1021 | L238: =IFERROR(INDEX(Transaction_Types!$B$5:$B$20,MATCH(D238,Transaction_Types!$A$5:$A$20,0)),"Not in catalogue") -> Supported | M238: =IFERROR(INDEX(Transaction_Types!$C$5:$C$20,MATCH(D238,Transaction_Types!$A$5:$A$20,0)),"") -> Credit | N238: =IF(G238="Posted",E238,0) -> 250 | O238: =COUNTIFS($J$5:$J$3000,A238,$K$5:$K$3000,"Reverses") -> 0 | P238: =IF(K238<>"","",IF(G238="Posted",E238+SUMIFS($N$5:$N$3000,$J$5:$J$3000,A238),0)) -> 250 | Q238: =IF(L238="Not in catalogue","CHECK type",IF(F238<>Settings!$B$6,"CHECK unit",IF(OR(AND(M238="Credit",E238<=0),AND(M238="Debit",E238>=0)),"CHECK sign",IF(D238="Reversal",IF(OR(J238="",COUNTIF($A$5:$A$3000,J238)=0),"CHECK reversal link",IF(E238<>-INDEX($E$5:$E$3000,MATCH(J238,$A$5:$A$3000,0)),"CHECK reversal amount","OK")),IF(AND(D238="Adjustment",K238<>"",COUNTIF($A$5:$A$3000,J238)=0),"CHECK correction link","OK"))))) -> OK | R238: =INT(C238) -> 46300
A239: WTX-00235 | B239: U011 | C239: 46300.565 | D239: Reward Credit | E239: 250 | F239: Points | G239: Posted | H239: Task Reward | I239: TASK-1136 | L239: =IFERROR(INDEX(Transaction_Types!$B$5:$B$20,MATCH(D239,Transaction_Types!$A$5:$A$20,0)),"Not in catalogue") -> Supported | M239: =IFERROR(INDEX(Transaction_Types!$C$5:$C$20,MATCH(D239,Transaction_Types!$A$5:$A$20,0)),"") -> Credit | N239: =IF(G239="Posted",E239,0) -> 250 | O239: =COUNTIFS($J$5:$J$3000,A239,$K$5:$K$3000,"Reverses") -> 0 | P239: =IF(K239<>"","",IF(G239="Posted",E239+SUMIFS($N$5:$N$3000,$J$5:$J$3000,A239),0)) -> 250 | Q239: =IF(L239="Not in catalogue","CHECK type",IF(F239<>Settings!$B$6,"CHECK unit",IF(OR(AND(M239="Credit",E239<=0),AND(M239="Debit",E239>=0)),"CHECK sign",IF(D239="Reversal",IF(OR(J239="",COUNTIF($A$5:$A$3000,J239)=0),"CHECK reversal link",IF(E239<>-INDEX($E$5:$E$3000,MATCH(J239,$A$5:$A$3000,0)),"CHECK reversal amount","OK")),IF(AND(D239="Adjustment",K239<>"",COUNTIF($A$5:$A$3000,J239)=0),"CHECK correction link","OK"))))) -> OK | R239: =INT(C239) -> 46300
A240: WTX-00236 | B240: U020 | C240: 46300.763 | D240: Reward Credit | E240: 100 | F240: Points | G240: Posted | H240: Task Reward | I240: TASK-1246 | L240: =IFERROR(INDEX(Transaction_Types!$B$5:$B$20,MATCH(D240,Transaction_Types!$A$5:$A$20,0)),"Not in catalogue") -> Supported | M240: =IFERROR(INDEX(Transaction_Types!$C$5:$C$20,MATCH(D240,Transaction_Types!$A$5:$A$20,0)),"") -> Credit | N240: =IF(G240="Posted",E240,0) -> 100 | O240: =COUNTIFS($J$5:$J$3000,A240,$K$5:$K$3000,"Reverses") -> 1 | P240: =IF(K240<>"","",IF(G240="Posted",E240+SUMIFS($N$5:$N$3000,$J$5:$J$3000,A240),0)) -> 0 | Q240: =IF(L240="Not in catalogue","CHECK type",IF(F240<>Settings!$B$6,"CHECK unit",IF(OR(AND(M240="Credit",E240<=0),AND(M240="Debit",E240>=0)),"CHECK sign",IF(D240="Reversal",IF(OR(J240="",COUNTIF($A$5:$A$3000,J240)=0),"CHECK reversal link",IF(E240<>-INDEX($E$5:$E$3000,MATCH(J240,$A$5:$A$3000,0)),"CHECK reversal amount","OK")),IF(AND(D240="Adjustment",K240<>"",COUNTIF($A$5:$A$3000,J240)=0),"CHECK correction link","OK"))))) -> OK | R240: =INT(C240) -> 46300
A241: WTX-00237 | B241: U003 | C241: 46300.963 | D241: Reward Credit | E241: 400 | F241: Points | G241: Posted | H241: Task Reward | I241: TASK-1032 | L241: =IFERROR(INDEX(Transaction_Types!$B$5:$B$20,MATCH(D241,Transaction_Types!$A$5:$A$20,0)),"Not in catalogue") -> Supported | M241: =IFERROR(INDEX(Transaction_Types!$C$5:$C$20,MATCH(D241,Transaction_Types!$A$5:$A$20,0)),"") -> Credit | N241: =IF(G241="Posted",E241,0) -> 400 | O241: =COUNTIFS($J$5:$J$3000,A241,$K$5:$K$3000,"Reverses") -> 0 | P241: =IF(K241<>"","",IF(G241="Posted",E241+SUMIFS($N$5:$N$3000,$J$5:$J$3000,A241),0)) -> 400 | Q241: =IF(L241="Not in catalogue","CHECK type",IF(F241<>Settings!$B$6,"CHECK unit",IF(OR(AND(M241="Credit",E241<=0),AND(M241="Debit",E241>=0)),"CHECK sign",IF(D241="Reversal",IF(OR(J241="",COUNTIF($A$5:$A$3000,J241)=0),"CHECK reversal link",IF(E241<>-INDEX($E$5:$E$3000,MATCH(J241,$A$5:$A$3000,0)),"CHECK reversal amount","OK")),IF(AND(D241="Adjustment",K241<>"",COUNTIF($A$5:$A$3000,J241)=0),"CHECK correction link","OK"))))) -> OK | R241: =INT(C241) -> 46300
A242: WTX-00238 | B242: U013 | C242: 46301.327 | D242: Reward Credit | E242: 200 | F242: Points | G242: Posted | H242: Task Reward | I242: TASK-1156 | L242: =IFERROR(INDEX(Transaction_Types!$B$5:$B$20,MATCH(D242,Transaction_Types!$A$5:$A$20,0)),"Not in catalogue") -> Supported | M242: =IFERROR(INDEX(Transaction_Types!$C$5:$C$20,MATCH(D242,Transaction_Types!$A$5:$A$20,0)),"") -> Credit | N242: =IF(G242="Posted",E242,0) -> 200 | O242: =COUNTIFS($J$5:$J$3000,A242,$K$5:$K$3000,"Reverses") -> 0 | P242: =IF(K242<>"","",IF(G242="Posted",E242+SUMIFS($N$5:$N$3000,$J$5:$J$3000,A242),0)) -> 200 | Q242: =IF(L242="Not in catalogue","CHECK type",IF(F242<>Settings!$B$6,"CHECK unit",IF(OR(AND(M242="Credit",E242<=0),AND(M242="Debit",E242>=0)),"CHECK sign",IF(D242="Reversal",IF(OR(J242="",COUNTIF($A$5:$A$3000,J242)=0),"CHECK reversal link",IF(E242<>-INDEX($E$5:$E$3000,MATCH(J242,$A$5:$A$3000,0)),"CHECK reversal amount","OK")),IF(AND(D242="Adjustment",K242<>"",COUNTIF($A$5:$A$3000,J242)=0),"CHECK correction link","OK"))))) -> OK | R242: =INT(C242) -> 46301
A243: WTX-00239 | B243: U002 | C243: 46301.372 | D243: Reward Credit | E243: 300 | F243: Points | G243: Posted | H243: Task Reward | I243: TASK-1015 | L243: =IFERROR(INDEX(Transaction_Types!$B$5:$B$20,MATCH(D243,Transaction_Types!$A$5:$A$20,0)),"Not in catalogue") -> Supported | M243: =IFERROR(INDEX(Transaction_Types!$C$5:$C$20,MATCH(D243,Transaction_Types!$A$5:$A$20,0)),"") -> Credit | N243: =IF(G243="Posted",E243,0) -> 300 | O243: =COUNTIFS($J$5:$J$3000,A243,$K$5:$K$3000,"Reverses") -> 0 | P243: =IF(K243<>"","",IF(G243="Posted",E243+SUMIFS($N$5:$N$3000,$J$5:$J$3000,A243),0)) -> 300 | Q243: =IF(L243="Not in catalogue","CHECK type",IF(F243<>Settings!$B$6,"CHECK unit",IF(OR(AND(M243="Credit",E243<=0),AND(M243="Debit",E243>=0)),"CHECK sign",IF(D243="Reversal",IF(OR(J243="",COUNTIF($A$5:$A$3000,J243)=0),"CHECK reversal link",IF(E243<>-INDEX($E$5:$E$3000,MATCH(J243,$A$5:$A$3000,0)),"CHECK reversal amount","OK")),IF(AND(D243="Adjustment",K243<>"",COUNTIF($A$5:$A$3000,J243)=0),"CHECK correction link","OK"))))) -> OK | R243: =INT(C243) -> 46301
A244: WTX-00240 | B244: U010 | C244: 46301.879 | D244: Reward Credit | E244: 100 | F244: Points | G244: Posted | H244: Task Reward | I244: TASK-1121 | L244: =IFERROR(INDEX(Transaction_Types!$B$5:$B$20,MATCH(D244,Transaction_Types!$A$5:$A$20,0)),"Not in catalogue") -> Supported | M244: =IFERROR(INDEX(Transaction_Types!$C$5:$C$20,MATCH(D244,Transaction_Types!$A$5:$A$20,0)),"") -> Credit | N244: =IF(G244="Posted",E244,0) -> 100 | O244: =COUNTIFS($J$5:$J$3000,A244,$K$5:$K$3000,"Reverses") -> 0 | P244: =IF(K244<>"","",IF(G244="Posted",E244+SUMIFS($N$5:$N$3000,$J$5:$J$3000,A244),0)) -> 100 | Q244: =IF(L244="Not in catalogue","CHECK type",IF(F244<>Settings!$B$6,"CHECK unit",IF(OR(AND(M244="Credit",E244<=0),AND(M244="Debit",E244>=0)),"CHECK sign",IF(D244="Reversal",IF(OR(J244="",COUNTIF($A$5:$A$3000,J244)=0),"CHECK reversal link",IF(E244<>-INDEX($E$5:$E$3000,MATCH(J244,$A$5:$A$3000,0)),"CHECK reversal amount","OK")),IF(AND(D244="Adjustment",K244<>"",COUNTIF($A$5:$A$3000,J244)=0),"CHECK correction link","OK"))))) -> OK | R244: =INT(C244) -> 46301
A245: WTX-00241 | B245: U005 | C245: 46301.881 | D245: Reward Credit | E245: 500 | F245: Points | G245: Posted | H245: Campaign Bonus | I245: CMP-001 | L245: =IFERROR(INDEX(Transaction_Types!$B$5:$B$20,MATCH(D245,Transaction_Types!$A$5:$A$20,0)),"Not in catalogue") -> Supported | M245: =IFERROR(INDEX(Transaction_Types!$C$5:$C$20,MATCH(D245,Transaction_Types!$A$5:$A$20,0)),"") -> Credit | N245: =IF(G245="Posted",E245,0) -> 500 | O245: =COUNTIFS($J$5:$J$3000,A245,$K$5:$K$3000,"Reverses") -> 0 | P245: =IF(K245<>"","",IF(G245="Posted",E245+SUMIFS($N$5:$N$3000,$J$5:$J$3000,A245),0)) -> 500 | Q245: =IF(L245="Not in catalogue","CHECK type",IF(F245<>Settings!$B$6,"CHECK unit",IF(OR(AND(M245="Credit",E245<=0),AND(M245="Debit",E245>=0)),"CHECK sign",IF(D245="Reversal",IF(OR(J245="",COUNTIF($A$5:$A$3000,J245)=0),"CHECK reversal link",IF(E245<>-INDEX($E$5:$E$3000,MATCH(J245,$A$5:$A$3000,0)),"CHECK reversal amount","OK")),IF(AND(D245="Adjustment",K245<>"",COUNTIF($A$5:$A$3000,J245)=0),"CHECK correction link","OK"))))) -> OK | R245: =INT(C245) -> 46301
A246: WTX-00242 | B246: U015 | C246: 46302.34 | D246: Reward Credit | E246: 200 | F246: Points | G246: Pending | H246: Task Reward | I246: TASK-1250 | L246: =IFERROR(INDEX(Transaction_Types!$B$5:$B$20,MATCH(D246,Transaction_Types!$A$5:$A$20,0)),"Not in catalogue") -> Supported | M246: =IFERROR(INDEX(Transaction_Types!$C$5:$C$20,MATCH(D246,Transaction_Types!$A$5:$A$20,0)),"") -> Credit | N246: =IF(G246="Posted",E246,0) -> 0 | O246: =COUNTIFS($J$5:$J$3000,A246,$K$5:$K$3000,"Reverses") -> 0 | P246: =IF(K246<>"","",IF(G246="Posted",E246+SUMIFS($N$5:$N$3000,$J$5:$J$3000,A246),0)) -> 0 | Q246: =IF(L246="Not in catalogue","CHECK type",IF(F246<>Settings!$B$6,"CHECK unit",IF(OR(AND(M246="Credit",E246<=0),AND(M246="Debit",E246>=0)),"CHECK sign",IF(D246="Reversal",IF(OR(J246="",COUNTIF($A$5:$A$3000,J246)=0),"CHECK reversal link",IF(E246<>-INDEX($E$5:$E$3000,MATCH(J246,$A$5:$A$3000,0)),"CHECK reversal amount","OK")),IF(AND(D246="Adjustment",K246<>"",COUNTIF($A$5:$A$3000,J246)=0),"CHECK correction link","OK"))))) -> OK | R246: =INT(C246) -> 46302
... A251: WTX-00247 | B251: U005 | C251: 46302.685 | D251: Reward Credit | E251: 250 | F251: Points | G251: Posted | H251: Task Reward | I251: TASK-1065 | L251: =IFERROR(INDEX(Transaction_Types!$B$5:$B$20,MATCH(D251,Transaction_Types!$A$5:$A$20,0)),"Not in catalogue") -> Supported | M251: =IFERROR(INDEX(Transaction_Types!$C$5:$C$20,MATCH(D251,Transaction_Types!$A$5:$A$20,0)),"") -> Credit | N251: =IF(G251="Posted",E251,0) -> 250 | O251: =COUNTIFS($J$5:$J$3000,A251,$K$5:$K$3000,"Reverses") -> 0 | P251: =IF(K251<>"","",IF(G251="Posted",E251+SUMIFS($N$5:$N$3000,$J$5:$J$3000,A251),0)) -> 250 | Q251: =IF(L251="Not in catalogue","CHECK type",IF(F251<>Settings!$B$6,"CHECK unit",IF(OR(AND(M251="Credit",E251<=0),AND(M251="Debit",E251>=0)),"CHECK sign",IF(D251="Reversal",IF(OR(J251="",COUNTIF($A$5:$A$3000,J251)=0),"CHECK reversal link",IF(E251<>-INDEX($E$5:$E$3000,MATCH(J251,$A$5:$A$3000,0)),"CHECK reversal amount","OK")),IF(AND(D251="Adjustment",K251<>"",COUNTIF($A$5:$A$3000,J251)=0),"CHECK correction link","OK"))))) -> OK | R251: =INT(C251) -> 46302
A252: WTX-00248 | B252: U020 | C252: 46302.888 | D252: Reversal | E252: -100 | F252: Points | G252: Posted | H252: Admin Console | I252: TASK-1246 | J252: WTX-00236 | K252: Reverses | L252: =IFERROR(INDEX(Transaction_Types!$B$5:$B$20,MATCH(D252,Transaction_Types!$A$5:$A$20,0)),"Not in catalogue") -> Supported | M252: =IFERROR(INDEX(Transaction_Types!$C$5:$C$20,MATCH(D252,Transaction_Types!$A$5:$A$20,0)),"") -> Either | N252: =IF(G252="Posted",E252,0) -> -100 | O252: =COUNTIFS($J$5:$J$3000,A252,$K$5:$K$3000,"Reverses") -> 0 | P252: =IF(K252<>"","",IF(G252="Posted",E252+SUMIFS($N$5:$N$3000,$J$5:$J$3000,A252),0)) | Q252: =IF(L252="Not in catalogue","CHECK type",IF(F252<>Settings!$B$6,"CHECK unit",IF(OR(AND(M252="Credit",E252<=0),AND(M252="Debit",E252>=0)),"CHECK sign",IF(D252="Reversal",IF(OR(J252="",COUNTIF($A$5:$A$3000,J252)=0),"CHECK reversal link",IF(E252<>-INDEX($E$5:$E$3000,MATCH(J252,$A$5:$A$3000,0)),"CHECK reversal amount","OK")),IF(AND(D252="Adjustment",K252<>"",COUNTIF($A$5:$A$3000,J252)=0),"CHECK correction link","OK"))))) -> OK | R252: =INT(C252) -> 46302
A253: WTX-00249 | B253: U016 | C253: 46303.328 | D253: Reward Credit | E253: 200 | F253: Points | G253: Posted | H253: Referral Reward | I253: REF-0057 | L253: =IFERROR(INDEX(Transaction_Types!$B$5:$B$20,MATCH(D253,Transaction_Types!$A$5:$A$20,0)),"Not in catalogue") -> Supported | M253: =IFERROR(INDEX(Transaction_Types!$C$5:$C$20,MATCH(D253,Transaction_Types!$A$5:$A$20,0)),"") -> Credit | N253: =IF(G253="Posted",E253,0) -> 200 | O253: =COUNTIFS($J$5:$J$3000,A253,$K$5:$K$3000,"Reverses") -> 0 | P253: =IF(K253<>"","",IF(G253="Posted",E253+SUMIFS($N$5:$N$3000,$J$5:$J$3000,A253),0)) -> 200 | Q253: =IF(L253="Not in catalogue","CHECK type",IF(F253<>Settings!$B$6,"CHECK unit",IF(OR(AND(M253="Credit",E253<=0),AND(M253="Debit",E253>=0)),"CHECK sign",IF(D253="Reversal",IF(OR(J253="",COUNTIF($A$5:$A$3000,J253)=0),"CHECK reversal link",IF(E253<>-INDEX($E$5:$E$3000,MATCH(J253,$A$5:$A$3000,0)),"CHECK reversal amount","OK")),IF(AND(D253="Adjustment",K253<>"",COUNTIF($A$5:$A$3000,J253)=0),"CHECK correction link","OK"))))) -> OK | R253: =INT(C253) -> 46303
A254: WTX-00250 | B254: U001 | C254: 46303.377 | D254: Reward Credit | E254: 200 | F254: Points | G254: Posted | H254: Task Reward | I254: TASK-1002 | L254: =IFERROR(INDEX(Transaction_Types!$B$5:$B$20,MATCH(D254,Transaction_Types!$A$5:$A$20,0)),"Not in catalogue") -> Supported | M254: =IFERROR(INDEX(Transaction_Types!$C$5:$C$20,MATCH(D254,Transaction_Types!$A$5:$A$20,0)),"") -> Credit | N254: =IF(G254="Posted",E254,0) -> 200 | O254: =COUNTIFS($J$5:$J$3000,A254,$K$5:$K$3000,"Reverses") -> 0 | P254: =IF(K254<>"","",IF(G254="Posted",E254+SUMIFS($N$5:$N$3000,$J$5:$J$3000,A254),0)) -> 200 | Q254: =IF(L254="Not in catalogue","CHECK type",IF(F254<>Settings!$B$6,"CHECK unit",IF(OR(AND(M254="Credit",E254<=0),AND(M254="Debit",E254>=0)),"CHECK sign",IF(D254="Reversal",IF(OR(J254="",COUNTIF($A$5:$A$3000,J254)=0),"CHECK reversal link",IF(E254<>-INDEX($E$5:$E$3000,MATCH(J254,$A$5:$A$3000,0)),"CHECK reversal amount","OK")),IF(AND(D254="Adjustment",K254<>"",COUNTIF($A$5:$A$3000,J254)=0),"CHECK correction link","OK"))))) -> OK | R254: =INT(C254) -> 46303
A255: WTX-00251 | B255: U007 | C255: 46303.599 | D255: Reward Credit | E255: 100 | F255: Points | G255: Posted | H255: Campaign Bonus | I255: CMP-001 | L255: =IFERROR(INDEX(Transaction_Types!$B$5:$B$20,MATCH(D255,Transaction_Types!$A$5:$A$20,0)),"Not in catalogue") -> Supported | M255: =IFERROR(INDEX(Transaction_Types!$C$5:$C$20,MATCH(D255,Transaction_Types!$A$5:$A$20,0)),"") -> Credit | N255: =IF(G255="Posted",E255,0) -> 100 | O255: =COUNTIFS($J$5:$J$3000,A255,$K$5:$K$3000,"Reverses") -> 0 | P255: =IF(K255<>"","",IF(G255="Posted",E255+SUMIFS($N$5:$N$3000,$J$5:$J$3000,A255),0)) -> 100 | Q255: =IF(L255="Not in catalogue","CHECK type",IF(F255<>Settings!$B$6,"CHECK unit",IF(OR(AND(M255="Credit",E255<=0),AND(M255="Debit",E255>=0)),"CHECK sign",IF(D255="Reversal",IF(OR(J255="",COUNTIF($A$5:$A$3000,J255)=0),"CHECK reversal link",IF(E255<>-INDEX($E$5:$E$3000,MATCH(J255,$A$5:$A$3000,0)),"CHECK reversal amount","OK")),IF(AND(D255="Adjustment",K255<>"",COUNTIF($A$5:$A$3000,J255)=0),"CHECK correction link","OK"))))) -> OK | R255: =INT(C255) -> 46303
A256: WTX-00252 | B256: U008 | C256: 46303.644 | D256: Reward Credit | E256: 300 | F256: Points | G256: Posted | H256: Campaign Bonus | I256: CMP-001 | L256: =IFERROR(INDEX(Transaction_Types!$B$5:$B$20,MATCH(D256,Transaction_Types!$A$5:$A$20,0)),"Not in catalogue") -> Supported | M256: =IFERROR(INDEX(Transaction_Types!$C$5:$C$20,MATCH(D256,Transaction_Types!$A$5:$A$20,0)),"") -> Credit | N256: =IF(G256="Posted",E256,0) -> 300 | O256: =COUNTIFS($J$5:$J$3000,A256,$K$5:$K$3000,"Reverses") -> 0 | P256: =IF(K256<>"","",IF(G256="Posted",E256+SUMIFS($N$5:$N$3000,$J$5:$J$3000,A256),0)) -> 300 | Q256: =IF(L256="Not in catalogue","CHECK type",IF(F256<>Settings!$B$6,"CHECK unit",IF(OR(AND(M256="Credit",E256<=0),AND(M256="Debit",E256>=0)),"CHECK sign",IF(D256="Reversal",IF(OR(J256="",COUNTIF($A$5:$A$3000,J256)=0),"CHECK reversal link",IF(E256<>-INDEX($E$5:$E$3000,MATCH(J256,$A$5:$A$3000,0)),"CHECK reversal amount","OK")),IF(AND(D256="Adjustment",K256<>"",COUNTIF($A$5:$A$3000,J256)=0),"CHECK correction link","OK"))))) -> OK | R256: =INT(C256) -> 46303
A257: WTX-00253 | B257: U007 | C257: 46303.965 | D257: Reward Credit | E257: 400 | F257: Points | G257: Posted | H257: Task Reward | I257: TASK-1090 | L257: =IFERROR(INDEX(Transaction_Types!$B$5:$B$20,MATCH(D257,Transaction_Types!$A$5:$A$20,0)),"Not in catalogue") -> Supported | M257: =IFERROR(INDEX(Transaction_Types!$C$5:$C$20,MATCH(D257,Transaction_Types!$A$5:$A$20,0)),"") -> Credit | N257: =IF(G257="Posted",E257,0) -> 400 | O257: =COUNTIFS($J$5:$J$3000,A257,$K$5:$K$3000,"Reverses") -> 0 | P257: =IF(K257<>"","",IF(G257="Posted",E257+SUMIFS($N$5:$N$3000,$J$5:$J$3000,A257),0)) -> 400 | Q257: =IF(L257="Not in catalogue","CHECK type",IF(F257<>Settings!$B$6,"CHECK unit",IF(OR(AND(M257="Credit",E257<=0),AND(M257="Debit",E257>=0)),"CHECK sign",IF(D257="Reversal",IF(OR(J257="",COUNTIF($A$5:$A$3000,J257)=0),"CHECK reversal link",IF(E257<>-INDEX($E$5:$E$3000,MATCH(J257,$A$5:$A$3000,0)),"CHECK reversal amount","OK")),IF(AND(D257="Adjustment",K257<>"",COUNTIF($A$5:$A$3000,J257)=0),"CHECK correction link","OK"))))) -> OK | R257: =INT(C257) -> 46303
A258: WTX-00254 | B258: U014 | C258: 46303.999 | D258: Reward Credit | E258: 100 | F258: Points | G258: Posted | H258: Referral Reward | I258: REF-0053 | L258: =IFERROR(INDEX(Transaction_Types!$B$5:$B$20,MATCH(D258,Transaction_Types!$A$5:$A$20,0)),"Not in catalogue") -> Supported | M258: =IFERROR(INDEX(Transaction_Types!$C$5:$C$20,MATCH(D258,Transaction_Types!$A$5:$A$20,0)),"") -> Credit | N258: =IF(G258="Posted",E258,0) -> 100 | O258: =COUNTIFS($J$5:$J$3000,A258,$K$5:$K$3000,"Reverses") -> 0 | P258: =IF(K258<>"","",IF(G258="Posted",E258+SUMIFS($N$5:$N$3000,$J$5:$J$3000,A258),0)) -> 100 | Q258: =IF(L258="Not in catalogue","CHECK type",IF(F258<>Settings!$B$6,"CHECK unit",IF(OR(AND(M258="Credit",E258<=0),AND(M258="Debit",E258>=0)),"CHECK sign",IF(D258="Reversal",IF(OR(J258="",COUNTIF($A$5:$A$3000,J258)=0),"CHECK reversal link",IF(E258<>-INDEX($E$5:$E$3000,MATCH(J258,$A$5:$A$3000,0)),"CHECK reversal amount","OK")),IF(AND(D258="Adjustment",K258<>"",COUNTIF($A$5:$A$3000,J258)=0),"CHECK correction link","OK"))))) -> OK | R258: =INT(C258) -> 46303
A259: WTX-00255 | B259: U015 | C259: 46304.039 | D259: Reward Credit | E259: 100 | F259: Points | G259: Posted | H259: Task Reward | I259: TASK-1171 | L259: =IFERROR(INDEX(Transaction_Types!$B$5:$B$20,MATCH(D259,Transaction_Types!$A$5:$A$20,0)),"Not in catalogue") -> Supported | M259: =IFERROR(INDEX(Transaction_Types!$C$5:$C$20,MATCH(D259,Transaction_Types!$A$5:$A$20,0)),"") -> Credit | N259: =IF(G259="Posted",E259,0) -> 100 | O259: =COUNTIFS($J$5:$J$3000,A259,$K$5:$K$3000,"Reverses") -> 0 | P259: =IF(K259<>"","",IF(G259="Posted",E259+SUMIFS($N$5:$N$3000,$J$5:$J$3000,A259),0)) -> 100 | Q259: =IF(L259="Not in catalogue","CHECK type",IF(F259<>Settings!$B$6,"CHECK unit",IF(OR(AND(M259="Credit",E259<=0),AND(M259="Debit",E259>=0)),"CHECK sign",IF(D259="Reversal",IF(OR(J259="",COUNTIF($A$5:$A$3000,J259)=0),"CHECK reversal link",IF(E259<>-INDEX($E$5:$E$3000,MATCH(J259,$A$5:$A$3000,0)),"CHECK reversal amount","OK")),IF(AND(D259="Adjustment",K259<>"",COUNTIF($A$5:$A$3000,J259)=0),"CHECK correction link","OK"))))) -> OK | R259: =INT(C259) -> 46304
A260: WTX-00256 | B260: U012 | C260: 46304.092 | D260: Reward Credit | E260: 100 | F260: Points | G260: Posted | H260: Task Reward | I260: TASK-1146 | L260: =IFERROR(INDEX(Transaction_Types!$B$5:$B$20,MATCH(D260,Transaction_Types!$A$5:$A$20,0)),"Not in catalogue") -> Supported | M260: =IFERROR(INDEX(Transaction_Types!$C$5:$C$20,MATCH(D260,Transaction_Types!$A$5:$A$20,0)),"") -> Credit | N260: =IF(G260="Posted",E260,0) -> 100 | O260: =COUNTIFS($J$5:$J$3000,A260,$K$5:$K$3000,"Reverses") -> 0 | P260: =IF(K260<>"","",IF(G260="Posted",E260+SUMIFS($N$5:$N$3000,$J$5:$J$3000,A260),0)) -> 100 | Q260: =IF(L260="Not in catalogue","CHECK type",IF(F260<>Settings!$B$6,"CHECK unit",IF(OR(AND(M260="Credit",E260<=0),AND(M260="Debit",E260>=0)),"CHECK sign",IF(D260="Reversal",IF(OR(J260="",COUNTIF($A$5:$A$3000,J260)=0),"CHECK reversal link",IF(E260<>-INDEX($E$5:$E$3000,MATCH(J260,$A$5:$A$3000,0)),"CHECK reversal amount","OK")),IF(AND(D260="Adjustment",K260<>"",COUNTIF($A$5:$A$3000,J260)=0),"CHECK correction link","OK"))))) -> OK | R260: =INT(C260) -> 46304
A261: WTX-00257 | B261: U017 | C261: 46304.188 | D261: Reward Credit | E261: 150 | F261: Points | G261: Posted | H261: Task Reward | I261: TASK-1202 | L261: =IFERROR(INDEX(Transaction_Types!$B$5:$B$20,MATCH(D261,Transaction_Types!$A$5:$A$20,0)),"Not in catalogue") -> Supported | M261: =IFERROR(INDEX(Transaction_Types!$C$5:$C$20,MATCH(D261,Transaction_Types!$A$5:$A$20,0)),"") -> Credit | N261: =IF(G261="Posted",E261,0) -> 150 | O261: =COUNTIFS($J$5:$J$3000,A261,$K$5:$K$3000,"Reverses") -> 0 | P261: =IF(K261<>"","",IF(G261="Posted",E261+SUMIFS($N$5:$N$3000,$J$5:$J$3000,A261),0)) -> 150 | Q261: =IF(L261="Not in catalogue","CHECK type",IF(F261<>Settings!$B$6,"CHECK unit",IF(OR(AND(M261="Credit",E261<=0),AND(M261="Debit",E261>=0)),"CHECK sign",IF(D261="Reversal",IF(OR(J261="",COUNTIF($A$5:$A$3000,J261)=0),"CHECK reversal link",IF(E261<>-INDEX($E$5:$E$3000,MATCH(J261,$A$5:$A$3000,0)),"CHECK reversal amount","OK")),IF(AND(D261="Adjustment",K261<>"",COUNTIF($A$5:$A$3000,J261)=0),"CHECK correction link","OK"))))) -> OK | R261: =INT(C261) -> 46304
A262: WTX-00258 | B262: U009 | C262: 46304.229 | D262: Reward Credit | E262: 250 | F262: Points | G262: Posted | H262: Task Reward | I262: TASK-1107 | L262: =IFERROR(INDEX(Transaction_Types!$B$5:$B$20,MATCH(D262,Transaction_Types!$A$5:$A$20,0)),"Not in catalogue") -> Supported | M262: =IFERROR(INDEX(Transaction_Types!$C$5:$C$20,MATCH(D262,Transaction_Types!$A$5:$A$20,0)),"") -> Credit | N262: =IF(G262="Posted",E262,0) -> 250 | O262: =COUNTIFS($J$5:$J$3000,A262,$K$5:$K$3000,"Reverses") -> 0 | P262: =IF(K262<>"","",IF(G262="Posted",E262+SUMIFS($N$5:$N$3000,$J$5:$J$3000,A262),0)) -> 250 | Q262: =IF(L262="Not in catalogue","CHECK type",IF(F262<>Settings!$B$6,"CHECK unit",IF(OR(AND(M262="Credit",E262<=0),AND(M262="Debit",E262>=0)),"CHECK sign",IF(D262="Reversal",IF(OR(J262="",COUNTIF($A$5:$A$3000,J262)=0),"CHECK reversal link",IF(E262<>-INDEX($E$5:$E$3000,MATCH(J262,$A$5:$A$3000,0)),"CHECK reversal amount","OK")),IF(AND(D262="Adjustment",K262<>"",COUNTIF($A$5:$A$3000,J262)=0),"CHECK correction link","OK"))))) -> OK | R262: =INT(C262) -> 46304
A263: WTX-00259 | B263: U013 | C263: 46304.287 | D263: Reward Credit | E263: 300 | F263: Points | G263: Posted | H263: Task Reward | I263: TASK-1148 | L263: =IFERROR(INDEX(Transaction_Types!$B$5:$B$20,MATCH(D263,Transaction_Types!$A$5:$A$20,0)),"Not in catalogue") -> Supported | M263: =IFERROR(INDEX(Transaction_Types!$C$5:$C$20,MATCH(D263,Transaction_Types!$A$5:$A$20,0)),"") -> Credit | N263: =IF(G263="Posted",E263,0) -> 300 | O263: =COUNTIFS($J$5:$J$3000,A263,$K$5:$K$3000,"Reverses") -> 0 | P263: =IF(K263<>"","",IF(G263="Posted",E263+SUMIFS($N$5:$N$3000,$J$5:$J$3000,A263),0)) -> 300 | Q263: =IF(L263="Not in catalogue","CHECK type",IF(F263<>Settings!$B$6,"CHECK unit",IF(OR(AND(M263="Credit",E263<=0),AND(M263="Debit",E263>=0)),"CHECK sign",IF(D263="Reversal",IF(OR(J263="",COUNTIF($A$5:$A$3000,J263)=0),"CHECK reversal link",IF(E263<>-INDEX($E$5:$E$3000,MATCH(J263,$A$5:$A$3000,0)),"CHECK reversal amount","OK")),IF(AND(D263="Adjustment",K263<>"",COUNTIF($A$5:$A$3000,J263)=0),"CHECK correction link","OK"))))) -> OK | R263: =INT(C263) -> 46304
A264: WTX-00260 | B264: U019 | C264: 46304.624 | D264: Reward Credit | E264: 100 | F264: Points | G264: Posted | H264: Referral Reward | I264: REF-0009 | L264: =IFERROR(INDEX(Transaction_Types!$B$5:$B$20,MATCH(D264,Transaction_Types!$A$5:$A$20,0)),"Not in catalogue") -> Supported | M264: =IFERROR(INDEX(Transaction_Types!$C$5:$C$20,MATCH(D264,Transaction_Types!$A$5:$A$20,0)),"") -> Credit | N264: =IF(G264="Posted",E264,0) -> 100 | O264: =COUNTIFS($J$5:$J$3000,A264,$K$5:$K$3000,"Reverses") -> 0 | P264: =IF(K264<>"","",IF(G264="Posted",E264+SUMIFS($N$5:$N$3000,$J$5:$J$3000,A264),0)) -> 100 | Q264: =IF(L264="Not in catalogue","CHECK type",IF(F264<>Settings!$B$6,"CHECK unit",IF(OR(AND(M264="Credit",E264<=0),AND(M264="Debit",E264>=0)),"CHECK sign",IF(D264="Reversal",IF(OR(J264="",COUNTIF($A$5:$A$3000,J264)=0),"CHECK reversal link",IF(E264<>-INDEX($E$5:$E$3000,MATCH(J264,$A$5:$A$3000,0)),"CHECK reversal amount","OK")),IF(AND(D264="Adjustment",K264<>"",COUNTIF($A$5:$A$3000,J264)=0),"CHECK correction link","OK"))))) -> OK | R264: =INT(C264) -> 46304
... A293: WTX-00289 | B293: U004 | C293: 46310.48 | D293: Redemption | E293: -950 | F293: Points | G293: Posted | H293: Withdrawal | I293: WD-0041 | L293: =IFERROR(INDEX(Transaction_Types!$B$5:$B$20,MATCH(D293,Transaction_Types!$A$5:$A$20,0)),"Not in catalogue") -> Supported | M293: =IFERROR(INDEX(Transaction_Types!$C$5:$C$20,MATCH(D293,Transaction_Types!$A$5:$A$20,0)),"") -> Debit | N293: =IF(G293="Posted",E293,0) -> -950 | O293: =COUNTIFS($J$5:$J$3000,A293,$K$5:$K$3000,"Reverses") -> 0 | P293: =IF(K293<>"","",IF(G293="Posted",E293+SUMIFS($N$5:$N$3000,$J$5:$J$3000,A293),0)) -> -950 | Q293: =IF(L293="Not in catalogue","CHECK type",IF(F293<>Settings!$B$6,"CHECK unit",IF(OR(AND(M293="Credit",E293<=0),AND(M293="Debit",E293>=0)),"CHECK sign",IF(D293="Reversal",IF(OR(J293="",COUNTIF($A$5:$A$3000,J293)=0),"CHECK reversal link",IF(E293<>-INDEX($E$5:$E$3000,MATCH(J293,$A$5:$A$3000,0)),"CHECK reversal amount","OK")),IF(AND(D293="Adjustment",K293<>"",COUNTIF($A$5:$A$3000,J293)=0),"CHECK correction link","OK"))))) -> OK | R293: =INT(C293) -> 46310

Sheet Wallet_Balances
A1: Wallet Balances by User (Posted transactions only)
A2: All formulas. Add a user ID in column A and copy the row down. A negative balance means the ledger is inconsistent.
A4: User ID | B4: Reward Credits | C4: Redemptions | D4: Reversals | E4: Adjustments | F4: Other Types | G4: Wallet Balance | H4: Pending Withdrawal Amount | I4: Withdrawal Requests | J4: Balance Flag
A5: U001 | B5: =SUMIFS(Wallet_Transactions!$N$5:$N$3000,Wallet_Transactions!$B$5:$B$3000,$A5,Wallet_Transactions!$D$5:$D$3000,"Reward Credit") -> 2200 | C5: =SUMIFS(Wallet_Transactions!$N$5:$N$3000,Wallet_Transactions!$B$5:$B$3000,$A5,Wallet_Transactions!$D$5:$D$3000,"Redemption") -> -650 | D5: =SUMIFS(Wallet_Transactions!$N$5:$N$3000,Wallet_Transactions!$B$5:$B$3000,$A5,Wallet_Transactions!$D$5:$D$3000,"Reversal") -> -150 | E5: =SUMIFS(Wallet_Transactions!$N$5:$N$3000,Wallet_Transactions!$B$5:$B$3000,$A5,Wallet_Transactions!$D$5:$D$3000,"Adjustment") -> 0 | F5: =G5-SUM(B5:E5) -> 0 | G5: =SUMIFS(Wallet_Transactions!$N$5:$N$3000,Wallet_Transactions!$B$5:$B$3000,$A5) -> 1400 | H5: =SUMIFS(Withdrawals!$C$5:$C$1000,Withdrawals!$B$5:$B$1000,$A5,Withdrawals!$L$5:$L$1000,1,Withdrawals!$D$5:$D$1000,Settings!$B$6) -> 1150 | I5: =COUNTIF(Withdrawals!$B$5:$B$1000,$A5) -> 2 | J5: =IF(G5<0,"NEGATIVE",IF(H5>G5,"Pending > balance","OK")) -> OK
A6: U002 | B6: =SUMIFS(Wallet_Transactions!$N$5:$N$3000,Wallet_Transactions!$B$5:$B$3000,$A6,Wallet_Transactions!$D$5:$D$3000,"Reward Credit") -> 3850 | C6: =SUMIFS(Wallet_Transactions!$N$5:$N$3000,Wallet_Transactions!$B$5:$B$3000,$A6,Wallet_Transactions!$D$5:$D$3000,"Redemption") -> -3500 | D6: =SUMIFS(Wallet_Transactions!$N$5:$N$3000,Wallet_Transactions!$B$5:$B$3000,$A6,Wallet_Transactions!$D$5:$D$3000,"Reversal") -> 0 | E6: =SUMIFS(Wallet_Transactions!$N$5:$N$3000,Wallet_Transactions!$B$5:$B$3000,$A6,Wallet_Transactions!$D$5:$D$3000,"Adjustment") -> 0 | F6: =G6-SUM(B6:E6) -> 0 | G6: =SUMIFS(Wallet_Transactions!$N$5:$N$3000,Wallet_Transactions!$B$5:$B$3000,$A6) -> 350 | H6: =SUMIFS(Withdrawals!$C$5:$C$1000,Withdrawals!$B$5:$B$1000,$A6,Withdrawals!$L$5:$L$1000,1,Withdrawals!$D$5:$D$1000,Settings!$B$6) -> 0 | I6: =COUNTIF(Withdrawals!$B$5:$B$1000,$A6) -> 4 | J6: =IF(G6<0,"NEGATIVE",IF(H6>G6,"Pending > balance","OK")) -> OK
A7: U003 | B7: =SUMIFS(Wallet_Transactions!$N$5:$N$3000,Wallet_Transactions!$B$5:$B$3000,$A7,Wallet_Transactions!$D$5:$D$3000,"Reward Credit") -> 3850 | C7: =SUMIFS(Wallet_Transactions!$N$5:$N$3000,Wallet_Transactions!$B$5:$B$3000,$A7,Wallet_Transactions!$D$5:$D$3000,"Redemption") -> -3700 | D7: =SUMIFS(Wallet_Transactions!$N$5:$N$3000,Wallet_Transactions!$B$5:$B$3000,$A7,Wallet_Transactions!$D$5:$D$3000,"Reversal") -> 0 | E7: =SUMIFS(Wallet_Transactions!$N$5:$N$3000,Wallet_Transactions!$B$5:$B$3000,$A7,Wallet_Transactions!$D$5:$D$3000,"Adjustment") -> 0 | F7: =G7-SUM(B7:E7) -> 0 | G7: =SUMIFS(Wallet_Transactions!$N$5:$N$3000,Wallet_Transactions!$B$5:$B$3000,$A7) -> 150 | H7: =SUMIFS(Withdrawals!$C$5:$C$1000,Withdrawals!$B$5:$B$1000,$A7,Withdrawals!$L$5:$L$1000,1,Withdrawals!$D$5:$D$1000,Settings!$B$6) -> 0 | I7: =COUNTIF(Withdrawals!$B$5:$B$1000,$A7) -> 4 | J7: =IF(G7<0,"NEGATIVE",IF(H7>G7,"Pending > balance","OK")) -> OK
A8: U004 | B8: =SUMIFS(Wallet_Transactions!$N$5:$N$3000,Wallet_Transactions!$B$5:$B$3000,$A8,Wallet_Transactions!$D$5:$D$3000,"Reward Credit") -> 2150 | C8: =SUMIFS(Wallet_Transactions!$N$5:$N$3000,Wallet_Transactions!$B$5:$B$3000,$A8,Wallet_Transactions!$D$5:$D$3000,"Redemption") -> -2000 | D8: =SUMIFS(Wallet_Transactions!$N$5:$N$3000,Wallet_Transactions!$B$5:$B$3000,$A8,Wallet_Transactions!$D$5:$D$3000,"Reversal") -> 0 | E8: =SUMIFS(Wallet_Transactions!$N$5:$N$3000,Wallet_Transactions!$B$5:$B$3000,$A8,Wallet_Transactions!$D$5:$D$3000,"Adjustment") -> 50 | F8: =G8-SUM(B8:E8) -> 0 | G8: =SUMIFS(Wallet_Transactions!$N$5:$N$3000,Wallet_Transactions!$B$5:$B$3000,$A8) -> 200 | H8: =SUMIFS(Withdrawals!$C$5:$C$1000,Withdrawals!$B$5:$B$1000,$A8,Withdrawals!$L$5:$L$1000,1,Withdrawals!$D$5:$D$1000,Settings!$B$6) -> 0 | I8: =COUNTIF(Withdrawals!$B$5:$B$1000,$A8) -> 3 | J8: =IF(G8<0,"NEGATIVE",IF(H8>G8,"Pending > balance","OK")) -> OK
A9: U005 | B9: =SUMIFS(Wallet_Transactions!$N$5:$N$3000,Wallet_Transactions!$B$5:$B$3000,$A9,Wallet_Transactions!$D$5:$D$3000,"Reward Credit") -> 4350 | C9: =SUMIFS(Wallet_Transactions!$N$5:$N$3000,Wallet_Transactions!$B$5:$B$3000,$A9,Wallet_Transactions!$D$5:$D$3000,"Redemption") -> 0 | D9: =SUMIFS(Wallet_Transactions!$N$5:$N$3000,Wallet_Transactions!$B$5:$B$3000,$A9,Wallet_Transactions!$D$5:$D$3000,"Reversal") -> 0 | E9: =SUMIFS(Wallet_Transactions!$N$5:$N$3000,Wallet_Transactions!$B$5:$B$3000,$A9,Wallet_Transactions!$D$5:$D$3000,"Adjustment") -> 0 | F9: =G9-SUM(B9:E9) -> 0 | G9: =SUMIFS(Wallet_Transactions!$N$5:$N$3000,Wallet_Transactions!$B$5:$B$3000,$A9) -> 4350 | H9: =SUMIFS(Withdrawals!$C$5:$C$1000,Withdrawals!$B$5:$B$1000,$A9,Withdrawals!$L$5:$L$1000,1,Withdrawals!$D$5:$D$1000,Settings!$B$6) -> 0 | I9: =COUNTIF(Withdrawals!$B$5:$B$1000,$A9) -> 0 | J9: =IF(G9<0,"NEGATIVE",IF(H9>G9,"Pending > balance","OK")) -> OK
A10: U006 | B10: =SUMIFS(Wallet_Transactions!$N$5:$N$3000,Wallet_Transactions!$B$5:$B$3000,$A10,Wallet_Transactions!$D$5:$D$3000,"Reward Credit") -> 3600 | C10: =SUMIFS(Wallet_Transactions!$N$5:$N$3000,Wallet_Transactions!$B$5:$B$3000,$A10,Wallet_Transactions!$D$5:$D$3000,"Redemption") -> -1100 | D10: =SUMIFS(Wallet_Transactions!$N$5:$N$3000,Wallet_Transactions!$B$5:$B$3000,$A10,Wallet_Transactions!$D$5:$D$3000,"Reversal") -> 0 | E10: =SUMIFS(Wallet_Transactions!$N$5:$N$3000,Wallet_Transactions!$B$5:$B$3000,$A10,Wallet_Transactions!$D$5:$D$3000,"Adjustment") -> 0 | F10: =G10-SUM(B10:E10) -> 0 | G10: =SUMIFS(Wallet_Transactions!$N$5:$N$3000,Wallet_Transactions!$B$5:$B$3000,$A10) -> 2500 | H10: =SUMIFS(Withdrawals!$C$5:$C$1000,Withdrawals!$B$5:$B$1000,$A10,Withdrawals!$L$5:$L$1000,1,Withdrawals!$D$5:$D$1000,Settings!$B$6) -> 0 | I10: =COUNTIF(Withdrawals!$B$5:$B$1000,$A10) -> 1 | J10: =IF(G10<0,"NEGATIVE",IF(H10>G10,"Pending > balance","OK")) -> OK
